Workbook

Sheet 前台好评提成录入
B1: 前台好评提成明细
B2: 酒店名称：
A3: 序号 | B3: 人员姓名 | C3: 平台 | D3: 单位 | E3: 单价（根据实际情况填写） | G3: 金额 | H3: 1号 | I3: 2号 | J3: 3号 | K3: 4号 | L3: 5号 | M3: 6号 | N3: 7号 | O3: 8号 | P3: 9号 | Q3: 10号 | R3: 11号 | S3: 12号 | T3: 13号 | U3: 14号 | V3: 15号 | W3: 16号 | X3: 17号 | Y3: 18号 | Z3: 19号 | AA3: 20号 | AB3: 21号 | AC3: 22号 | AD3: 23号 | AE3: 24号 | AF3: 25号 | AG3: 26号 | AH3: 27号 | AI3: 28号 | AJ3: 29号 | AK3: 30号 | AL3: 31号
F4: 好评数 | H4: 好评数 | I4: 好评数 | J4: 好评数 | K4: 好评数 | L4: 好评数 | M4: 好评数 | N4: 好评数 | O4: 好评数 | P4: 好评数 | Q4: 好评数 | R4: 好评数 | S4: 好评数 | T4: 好评数 | U4: 好评数 | V4: 好评数 | W4: 好评数 | X4: 好评数 | Y4: 好评数 | Z4: 好评数 | AA4: 好评数 | AB4: 好评数 | AC4: 好评数 | AD4: 好评数 | AE4: 好评数 | AF4: 好评数 | AG4: 好评数 | AH4: 好评数 | AI4: 好评数 | AJ4: 好评数 | AK4: 好评数 | AL4: 好评数
A5: 1 | B5: 张馨月 | C5: 携程 | D5: 条 | E5: 6 | F5: =SUMIF($H$4:$AL$4,$F$4,$H5:$AL5) -> 65 | G5: =+E5*F5 -> 390 | H5: 65
A6: 2 | B6: 张馨月 | C6: 携程优质 | D6: 条 | E6: 15 | F6: =SUMIF($H$4:$AL$4,$F$4,$H6:$AL6) -> 32 | G6: =F6*E6 -> 480 | H6: 32
A7: 3 | B7: 张馨月 | C7: 黑/金优质 | D7: 条 | E7: 30 | F7: =SUMIF($H$4:$AL$4,$F$4,$H7:$AL7) -> 0 | G7: =F7*E7 -> 0
A8: 4 | B8: 张馨月 | C8: 去哪儿 | D8: 条 | E8: 6 | F8: =SUMIF($H$4:$AL$4,$F$4,$H8:$AL8) -> 0 | G8: =+E8*F8 -> 0
A9: 5 | B9: 张馨月 | C9: 同程 | D9: 条 | E9: 6 | F9: =SUMIF($H$4:$AL$4,$F$4,$H9:$AL9) -> 0 | G9: =+E9*F9 -> 0
A10: 6 | B10: 张馨月 | C10: 智行 | D10: 条 | E10: 6 | F10: =SUMIF($H$4:$AL$4,$F$4,$H10:$AL10) -> 0 | G10: =+E10*F10 -> 0
A11: 7 | B11: 张馨月 | C11: 抖音 | D11: 条 | E11: 6 | F11: =SUMIF($H$4:$AL$4,$F$4,$H11:$AL11) -> 0 | G11: =+E11*F11 -> 0
A12: 8 | B12: 张馨月 | C12: 美团 | D12: 条 | E12: 6 | F12: =SUMIF($H$4:$AL$4,$F$4,$H12:$AL12) -> 1 | G12: =+E12*F12 -> 6 | H12: 1
A13: 9 | B13: 张馨月 | C13: 飞猪 | D13: 条 | E13: 6 | F13: =SUMIF($H$4:$AL$4,$F$4,$H13:$AL13) -> 0 | G13: =+E13*F13 -> 0
A14: 10 | B14: 张馨月 | C14: 官网 | D14: 条 | E14: 6 | F14: =SUMIF($H$4:$AL$4,$F$4,$H14:$AL14) -> 1 | G14: =F14*E14 -> 6 | H14: 1
A15: 11 | B15: 徐嘉瑜 | C15: 携程 | D15: 条 | E15: 5 | F15: =SUMIF($H$4:$AL$4,$F$4,$H15:$AL15) -> 4 | G15: =+E15*F15 -> 20 | H15: 4
A16: 12 | B16: 徐嘉瑜 | C16: 携程优质 | D16: 条 | E16: 15 | F16: =SUMIF($H$4:$AL$4,$F$4,$H16:$AL16) -> 1 | G16: =F16*E16 -> 15 | H16: 1
A17: 13 | B17: 徐嘉瑜 | C17: 黑/金优质 | D17: 条 | E17: 30 | F17: =SUMIF($H$4:$AL$4,$F$4,$H17:$AL17) -> 0 | G17: =F17*E17 -> 0
A18: 14 | B18: 徐嘉瑜 | C18: 去哪儿 | D18: 条 | E18: 5 | F18: =SUMIF($H$4:$AL$4,$F$4,$H18:$AL18) -> 0 | G18: =+E18*F18 -> 0
A19: 15 | B19: 徐嘉瑜 | C19: 同程 | D19: 条 | E19: 5 | F19: =SUMIF($H$4:$AL$4,$F$4,$H19:$AL19) -> 1 | G19: =+E19*F19 -> 5 | H19: 1
A20: 16 | B20: 徐嘉瑜 | C20: 智行 | D20: 条 | E20: 5 | F20: =SUMIF($H$4:$AL$4,$F$4,$H20:$AL20) -> 0 | G20: =+E20*F20 -> 0
A21: 17 | B21: 徐嘉瑜 | C21: 抖音 | D21: 条 | E21: 5 | F21: =SUMIF($H$4:$AL$4,$F$4,$H21:$AL21) -> 2 | G21: =+E21*F21 -> 10 | H21: 2
A22: 18 | B22: 徐嘉瑜 | C22: 美团 | D22: 条 | E22: 5 | F22: =SUMIF($H$4:$AL$4,$F$4,$H22:$AL22) -> 20 | G22: =+E22*F22 -> 100 | H22: 20
A23: 19 | B23: 徐嘉瑜 | C23: 飞猪 | D23: 条 | E23: 5 | F23: =SUMIF($H$4:$AL$4,$F$4,$H23:$AL23) -> 1 | G23: =+E23*F23 -> 5 | H23: 1
A24: 20 | B24: 徐嘉瑜 | C24: 官网 | D24: 条 | E24: 5 | F24: =SUMIF($H$4:$AL$4,$F$4,$H24:$AL24) -> 7 | G24: =+E24*F24 -> 35 | H24: 7
A25: 21 | B25: 王增 | C25: 携程 | D25: 条 | E25: 5 | F25: =SUMIF($H$4:$AL$4,$F$4,$H25:$AL25) -> 0 | G25: =+E25*F25 -> 0
A26: 22 | B26: 王增 | C26: 携程优质 | D26: 条 | E26: 15 | F26: =SUMIF($H$4:$AL$4,$F$4,$H26:$AL26) -> 2 | G26: =F26*E26 -> 30 | H26: 2
A27: 23 | B27: 王增 | C27: 黑/金优质 | D27: 条 | E27: 30 | F27: =SUMIF($H$4:$AL$4,$F$4,$H27:$AL27) -> 1 | G27: =F27*E27 -> 30 | H27: 1
A28: 24 | B28: 王增 | C28: 去哪儿 | D28: 条 | E28: 5 | F28: =SUMIF($H$4:$AL$4,$F$4,$H28:$AL28) -> 4 | G28: =+E28*F28 -> 20 | H28: 4
A29: 25 | B29: 王增 | C29: 同程 | D29: 条 | E29: 5 | F29: =SUMIF($H$4:$AL$4,$F$4,$H29:$AL29) -> 1 | G29: =+E29*F29 -> 5 | H29: 1
A30: 26 | B30: 王增 | C30: 智行 | D30: 条 | E30: 5 | F30: =SUMIF($H$4:$AL$4,$F$4,$H30:$AL30) -> 0 | G30: =+E30*F30 -> 0
A31: 27 | B31: 王增 | C31: 抖音 | D31: 条 | E31: 5 | F31: =SUMIF($H$4:$AL$4,$F$4,$H31:$AL31) -> 14 | G31: =+E31*F31 -> 70 | H31: 14
A32: 28 | B32: 王增 | C32: 美团 | D32: 条 | E32: 5 | F32: =SUMIF($H$4:$AL$4,$F$4,$H32:$AL32) -> 50 | G32: =+E32*F32 -> 250 | H32: 50
A33: 29 | B33: 王增 | C33: 飞猪 | D33: 条 | E33: 5 | F33: =SUMIF($H$4:$AL$4,$F$4,$H33:$AL33) -> 1 | G33: =+E33*F33 -> 5 | H33: 1
A34: 30 | B34: 王增 | C34: 官网 | D34: 条 | E34: 5 | F34: =SUMIF($H$4:$AL$4,$F$4,$H34:$AL34) -> 26 | G34: =+E34*F34 -> 130 | H34: 26
A35: 31 | B35: 翟芮瑶 | C35: 携程 | D35: 条 | E35: 5 | F35: =SUMIF($H$4:$AL$4,$F$4,$H35:$AL35) -> 2 | G35: =F35*E35 -> 10 | H35: 2
A36: 32 | B36: 翟芮瑶 | C36: 携程优质 | D36: 条 | E36: 15 | F36: =SUMIF($H$4:$AL$4,$F$4,$H36:$AL36) -> 7 | G36: =F36*E36 -> 105 | H36: 7
A37: 33 | B37: 翟芮瑶 | C37: 黑/金优质 | D37: 条 | E37: 30 | F37: =SUMIF($H$4:$AL$4,$F$4,$H37:$AL37) -> 2 | G37: =F37*E37 -> 60 | H37: 2
A38: 34 | B38: 翟芮瑶 | C38: 去哪儿 | D38: 条 | E38: 5 | F38: =SUMIF($H$4:$AL$4,$F$4,$H38:$AL38) -> 3 | G38: =F38*E38 -> 15 | H38: 3
A39: 35 | B39: 翟芮瑶 | C39: 同程 | D39: 条 | E39: 5 | F39: =SUMIF($H$4:$AL$4,$F$4,$H39:$AL39) -> 0 | G39: =F39*E39 -> 0
A40: 36 | B40: 翟芮瑶 | C40: 智行 | D40: 条 | E40: 5 | F40: =SUMIF($H$4:$AL$4,$F$4,$H40:$AL40) -> 0 | G40: =F40*E40 -> 0
A41: 37 | B41: 翟芮瑶 | C41: 抖音 | D41: 条 | E41: 5 | F41: =SUMIF($H$4:$AL$4,$F$4,$H41:$AL41) -> 13 | G41: =F41*E41 -> 65 | H41: 13
A42: 38 | B42: 翟芮瑶 | C42: 美团 | D42: 条 | E42: 5 | F42: =SUMIF($H$4:$AL$4,$F$4,$H42:$AL42) -> 57 | G42: =F42*E42 -> 285 | H42: 57
A43: 39 | B43: 翟芮瑶 | C43: 飞猪 | D43: 条 | E43: 5 | F43: =SUMIF($H$4:$AL$4,$F$4,$H43:$AL43) -> 7 | G43: =F43*E43 -> 35 | H43: 7
A44: 40 | B44: 翟芮瑶 | C44: 官网 | D44: 条 | E44: 5 | F44: =SUMIF($H$4:$AL$4,$F$4,$H44:$AL44) -> 23 | G44: =F44*E44 -> 115 | H44: 23
A45: 41 | B45: 孙源 | C45: 携程 | D45: 条 | E45: 5 | F45: =SUMIF($H$4:$AL$4,$F$4,$H45:$AL45) -> 0 | G45: =F45*E45 -> 0
A46: 42 | B46: 孙源 | C46: 携程优质 | D46: 条 | E46: 15 | F46: =SUMIF($H$4:$AL$4,$F$4,$H46:$AL46) -> 0 | G46: =F46*E46 -> 0
A47: 43 | B47: 孙源 | C47: 黑/金优质 | D47: 条 | E47: 30 | F47: =SUMIF($H$4:$AL$4,$F$4,$H47:$AL47) -> 0 | G47: =F47*E47 -> 0
A48: 44 | B48: 孙源 | C48: 去哪儿 | D48: 条 | E48: 5 | F48: =SUMIF($H$4:$AL$4,$F$4,$H48:$AL48) -> 0 | G48: =F48*E48 -> 0
A49: 45 | B49: 孙源 | C49: 同程 | D49: 条 | E49: 5 | F49: =SUMIF($H$4:$AL$4,$F$4,$H49:$AL49) -> 0 | G49: =F49*E49 -> 0
A50: 46 | B50: 孙源 | C50: 智行 | D50: 条 | E50: 5 | F50: =SUMIF($H$4:$AL$4,$F$4,$H50:$AL50) -> 0 | G50: =F50*E50 -> 0
A51: 47 | B51: 孙源 | C51: 抖音 | D51: 条 | E51: 5 | F51: =SUMIF($H$4:$AL$4,$F$4,$H51:$AL51) -> 0 | G51: =F51*E51 -> 0
A52: 48 | B52: 孙源 | C52: 美团 | D52: 条 | E52: 5 | F52: =SUMIF($H$4:$AL$4,$F$4,$H52:$AL52) -> 0 | G52: =F52*E52 -> 0
A53: 49 | B53: 孙源 | C53: 飞猪 | D53: 条 | E53: 5 | F53: =SUMIF($H$4:$AL$4,$F$4,$H53:$AL53) -> 0 | G53: =F53*E53 -> 0
A54: 50 | B54: 孙源 | C54: 官网 | D54: 条 | E54: 5 | F54: =SUMIF($H$4:$AL$4,$F$4,$H54:$AL54) -> 0 | G54: =F54*E54 -> 0
A55: 51 | B55: 宋雨霏 | C55: 携程 | D55: 条 | E55: 5 | F55: =SUMIF($H$4:$AL$4,$F$4,$H55:$AL55) -> 0 | G55: =F55*E55 -> 0
A56: 52 | B56: 宋雨霏 | C56: 携程优质 | D56: 条 | E56: 15 | F56: =SUMIF($H$4:$AL$4,$F$4,$H56:$AL56) -> 0 | G56: -
A57: 53 | B57: 宋雨霏 | C57: 黑/金优质 | D57: 条 | E57: 30 | F57: =SUMIF($H$4:$AL$4,$F$4,$H57:$AL57) -> 0 | G57: -
A58: 54 | B58: 宋雨霏 | C58: 去哪儿 | D58: 条 | E58: 5 | F58: =SUMIF($H$4:$AL$4,$F$4,$H58:$AL58) -> 0 | G58: =F58*E58 -> 0
A59: 55 | B59: 宋雨霏 | C59: 同程 | D59: 条 | E59: 5 | F59: =SUMIF($H$4:$AL$4,$F$4,$H59:$AL59) -> 0 | G59: -
A60: 56 | B60: 宋雨霏 | C60: 智行 | D60: 条 | E60: 5 | F60: =SUMIF($H$4:$AL$4,$F$4,$H60:$AL60) -> 0 | G60: -
A61: 57 | B61: 宋雨霏 | C61: 抖音 | D61: 条 | E61: 5 | F61: =SUMIF($H$4:$AL$4,$F$4,$H61:$AL61) -> 0 | G61: -
A62: 58 | B62: 宋雨霏 | C62: 美团 | D62: 条 | E62: 5 | F62: =SUMIF($H$4:$AL$4,$F$4,$H62:$AL62) -> 0 | G62: =F62*5 -> 0
A63: 59 | B63: 宋雨霏 | C63: 飞猪 | D63: 条 | E63: 5 | F63: =SUMIF($H$4:$AL$4,$F$4,$H63:$AL63) -> 0 | G63: -
A64: 60 | B64: 宋雨霏 | C64: 官网 | D64: 条 | E64: 5 | F64: =SUMIF($H$4:$AL$4,$F$4,$H64:$AL64) -> 0 | G64: -
A65: 56 | B65: 李龙梅 | C65: 携程 | D65: 条 | E65: 5 | F65: =SUMIF($H$4:$AL$4,$F$4,$H65:$AL65) -> 3 | G65: =F65*E65 -> 15 | H65: 3
A66: 57 | B66: 李龙梅 | C66: 携程优质 | D66: 条 | E66: 15 | F66: =SUMIF($H$4:$AL$4,$F$4,$H66:$AL66) -> 3 | G66: =F66*E66 -> 45 | H66: 3
A67: 58 | B67: 李龙梅 | C67: 黑/金优质 | D67: 条 | E67: 30 | F67: =SUMIF($H$4:$AL$4,$F$4,$H67:$AL67) -> 1 | G67: =F67*E67 -> 30 | H67: 1
A68: 59 | B68: 李龙梅 | C68: 去哪儿 | D68: 条 | E68: 5 | F68: =SUMIF($H$4:$AL$4,$F$4,$H68:$AL68) -> 0 | G68: =F68*E68 -> 0
A69: 60 | B69: 李龙梅 | C69: 同程 | D69: 条 | E69: 5 | F69: =SUMIF($H$4:$AL$4,$F$4,$H69:$AL69) -> 0 | G69: =F69*E69 -> 0
A70: 61 | B70: 李龙梅 | C70: 智行 | D70: 条 | E70: 5 | F70: =SUMIF($H$4:$AL$4,$F$4,$H70:$AL70) -> 0 | G70: =F70*E70 -> 0
A71: 62 | B71: 李龙梅 | C71: 抖音 | D71: 条 | E71: 5 | F71: =SUMIF($H$4:$AL$4,$F$4,$H71:$AL71) -> 1 | G71: =F71*E71 -> 5 | H71: 1
A72: 63 | B72: 李龙梅 | C72: 美团 | D72: 条 | E72: 5 | F72: =SUMIF($H$4:$AL$4,$F$4,$H72:$AL72) -> 3 | G72: =F72*E72 -> 15 | H72: 3
A73: 64 | B73: 李龙梅 | C73: 飞猪 | D73: 条 | E73: 5 | F73: =SUMIF($H$4:$AL$4,$F$4,$H73:$AL73) -> 1 | G73: =F73*E73 -> 5 | H73: 1
A74: 65 | B74: 李龙梅 | C74: 官网 | D74: 条 | E74: 5 | F74: =SUMIF($H$4:$AL$4,$F$4,$H74:$AL74) -> 0 | G74: =F74*E74 -> 0
A75: 66 | B75: 吴怡 | C75: 携程 | D75: 条 | E75: 5 | F75: =SUMIF($H$4:$AL$4,$F$4,$H75:$AL75) -> 0 | G75: =F75*E75 -> 0
A76: 67 | B76: 吴怡 | C76: 携程优质 | D76: 条 | E76: 15 | F76: =SUMIF($H$4:$AL$4,$F$4,$H76:$AL76) -> 0 | G76: =F76*E76 -> 0
A77: 68 | B77: 吴怡 | C77: 黑/金优质 | D77: 条 | E77: 30 | F77: =SUMIF($H$4:$AL$4,$F$4,$H77:$AL77) -> 0 | G77: =F77*E77 -> 0
A78: 69 | B78: 吴怡 | C78: 去哪儿 | D78: 条 | E78: 5 | F78: =SUMIF($H$4:$AL$4,$F$4,$H78:$AL78) -> 6 | G78: =F78*E78 -> 30 | H78: 6
A79: 70 | B79: 吴怡 | C79: 同程 | D79: 条 | E79: 5 | F79: =SUMIF($H$4:$AL$4,$F$4,$H79:$AL79) -> 4 | G79: =F79*E79 -> 20 | H79: 4
A80: 71 | B80: 吴怡 | C80: 智行 | D80: 条 | E80: 5 | F80: =SUMIF($H$4:$AL$4,$F$4,$H80:$AL80) -> 0 | G80: =F80*E80 -> 0
A81: 72 | B81: 吴怡 | C81: 抖音 | D81: 条 | E81: 5 | F81: =SUMIF($H$4:$AL$4,$F$4,$H81:$AL81) -> 9 | G81: =F81*E81 -> 45 | H81: 9
A82: 73 | B82: 吴怡 | C82: 美团 | D82: 条 | E82: 5 | F82: =SUMIF($H$4:$AL$4,$F$4,$H82:$AL82) -> 49 | G82: =F82*E82 -> 245 | H82: 49
A83: 74 | B83: 吴怡 | C83: 飞猪 | D83: 条 | E83: 5 | F83: =SUMIF($H$4:$AL$4,$F$4,$H83:$AL83) -> 6 | G83: =F83*E83 -> 30 | H83: 6
A84: 75 | B84: 吴怡 | C84: 官网 | D84: 条 | E84: 5 | F84: =SUMIF($H$4:$AL$4,$F$4,$H84:$AL84) -> 0 | G84: =F84*E84 -> 0
A85: 76 | B85: 邹璇 | C85: 携程 | D85: 条 | E85: 5 | F85: =SUMIF($H$4:$AL$4,$F$4,$H85:$AL85) -> 0 | G85: =F85*E85 -> 0
A86: 77 | B86: 邹璇 | C86: 携程优质 | D86: 条 | E86: 15 | F86: =SUMIF($H$4:$AL$4,$F$4,$H86:$AL86) -> 0 | G86: =F86*E86 -> 0
A87: 78 | B87: 邹璇 | C87: 黑/金优质 | D87: 条 | E87: 30 | F87: =SUMIF($H$4:$AL$4,$F$4,$H87:$AL87) -> 0 | G87: =F87*E87 -> 0
A88: 79 | B88: 邹璇 | C88: 去哪儿 | D88: 条 | E88: 5 | F88: =SUMIF($H$4:$AL$4,$F$4,$H88:$AL88) -> 0 | G88: =F88*E88 -> 0
A89: 80 | B89: 邹璇 | C89: 同程 | D89: 条 | E89: 5 | F89: =SUMIF($H$4:$AL$4,$F$4,$H89:$AL89) -> 0 | G89: =F89*E89 -> 0
A90: 81 | B90: 邹璇 | C90: 智行 | D90: 条 | E90: 5 | F90: =SUMIF($H$4:$AL$4,$F$4,$H90:$AL90) -> 0 | G90: =F90*E90 -> 0
A91: 82 | B91: 邹璇 | C91: 抖音 | D91: 条 | E91: 5 | F91: =SUMIF($H$4:$AL$4,$F$4,$H91:$AL91) -> 1 | G91: =F91*E91 -> 5 | H91: 1
A92: 83 | B92: 邹璇 | C92: 美团 | D92: 条 | E92: 5 | F92: =SUMIF($H$4:$AL$4,$F$4,$H92:$AL92) -> 2 | G92: =F92*E92 -> 10 | H92: 2
A93: 84 | B93: 邹璇 | C93: 飞猪 | D93: 条 | E93: 5 | F93: =SUMIF($H$4:$AL$4,$F$4,$H93:$AL93) -> 0 | G93: =F93*E93 -> 0
A94: 85 | B94: 邹璇 | C94: 官网 | D94: 条 | E94: 5 | F94: =SUMIF($H$4:$AL$4,$F$4,$H94:$AL94) -> 0 | G94: =F94*E94 -> 0
A95: 86 | D95: 条 | F95: =SUMIF($H$4:$AL$4,$F$4,$H95:$AL95) -> 0 | G95: =+E95*F95 -> 0
A96: 87 | D96: 条 | F96: =SUMIF($H$4:$AL$4,$F$4,$H96:$AL96) -> 0 | G96: =+E96*F96 -> 0
A97: 88 | D97: 条 | F97: =SUMIF($H$4:$AL$4,$F$4,$H97:$AL97) -> 0 | G97: =+E97*F97 -> 0
A98: 89 | D98: 条 | F98: =SUMIF($H$4:$AL$4,$F$4,$H98:$AL98) -> 0 | G98: =+E98*F98 -> 0
A99: 90 | D99: 条 | F99: =SUMIF($H$4:$AL$4,$F$4,$H99:$AL99) -> 0 | G99: =+E99*F99 -> 0
A100: 91 | D100: 条 | F100: =SUMIF($H$4:$AL$4,$F$4,$H100:$AL100) -> 0 | G100: =+E100*F100 -> 0
...

Sheet 前台二维码提成录入
B1: 前台二维码提成明细
B2: 酒店名称：
A3: 序号 | B3: 人员姓名 | C3: 平台 | D3: 单位 | E3: 单价 | G3: 出库金额 | H3: 1号 | I3: 2号 | J3: 3号 | K3: 4号 | L3: 5号 | M3: 6号 | N3: 7号 | O3: 8号 | P3: 9号 | Q3: 10号 | R3: 11号 | S3: 12号 | T3: 13号 | U3: 14号 | V3: 15号 | W3: 16号 | X3: 17号 | Y3: 18号 | Z3: 19号 | AA3: 20号 | AB3: 21号 | AC3: 22号 | AD3: 23号 | AE3: 24号 | AF3: 25号 | AG3: 26号 | AH3: 27号 | AI3: 28号 | AJ3: 29号 | AK3: 30号 | AL3: 31号
F4: 服务次数 | H4: 服务次数 | I4: 服务次数 | J4: 服务次数 | K4: 服务次数 | L4: 服务次数 | M4: 服务次数 | N4: 服务次数 | O4: 服务次数 | P4: 服务次数 | Q4: 服务次数 | R4: 服务次数 | S4: 服务次数 | T4: 服务次数 | U4: 服务次数 | V4: 服务次数 | W4: 服务次数 | X4: 服务次数 | Y4: 服务次数 | Z4: 服务次数 | AA4: 服务次数 | AB4: 服务次数 | AC4: 服务次数 | AD4: 服务次数 | AE4: 服务次数 | AF4: 服务次数 | AG4: 服务次数 | AH4: 服务次数 | AI4: 服务次数 | AJ4: 服务次数 | AK4: 服务次数 | AL4: 服务次数
A5: 1 | B5: 李龙梅 | C5: 洗衣 | D5: 次 | E5: 1.5 | F5: =SUMIF($H$4:$AL$4,$F$4,$H5:$AL5) -> 3 | G5: =+E5*F5 -> 4.5 | O5: 1 | AE5: 1 | AF5: 1
A6: 2 | B6: 李龙梅 | C6: 送物品 | D6: 次 | E6: 0.5 | F6: =SUMIF($H$4:$AL$4,$F$4,$H6:$AL6) -> 63 | G6: =+E6*F6 -> 31.5 | J6: 11 | K6: 2 | L6: 3 | M6: 3 | O6: 5 | P6: 20 | S6: 2 | AE6: 6 | AG6: 8 | AL6: 3
A7: 3 | B7: 李龙梅 | C7: 点名表扬 | D7: 次 | E7: 1 | F7: =SUMIF($H$4:$AL$4,$F$4,$H7:$AL7) -> 0 | G7: =+E7*F7 -> 0
A8: 4 | B8: 李龙梅 | C8: 违规 | D8: 次 | E8: -2 | F8: =SUMIF($H$4:$AL$4,$F$4,$H8:$AL8) -> 0 | G8: =+E8*F8 -> 0
A9: 5 | B9: 李龙梅 | C9: 其他 | D9: 次 | E9: 2 | F9: =SUMIF($H$4:$AL$4,$F$4,$H9:$AL9) -> 0 | G9: =+E9*F9 -> 0
A10: 6 | B10: 于子杭 | C10: 洗衣 | D10: 次 | E10: 1.5 | F10: =SUMIF($H$4:$AL$4,$F$4,$H10:$AL10) -> 0 | G10: =+E10*F10 -> 0
A11: 7 | B11: 于子杭 | C11: 送物品 | D11: 次 | E11: 0.5 | F11: =SUMIF($H$4:$AL$4,$F$4,$H11:$AL11) -> 67 | G11: =+E11*F11 -> 33.5 | J11: 11 | L11: 3 | M11: 3 | O11: 5 | P11: 20 | R11: 2 | S11: 3 | Z11: 2 | AE11: 6 | AG11: 8 | AK11: 2 | AL11: 2
A12: 8 | B12: 于子杭 | C12: 点名表扬 | D12: 次 | E12: 1 | F12: =SUMIF($H$4:$AL$4,$F$4,$H12:$AL12) -> 0 | G12: =+E12*F12 -> 0
A13: 9 | B13: 于子杭 | C13: 违规 | D13: 次 | E13: -2 | F13: =SUMIF($H$4:$AL$4,$F$4,$H13:$AL13) -> 0 | G13: =+E13*F13 -> 0
A14: 10 | B14: 于子杭 | C14: 其他 | D14: 次 | E14: 2 | F14: =SUMIF($H$4:$AL$4,$F$4,$H14:$AL14) -> 0 | G14: =+E14*F14 -> 0
A15: 11 | B15: 张馨月 | C15: 洗衣 | D15: 次 | E15: 1.5 | F15: =SUMIF($H$4:$AL$4,$F$4,$H15:$AL15) -> 1 | G15: =+E15*F15 -> 1.5 | P15: 1
A16: 12 | B16: 张馨月 | C16: 送物品 | D16: 次 | E16: 0.5 | F16: =SUMIF($H$4:$AL$4,$F$4,$H16:$AL16) -> 70 | G16: =+E16*F16 -> 35 | J16: 11 | K16: 2 | L16: 3 | M16: 3 | O16: 5 | P16: 20 | R16: 2 | S16: 3 | AA16: 3 | AE16: 6 | AG16: 8 | AK16: 2 | AL16: 2
A17: 13 | B17: 张馨月 | C17: 点名表扬 | D17: 次 | E17: 1 | F17: =SUMIF($H$4:$AL$4,$F$4,$H17:$AL17) -> 0 | G17: =+E17*F17 -> 0
A18: 14 | B18: 张馨月 | C18: 违规 | D18: 次 | E18: -2 | F18: =SUMIF($H$4:$AL$4,$F$4,$H18:$AL18) -> 0 | G18: =+E18*F18 -> 0
A19: 15 | B19: 张馨月 | C19: 其他 | D19: 次 | E19: 2 | F19: =SUMIF($H$4:$AL$4,$F$4,$H19:$AL19) -> 0 | G19: =+E19*F19 -> 0
A20: 16 | B20: 王增 | C20: 洗衣 | D20: 次 | E20: 1.5 | F20: =SUMIF($H$4:$AL$4,$F$4,$H20:$AL20) -> 15 | G20: =+E20*F20 -> 22.5 | R20: 4 | S20: 3 | U20: 1 | V20: 2 | X20: 2 | Y20: 1 | AJ20: 1 | AK20: 1
A21: 17 | B21: 王增 | C21: 送物品 | D21: 次 | E21: 0.5 | F21: =SUMIF($H$4:$AL$4,$F$4,$H21:$AL21) -> 121 | G21: =+E21*F21 -> 60.5 | I21: 1 | L21: 12 | M21: 12 | N21: 3 | Q21: 20 | R21: 15 | S21: 10 | X21: 10 | Y21: 11 | AD21: 9 | AE21: 5 | AJ21: 3 | AK21: 10
A22: 18 | B22: 王增 | C22: 点名表扬 | D22: 次 | E22: 1 | F22: =SUMIF($H$4:$AL$4,$F$4,$H22:$AL22) -> 0 | G22: =+E22*F22 -> 0
A23: 19 | B23: 王增 | C23: 违规 | D23: 次 | E23: -2 | F23: =SUMIF($H$4:$AL$4,$F$4,$H23:$AL23) -> 0 | G23: =+E23*F23 -> 0
A24: 20 | B24: 王增 | C24: 其他 | D24: 次 | E24: 2 | F24: =SUMIF($H$4:$AL$4,$F$4,$H24:$AL24) -> 0 | G24: =+E24*F24 -> 0
A25: 21 | B25: 宋雨霏 | C25: 洗衣 | D25: 次 | E25: 1.5 | F25: =SUMIF($H$4:$AL$4,$F$4,$H25:$AL25) -> 6 | G25: =+E25*F25 -> 9 | M25: 1 | S25: 1 | Y25: 2 | AJ25: 1 | AK25: 1
A26: 22 | B26: 宋雨霏 | C26: 送物品 | D26: 次 | E26: 0.5 | F26: =SUMIF($H$4:$AL$4,$F$4,$H26:$AL26) -> 114 | G26: =+E26*F26 -> 57 | L26: 12 | M26: 12 | O26: 2 | Q26: 15 | R26: 15 | S26: 10 | X26: 10 | Y26: 10 | AD26: 9 | AE26: 5 | AJ26: 4 | AK26: 10
A27: 23 | B27: 宋雨霏 | C27: 点名表扬 | D27: 次 | E27: 1 | F27: =SUMIF($H$4:$AL$4,$F$4,$H27:$AL27) -> 0 | G27: =+E27*F27 -> 0
A28: 24 | B28: 宋雨霏 | C28: 违规 | D28: 次 | E28: -2 | F28: =SUMIF($H$4:$AL$4,$F$4,$H28:$AL28) -> 0 | G28: =+E28*F28 -> 0
A29: 25 | B29: 宋雨霏 | C29: 其他 | D29: 次 | E29: 2 | F29: =SUMIF($H$4:$AL$4,$F$4,$H29:$AL29) -> 0 | G29: =+E29*F29 -> 0
A30: 26 | B30: 翟芮瑶 | C30: 洗衣 | D30: 次 | E30: 1.5 | F30: =SUMIF($H$4:$AL$4,$F$4,$H30:$AL30) -> 6 | G30: =+E30*F30 -> 9 | P30: 2 | T30: 1 | V30: 2 | W30: 1
A31: 27 | B31: 翟芮瑶 | C31: 送物品 | D31: 次 | E31: 0.5 | F31: =SUMIF($H$4:$AL$4,$F$4,$H31:$AL31) -> 77 | G31: =+E31*F31 -> 38.5 | J31: 3 | K31: 5 | L31: 1 | P31: 20 | V31: 12 | W31: 4 | AB31: 12 | AH31: 10 | AI31: 10
A32: 28 | B32: 翟芮瑶 | C32: 点名表扬 | D32: 次 | E32: 1 | F32: =SUMIF($H$4:$AL$4,$F$4,$H32:$AL32) -> 0 | G32: =+E32*F32 -> 0
A33: 29 | B33: 翟芮瑶 | C33: 违规 | D33: 次 | E33: -2 | F33: =SUMIF($H$4:$AL$4,$F$4,$H33:$AL33) -> 0 | G33: =+E33*F33 -> 0
A34: 30 | B34: 翟芮瑶 | C34: 其他 | D34: 次 | E34: 2 | F34: =SUMIF($H$4:$AL$4,$F$4,$H34:$AL34) -> 0 | G34: =+E34*F34 -> 0
A35: 31 | B35: 孙源 | C35: 洗衣 | D35: 次 | E35: 1.5 | F35: =SUMIF($H$4:$AL$4,$F$4,$H35:$AL35) -> 8 | G35: =+E35*F35 -> 12 | P35: 1 | V35: 2 | W35: 1 | Y35: 1 | AB35: 1 | AC35: 1 | AI35: 1
A36: 32 | B36: 孙源 | C36: 送物品 | D36: 次 | E36: 0.5 | F36: =SUMIF($H$4:$AL$4,$F$4,$H36:$AL36) -> 77 | G36: =+E36*F36 -> 38.5 | J36: 11 | P36: 20 | V36: 12 | W36: 4 | AB36: 10 | AH36: 10 | AI36: 10
A37: 33 | B37: 孙源 | C37: 点名表扬 | D37: 次 | E37: 1 | F37: =SUMIF($H$4:$AL$4,$F$4,$H37:$AL37) -> 0 | G37: =+E37*F37 -> 0
A38: 34 | B38: 孙源 | C38: 违规 | D38: 次 | E38: -2 | F38: =SUMIF($H$4:$AL$4,$F$4,$H38:$AL38) -> 0 | G38: =+E38*F38 -> 0
A39: 35 | B39: 孙源 | C39: 其他 | D39: 次 | E39: 2 | F39: =SUMIF($H$4:$AL$4,$F$4,$H39:$AL39) -> 0 | G39: =+E39*F39 -> 0
A40: 36 | B40: 吴怡 | C40: 洗衣 | D40: 次 | E40: 1.5 | F40: =SUMIF($H$4:$AL$4,$F$4,$H40:$AL40) -> 5 | G40: =+E40*F40 -> 7.5 | I40: 1 | T40: 1 | U40: 1 | X40: 2
A41: 37 | B41: 吴怡 | C41: 送物品 | D41: 次 | E41: 0.5 | F41: =SUMIF($H$4:$AL$4,$F$4,$H41:$AL41) -> 210 | G41: =+E41*F41 -> 105 | H41: 6 | N41: 4 | O41: 15 | T41: 13 | U41: 10 | Z41: 20 | AA41: 10 | AF41: 14 | AG41: 108 | AL41: 10
A42: 38 | B42: 吴怡 | C42: 点名表扬 | D42: 次 | E42: 1 | F42: =SUMIF($H$4:$AL$4,$F$4,$H42:$AL42) -> 0 | G42: =+E42*F42 -> 0
A43: 39 | B43: 吴怡 | C43: 违规 | D43: 次 | E43: -2 | F43: =SUMIF($H$4:$AL$4,$F$4,$H43:$AL43) -> 0 | G43: =+E43*F43 -> 0
A44: 40 | B44: 吴怡 | C44: 其他 | D44: 次 | E44: 2 | F44: =SUMIF($H$4:$AL$4,$F$4,$H44:$AL44) -> 0 | G44: =+E44*F44 -> 0
A45: 41 | B45: 徐嘉瑜 | C45: 洗衣 | D45: 次 | E45: 1.5 | F45: =SUMIF($H$4:$AL$4,$F$4,$H45:$AL45) -> 9 | G45: =+E45*F45 -> 13.5 | O45: 4 | R45: 1 | U45: 1 | AB45: 1 | AF45: 1 | AG45: 1
A46: 42 | B46: 徐嘉瑜 | C46: 送物品 | D46: 次 | E46: 0.5 | F46: =SUMIF($H$4:$AL$4,$F$4,$H46:$AL46) -> 118 | G46: =+E46*F46 -> 59 | H46: 6 | I46: 1 | N46: 4 | O46: 15 | T46: 13 | U46: 10 | X46: 5 | Z46: 20 | AA46: 10 | AF46: 14 | AG46: 10 | AL46: 10
A47: 43 | B47: 徐嘉瑜 | C47: 点名表扬 | D47: 次 | E47: 1 | F47: =SUMIF($H$4:$AL$4,$F$4,$H47:$AL47) -> 0 | G47: =+E47*F47 -> 0
A48: 44 | B48: 徐嘉瑜 | C48: 违规 | D48: 次 | E48: -2 | F48: =SUMIF($H$4:$AL$4,$F$4,$H48:$AL48) -> 0 | G48: =+E48*F48 -> 0
A49: 45 | B49: 徐嘉瑜 | C49: 其他 | D49: 次 | E49: 2 | F49: =SUMIF($H$4:$AL$4,$F$4,$H49:$AL49) -> 0 | G49: =+E49*F49 -> 0
A50: 46 | B50: 刘昕 | C50: 洗衣 | D50: 次 | E50: 1.5 | F50: =SUMIF($H$4:$AL$4,$F$4,$H50:$AL50) -> 0 | G50: =+E50*F50 -> 0
A51: 47 | B51: 刘昕 | C51: 送物品 | D51: 次 | E51: 0.5 | F51: =SUMIF($H$4:$AL$4,$F$4,$H51:$AL51) -> 7 | G51: =+E51*F51 -> 3.5 | H51: 6 | I51: 1
A52: 48 | B52: 刘昕 | C52: 点名表扬 | D52: 次 | E52: 1 | F52: =SUMIF($H$4:$AL$4,$F$4,$H52:$AL52) -> 0 | G52: =+E52*F52 -> 0
A53: 49 | B53: 刘昕 | C53: 违规 | D53: 次 | E53: -2 | F53: =SUMIF($H$4:$AL$4,$F$4,$H53:$AL53) -> 0 | G53: =+E53*F53 -> 0
A54: 50 | B54: 刘昕 | C54: 其他 | D54: 次 | E54: 2 | F54: =SUMIF($H$4:$AL$4,$F$4,$H54:$AL54) -> 0 | G54: =+E54*F54 -> 0
A55: 51 | B55: 邹璇 | C55: 洗衣 | D55: 次 | E55: 1.5 | F55: =SUMIF($H$4:$AL$4,$F$4,$H55:$AL55) -> 3 | G55: =+E55*F55 -> 4.5 | T55: 1 | AC55: 1 | AH55: 1
A56: 52 | B56: 邹璇 | C56: 送物品 | D56: 次 | E56: 0.5 | F56: =SUMIF($H$4:$AL$4,$F$4,$H56:$AL56) -> 26 | G56: =+E56*F56 -> 13 | AC56: 3 | AH56: 9 | AI56: 14
A57: 53 | B57: 邹璇 | C57: 点名表扬 | D57: 次 | E57: 1 | F57: =SUMIF($H$4:$AL$4,$F$4,$H57:$AL57) -> 0 | G57: =+E57*F57 -> 0
A58: 54 | B58: 邹璇 | C58: 违规 | D58: 次 | E58: 0 | F58: =SUMIF($H$4:$AL$4,$F$4,$H58:$AL58) -> 0 | G58: =+E58*F58 -> 0
A59: 55 | B59: 邹璇 | C59: 其他 | D59: 次 | E59: 2 | F59: =SUMIF($H$4:$AL$4,$F$4,$H59:$AL59) -> 0 | G59: =+E59*F59 -> 0
A60: 56 | D60: 次 | F60: =SUMIF($H$4:$AL$4,$F$4,$H60:$AL60) -> 0 | G60: =+E60*F60 -> 0
A61: 57 | D61: 次 | F61: =SUMIF($H$4:$AL$4,$F$4,$H61:$AL61) -> 0 | G61: =+E61*F61 -> 0
A62: 58 | D62: 次 | F62: =SUMIF($H$4:$AL$4,$F$4,$H62:$AL62) -> 0 | G62: =+E62*F62 -> 0
A63: 59 | D63: 次 | F63: =SUMIF($H$4:$AL$4,$F$4,$H63:$AL63) -> 0 | G63: =+E63*F63 -> 0
A64: 60 | D64: 次 | F64: =SUMIF($H$4:$AL$4,$F$4,$H64:$AL64) -> 0 | G64: =+E64*F64 -> 0
A65: 61 | D65: 次 | F65: =SUMIF($H$4:$AL$4,$F$4,$H65:$AL65) -> 0 | G65: =+E65*F65 -> 0
A66: 62 | D66: 次 | F66: =SUMIF($H$4:$AL$4,$F$4,$H66:$AL66) -> 0 | G66: =+E66*F66 -> 0
A67: 63 | D67: 次 | F67: =SUMIF($H$4:$AL$4,$F$4,$H67:$AL67) -> 0 | G67: =+E67*F67 -> 0
A68: 64 | D68: 次 | F68: =SUMIF($H$4:$AL$4,$F$4,$H68:$AL68) -> 0 | G68: =+E68*F68 -> 0
A69: 65 | D69: 次 | F69: =SUMIF($H$4:$AL$4,$F$4,$H69:$AL69) -> 0 | G69: =+E69*F69 -> 0
A70: 66 | D70: 次 | F70: =SUMIF($H$4:$AL$4,$F$4,$H70:$AL70) -> 0 | G70: =+E70*F70 -> 0
A71: 67 | D71: 次 | F71: =SUMIF($H$4:$AL$4,$F$4,$H71:$AL71) -> 0 | G71: =+E71*F71 -> 0
... A104: 100 | D104: 次 | F104: =SUMIF($H$4:$AL$4,$F$4,$H104:$AL104) -> 0 | G104: =+E104*F104 -> 0
B105: 前台二维码提成 | F105: =SUMIF($H$4:$AL$4,$F$4,$H105:$AL105) -> 1006 | G105: =SUM(G5:G104) -> 559 | H105: =SUM(H5:H104) -> 18 | I105: =SUM(I5:I104) -> 4 | J105: =SUM(J5:J104) -> 47 | K105: =SUM(K5:K104) -> 9 | L105: =SUM(L5:L104) -> 34 | M105: =SUM(M5:M104) -> 34 | N105: =SUM(N5:N104) -> 11 | ... AL105: =SUM(AL5:AL104) -> 27

Sheet 前台工资录入
A1: 姓名 | B1: 部门 | C1: 岗位 | D1: 是否转正 | E1: 薪等 | F1: 薪级 | G1: 总工资 | H1: 基本工资 | I1: 岗位工资 | J1: 绩效工资 | K1: 出勤天数 | L1: 1号工作时长 | M1: 2号工作时长 | N1: 3号工作时长 | O1: 4号工作时长 | P1: 5号工作时长 | Q1: 6号工作时长 | R1: 7号工作时长 | S1: 8号工作时长 | T1: 9号工作时长 | U1: 10号工作时长 | V1: 11号工作时长 | W1: 12号工作时长 | X1: 13号工作时长 | Y1: 14号工作时长 | Z1: 15号工作时长 | AA1: 16号工作时长 | AB1: 17号工作时长 | AC1: 18号工作时长 | AD1: 19号工作时长 | AE1: 20号工作时长 | AF1: 21号工作时长 | AG1: 22号工作时长 | AH1: 23号工作时长 | AI1: 24号工作时长 | AJ1: 25号工作时长 | AK1: 26号工作时长 | AL1: 27号工作时长 | AM1: 28号工作时长 | AN1: 29号工作时长 | AO1: 30号工作时长 | AP1: 31号工作时长
A2: 李龙梅 | B2: 前厅 | C2: 前台 | D2: 是 | G2: =H2+I2+J2 -> 4500 | H2: 4050 | I2: 0 | J2: 450 | K2: 25 | L2: 0 | M2: 8 | N2: 8 | O2: 8 | P2: 8 | Q2: 8 | R2: 8 | S2: 8 | T2: 8 | U2: 8 | V2: 0 | W2: 8 | X2: 8 | Y2: 8 | Z2: 8 | AA2: 0 | AB2: 8 | AC2: 8 | AD2: 8 | AE2: 8 | AF2: 4 | AG2: 8 | AH2: 8 | AI2: 8 | AJ2: 8 | AK2: 8 | AL2: 8 | AM2: 8 | AN2: 8 | AO2: 8 | AP2: 4
A3: 于子杭 | B3: 前厅 | C3: 前厅领班 | D3: 是 | G3: =H3+I3+J3 -> 4500 | H3: 4050 | I3: 0 | J3: 450 | K3: 25 | L3: 8 | M3: 8 | N3: 8 | O3: 0 | P3: 8 | Q3: 8 | R3: 8 | S3: 8 | T3: 8 | U3: 0 | V3: 8 | W3: 8 | X3: 8 | Y3: 0 | Z3: 8 | AA3: 8 | AB3: 8 | AC3: 8 | AD3: 8 | AE3: 8 | AF3: 8 | AG3: 0 | AH3: 8 | AI3: 8 | AJ3: 8 | AK3: 8 | AL3: 8 | AM3: 8 | AN3: 8 | AO3: 8 | AP3: 8
A4: 张馨月 | B4: 前厅 | C4: 服务经理 | D4: 是 | G4: 4000 | H4: 4000 | I4: 0 | J4: 0 | K4: 25 | L4: 8 | M4: 0 | N4: 8 | O4: 8 | P4: 8 | Q4: 8 | R4: 8 | S4: 8 | T4: 0 | U4: 8 | V4: 8 | W4: 8 | X4: 8 | Y4: 8 | Z4: 8 | AA4: 8 | AB4: 8 | AC4: 8 | AD4: 0 | AE4: 8 | AF4: 8 | AG4: 8 | AH4: 8 | AI4: 0 | AJ4: 8 | AK4: 8 | AL4: 8 | AM4: 8 | AN4: 8 | AO4: 8 | AP4: 8
A5: 徐嘉瑜 | B5: 前厅 | C5: 前台 | D5: 是 | G5: 3500 | H5: 3500 | I5: 0 | J5: 0 | K5: 20 | L5: 12 | M5: 12 | N5: 12 | O5: 12 | P5: 0 | Q5: 0 | R5: 12 | S5: 12 | T5: 12 | U5: 12 | V5: 0 | W5: 0 | X5: 12 | Y5: 12 | Z5: 0 | AA5: 4 | AB5: 0 | AC5: 0 | AD5: 12 | AE5: 12 | AF5: 12 | AG5: 12 | AH5: 0 | AI5: 0 | AJ5: 12 | AK5: 12 | AL5: 12 | AM5: 12 | AN5: 0 | AO5: 0 | AP5: 12
A6: 王增 | B6: 前厅 | C6: 前台 | D6: 是 | G6: 3500 | H6: 3500 | I6: 0 | J6: 0 | K6: 20 | L6: 12 | M6: 12 | N6: 0 | O6: 0 | P6: 12 | Q6: 12 | R6: 12 | S6: 12 | T6: 0 | U6: 0 | V6: 12 | W6: 12 | X6: 12 | Y6: 12 | Z6: 0 | AA6: 0 | AB6: 12 | AC6: 12 | AD6: 12 | AE6: 12 | AF6: 0 | AG6: 0 | AH6: 12 | AI6: 12 | AJ6: 12 | AK6: 12 | AL6: 0 | AM6: 0 | AN6: 12 | AO6: 12 | AP6: 12
A7: 宋雨霏 | B7: 前厅 | C7: 前台 | D7: 是 | G7: 3500 | H7: 3500 | I7: 0 | J7: 0 | K7: 20 | L7: 12 | M7: 12 | N7: 0 | O7: 0 | P7: 12 | Q7: 12 | R7: 12 | S7: 12 | T7: 0 | U7: 0 | V7: 12 | W7: 12 | X7: 12 | Y7: 12 | Z7: 0 | AA7: 0 | AB7: 12 | AC7: 12 | AD7: 12 | AE7: 12 | AF7: 0 | AG7: 0 | AH7: 12 | AI7: 12 | AJ7: 12 | AK7: 12 | AL7: 0 | AM7: 0 | AN7: 12 | AO7: 12 | AP7: 12
A8: 翟芮瑶 | B8: 前厅 | C8: 前台 | D8: 是 | G8: 3500 | H8: 3500 | I8: 0 | J8: 0 | K8: 20 | L8: 0 | M8: 0 | N8: 0 | O8: 12 | P8: 12 | Q8: 12 | R8: 0 | S8: 0 | T8: 12 | U8: 12 | V8: 12 | W8: 12 | X8: 0 | Y8: 0 | Z8: 12 | AA8: 12 | AB8: 12 | AC8: 12 | AD8: 0 | AE8: 0 | AF8: 12 | AG8: 12 | AH8: 12 | AI8: 12 | AJ8: 0 | AK8: 0 | AL8: 12 | AM8: 12 | AN8: 12 | AO8: 12 | AP8: 0
A9: 孙源 | B9: 前厅 | C9: 前台 | D9: 是 | G9: 3500 | H9: 3500 | I9: 0 | J9: 0 | K9: 20 | L9: 0 | M9: 0 | N9: 12 | O9: 0 | P9: 12 | Q9: 12 | R9: 0 | S9: 0 | T9: 12 | U9: 12 | V9: 12 | W9: 12 | X9: 0 | Y9: 0 | Z9: 12 | AA9: 12 | AB9: 12 | AC9: 12 | AD9: 0 | AE9: 0 | AF9: 12 | AG9: 12 | AH9: 12 | AI9: 12 | AJ9: 0 | AK9: 0 | AL9: 0 | AM9: 12 | AN9: 12 | AO9: 12 | AP9: 0
A10: 吴怡 | B10: 前厅 | C10: 前台 | G10: 3500 | H10: 3500 | I10: 0 | J10: 0 | K10: 20 | L10: 12 | M10: 12 | N10: 12 | O10: 12 | P10: 0 | Q10: 0 | R10: 12 | S10: 12 | T10: 12 | U10: 12 | V10: 0 | W10: 0 | X10: 12 | Y10: 12 | Z10: 12 | AA10: 12 | AB10: 0 | AC10: 0 | AD10: 6 | AE10: 12 | AF10: 12 | AG10: 12 | AH10: 0 | AI10: 0 | AJ10: 12 | AK10: 12 | AL10: 12 | AM10: 12 | AN10: 0 | AO10: 0 | AP10: 12
A11: 刘昕 | B11: 前厅 | C11: 前台 | G11: 3500 | H11: 3500 | I11: 0 | J11: 0 | K11: 20
A12: 邹璇 | B12: 前厅 | C12: 前台 | G12: 3500 | H12: 3500 | I12: 0 | J12: 0 | K12: 26 | L12: 8 | M12: 8 | N12: 8 | O12: 8 | P12: 8 | Q12: 8 | R12: 0 | S12: 8 | T12: 8 | U12: 8 | V12: 8 | W12: 8 | X12: 8 | Y12: 0 | Z12: 12 | AA12: 12 | AB12: 0 | AC12: 8 | AD12: 8 | AE12: 8 | AF12: 8 | AG12: 8 | AH12: 12 | AI12: 12 | AJ12: 0 | AK12: 0 | AL12: 12 | AM12: 12 | AN12: 12 | AO12: 12 | AP12: 0
A16: 前台工时 | L16: =SUM(L2:L15) -> 72 | M16: =SUM(M2:M15) -> 72 | N16: =SUM(N2:N15) -> 68 | O16: =SUM(O2:O15) -> 60 | P16: =SUM(P2:P15) -> 80 | Q16: =SUM(Q2:Q15) -> 80 | R16: =SUM(R2:R15) -> 72 | S16: =SUM(S2:S15) -> 80 | ... AP16: =SUM(AP2:AP15) -> 68

Sheet 前台增值物品出入库录入
B1: 前台增值物品出入库表
B2: 酒店名称： | N2: 周期：
A3: 序号 | B3: 货品名称 | C3: 规格型号 | D3: 单位 | E3: 单价 | F3: 上月 结存 | G3: 结存金额 | H3: 入库合计 | I3: 入库金额 | J3: 出库合计 | K3: 出库金额 | L3: 结存合计 | M3: 结存金额 | N3: 1号 | P3: 2号 | R3: 3号 | T3: 4号 | V3: 5号 | X3: 6号 | Z3: 7号 | AB3: 8号 | AD3: 9号 | AF3: 10号 | AH3: 11号 | AJ3: 12号 | AL3: 13号 | AN3: 14号 | AP3: 15号 | AR3: 16号 | AT3: 17号 | AV3: 18号 | AX3: 19号 | AZ3: 20号 | BB3: 21号 | BD3: 22号 | BF3: 23号 | BH3: 24号 | BJ3: 25号 | BL3: 26号 | BN3: 27号 | BP3: 28号 | BR3: 29号 | BT3: 30号 | BV3: 31号
H4: 入库 | J4: 出库 | N4: 入库 | O4: 出库 | P4: 入库 | Q4: 出库 | R4: 入库 | S4: 出库 | T4: 入库 | U4: 出库 | V4: 入库 | W4: 出库 | X4: 入库 | Y4: 出库 | Z4: 入库 | AA4: 出库 | AB4: 入库 | AC4: 出库 | AD4: 入库 | AE4: 出库 | AF4: 入库 | AG4: 出库 | AH4: 入库 | AI4: 出库 | AJ4: 入库 | AK4: 出库 | AL4: 入库 | AM4: 出库 | AN4: 入库 | AO4: 出库 | AP4: 入库 | AQ4: 出库 | AR4: 入库 | AS4: 出库 | AT4: 入库 | AU4: 出库 | AV4: 入库 | AW4: 出库 | AX4: 入库 | AY4: 出库 | AZ4: 入库 | BA4: 出库 | BB4: 入库 | BC4: 出库 | BD4: 入库 | BE4: 出库 | BF4: 入库 | BG4: 出库 | BH4: 入库 | BI4: 出库 | BJ4: 入库 | BK4: 出库 | BL4: 入库 | BM4: 出库 | BN4: 入库 | BO4: 出库 | BP4: 入库 | BQ4: 出库 | BR4: 入库 | BS4: 出库 | BT4: 入库 | BU4: 出库 | BV4: 入库 | BW4: 出库
A5: 1 | B5: 剃须刀 | D5: 个 | E5: 1.2 | F5: 0 | G5: =F5*E5 -> 0 | H5: =SUMIF($N$4:$BW$4,$H$4,$N5:$BW5) -> 0 | I5: =+E5*H5 -> 0 | J5: =SUMIF($N$4:$BW$4,$J$4,$N5:$BW5) -> 0 | K5: =+E5*J5 -> 0 | L5: =+F5+H5-J5 -> 0 | M5: =+E5*L5 -> 0
A6: 2 | B6: 费用报销单 | D6: 个 | E6: 2 | F6: 5 | G6: =F6*E6 -> 10 | H6: =SUMIF($N$4:$BW$4,$H$4,$N6:$BW6) -> 0 | I6: =+E6*H6 -> 0 | J6: =SUMIF($N$4:$BW$4,$J$4,$N6:$BW6) -> 0 | K6: =+E6*J6 -> 0 | L6: =+F6+H6-J6 -> 5 | M6: =+E6*L6 -> 10
A7: 3 | B7: 记号笔 | D7: 个 | E7: 0.398 | F7: 35 | G7: =F7*E7 -> 13.93 | H7: =SUMIF($N$4:$BW$4,$H$4,$N7:$BW7) -> 0 | I7: =+E7*H7 -> 0 | J7: =SUMIF($N$4:$BW$4,$J$4,$N7:$BW7) -> 4 | K7: =+E7*J7 -> 1.592 | L7: =+F7+H7-J7 -> 31 | M7: =+E7*L7 -> 12.338 | O7: 1 | BK7: 3
A8: 4 | B8: 前台交接本 | D8: 个 | E8: 7 | F8: 27 | G8: =F8*E8 -> 189 | H8: =SUMIF($N$4:$BW$4,$H$4,$N8:$BW8) -> 0 | I8: =+E8*H8 -> 0 | J8: =SUMIF($N$4:$BW$4,$J$4,$N8:$BW8) -> 2 | K8: =+E8*J8 -> 14 | L8: =+F8+H8-J8 -> 25 | M8: =+E8*L8 -> 175 | O8: 1 | BK8: 1
A9: 5 | B9: 遗留物品登记表 | D9: 个 | E9: 7 | F9: 4 | G9: =F9*E9 -> 28 | H9: =SUMIF($N$4:$BW$4,$H$4,$N9:$BW9) -> 0 | I9: =+E9*H9 -> 0 | J9: =SUMIF($N$4:$BW$4,$J$4,$N9:$BW9) -> 0 | K9: =+E9*J9 -> 0 | L9: =+F9+H9-J9 -> 4 | M9: =+E9*L9 -> 28
A10: 6 | B10: 前台预抵本 | D10: 个 | E10: 7 | F10: 11 | G10: =F10*E10 -> 77 | H10: =SUMIF($N$4:$BW$4,$H$4,$N10:$BW10) -> 0 | I10: =+E10*H10 -> 0 | J10: =SUMIF($N$4:$BW$4,$J$4,$N10:$BW10) -> 0 | K10: =+E10*J10 -> 0 | L10: =+F10+H10-J10 -> 11 | M10: =+E10*L10 -> 77
A11: 7 | B11: 会议记录表 | D11: 个 | E11: 7 | F11: 15 | G11: =F11*E11 -> 105 | H11: =SUMIF($N$4:$BW$4,$H$4,$N11:$BW11) -> 0 | I11: =+E11*H11 -> 0 | J11: =SUMIF($N$4:$BW$4,$J$4,$N11:$BW11) -> 0 | K11: =+E11*J11 -> 0 | L11: =+F11+H11-J11 -> 15 | M11: =+E11*L11 -> 105
A12: 8 | B12: A4纸2 | D12: 张 | E12: 0.0354 | F12: 300 | G12: =F12*E12 -> 10.62 | H12: =SUMIF($N$4:$BW$4,$H$4,$N12:$BW12) -> 0 | I12: =+E12*H12 -> 0 | J12: =SUMIF($N$4:$BW$4,$J$4,$N12:$BW12) -> 300 | K12: =+E12*J12 -> 10.62 | L12: =+F12+H12-J12 -> 0 | M12: =+E12*L12 -> 0 | O12: 100 | AM12: 100 | AS12: 100
A13: 9 | B13: 纸碟子 | D13: 个 | E13: 0.06384 | F13: 360 | G13: =F13*E13 -> 22.9824 | H13: =SUMIF($N$4:$BW$4,$H$4,$N13:$BW13) -> 0 | I13: =+E13*H13 -> 0 | J13: =SUMIF($N$4:$BW$4,$J$4,$N13:$BW13) -> 360 | K13: =+E13*J13 -> 22.9824 | L13: =+F13+H13-J13 -> 0 | M13: =+E13*L13 -> 0 | O13: 20 | Q13: 20 | S13: 20 | U13: 20 | W13: 20 | AA13: 20 | AE13: 20 | AG13: 20 | AK13: 20 | BK13: 180
A14: 10 | B14: 口罩 | D14: 个 | E14: 0.115 | F14: 199 | G14: =F14*E14 -> 22.885 | H14: =SUMIF($N$4:$BW$4,$H$4,$N14:$BW14) -> 0 | I14: =+E14*H14 -> 0 | J14: =SUMIF($N$4:$BW$4,$J$4,$N14:$BW14) -> 57 | K14: =+E14*J14 -> 6.555 | L14: =+F14+H14-J14 -> 142 | M14: =+E14*L14 -> 16.33 | O14: 5 | S14: 6 | W14: 5 | AM14: 15 | AQ14: 10 | BK14: 2 | BM14: 2 | BO14: 1 | BS14: 1 | BU14: 5 | BW14: 5
A15: 11 | B15: 文件盒 | D15: 个 | E15: 4.495 | F15: 3 | G15: =F15*E15 -> 13.485 | H15: =SUMIF($N$4:$BW$4,$H$4,$N15:$BW15) -> 0 | I15: =+E15*H15 -> 0 | J15: =SUMIF($N$4:$BW$4,$J$4,$N15:$BW15) -> 2 | K15: =+E15*J15 -> 8.99 | L15: =+F15+H15-J15 -> 1 | M15: =+E15*L15 -> 4.495 | BG15: 1 | BM15: 1
A16: 12 | B16: 壁纸刀 | D16: 个 | E16: 3.495 | F16: 4 | G16: =F16*E16 -> 13.98 | H16: =SUMIF($N$4:$BW$4,$H$4,$N16:$BW16) -> 0 | I16: =+E16*H16 -> 0 | J16: =SUMIF($N$4:$BW$4,$J$4,$N16:$BW16) -> 4 | K16: =+E16*J16 -> 13.98 | L16: =+F16+H16-J16 -> 0 | M16: =+E16*L16 -> 0 | O16: 1 | BK16: 3
A17: 13 | B17: 铅笔 | D17: 个 | E17: 0.3779 | F17: 59 | G17: =F17*E17 -> 22.2961 | H17: =SUMIF($N$4:$BW$4,$H$4,$N17:$BW17) -> 0 | I17: =+E17*H17 -> 0 | J17: =SUMIF($N$4:$BW$4,$J$4,$N17:$BW17) -> 14 | K17: =+E17*J17 -> 5.2906 | L17: =+F17+H17-J17 -> 45 | M17: =+E17*L17 -> 17.0055 | AS17: 5 | BS17: 1 | BU17: 6 | BW17: 2
A18: 14 | B18: 拖把 | D18: 个 | E18: 29.6 | F18: 0 | G18: =F18*E18 -> 0 | H18: =SUMIF($N$4:$BW$4,$H$4,$N18:$BW18) -> 1 | I18: =+E18*H18 -> 29.6 | J18: =SUMIF($N$4:$BW$4,$J$4,$N18:$BW18) -> 1 | K18: =+E18*J18 -> 29.6 | L18: =+F18+H18-J18 -> 0 | M18: =+E18*L18 -> 0 | V18: 1 | BI18: 1
A19: 15 | B19: 削笔刀 | D19: 个 | E19: 9.5 | F19: 2 | G19: =F19*E19 -> 19 | H19: =SUMIF($N$4:$BW$4,$H$4,$N19:$BW19) -> 0 | I19: =+E19*H19 -> 0 | J19: =SUMIF($N$4:$BW$4,$J$4,$N19:$BW19) -> 0 | K19: =+E19*J19 -> 0 | L19: =+F19+H19-J19 -> 2 | M19: =+E19*L19 -> 19
A20: 70 | B20: 橡皮筋 | D20: 个 | E20: 0.28 | F20: 110 | G20: =F20*E20 -> 30.8 | H20: =SUMIF($N$4:$BW$4,$H$4,$N20:$BW20) -> 0 | I20: =+E20*H20 -> 0 | J20: =SUMIF($N$4:$BW$4,$J$4,$N20:$BW20) -> 60 | K20: =+E20*J20 -> 16.8 | L20: =+F20+H20-J20 -> 50 | M20: =+E20*L20 -> 14 | AQ20: 10 | AU20: 10 | AY20: 10 | BC20: 10 | BK20: 20
A21: 16 | B21: 茉莉花 | D21: 个 | E21: 19.9 | F21: 1 | G21: =F21*E21 -> 19.9 | H21: =SUMIF($N$4:$BW$4,$H$4,$N21:$BW21) -> 0 | I21: =+E21*H21 -> 0 | J21: =SUMIF($N$4:$BW$4,$J$4,$N21:$BW21) -> 1 | K21: =+E21*J21 -> 19.9 | L21: =+F21+H21-J21 -> 0 | M21: =+E21*L21 -> 0 | O21: 1
A22: 18 | B22: 中性笔 | D22: 个 | E22: 1.0605556 | F22: 26 | G22: =F22*E22 -> 27.574444 | H22: =SUMIF($N$4:$BW$4,$H$4,$N22:$BW22) -> 0 | I22: =+E22*H22 -> 0 | J22: =SUMIF($N$4:$BW$4,$J$4,$N22:$BW22) -> 11 | K22: =+E22*J22 -> 11.666111 | L22: =+F22+H22-J22 -> 15 | M22: =+E22*L22 -> 15.908333 | BA22: 3 | BC22: 3 | BI22: 2 | BK22: 1 | BM22: 2
A23: 19 | B23: 标签纸 | D23: 个 | E23: 0.0653 | F23: 50 | G23: =F23*E23 -> 3.265 | H23: =SUMIF($N$4:$BW$4,$H$4,$N23:$BW23) -> 0 | I23: =+E23*H23 -> 0 | J23: =SUMIF($N$4:$BW$4,$J$4,$N23:$BW23) -> 22 | K23: =+E23*J23 -> 1.4366 | L23: =+F23+H23-J23 -> 28 | M23: =+E23*L23 -> 1.8284 | O23: 2 | AU23: 5 | AW23: 3 | AY23: 10 | BK23: 2
A24: 20 | B24: 订书机 | D24: 个 | E24: 3.31 | F24: 1 | G24: =F24*E24 -> 3.31 | H24: =SUMIF($N$4:$BW$4,$H$4,$N24:$BW24) -> 0 | I24: =+E24*H24 -> 0 | J24: =SUMIF($N$4:$BW$4,$J$4,$N24:$BW24) -> 0 | K24: =+E24*J24 -> 0 | L24: =+F24+H24-J24 -> 1 | M24: =+E24*L24 -> 3.31
A25: 1 | B25: 订书钉 | D25: 个 | E25: 3.31 | F25: 8 | G25: =F25*E25 -> 26.48 | H25: =SUMIF($N$4:$BW$4,$H$4,$N25:$BW25) -> 0 | I25: =+E25*H25 -> 0 | J25: =SUMIF($N$4:$BW$4,$J$4,$N25:$BW25) -> 0 | K25: =+E25*J25 -> 0 | L25: =+F25+H25-J25 -> 8 | M25: =+E25*L25 -> 26.48
A26: 24 | B26: 固体胶 | D26: 个 | E26: 1.9916667 | F26: 4 | G26: =F26*E26 -> 7.9666667 | H26: =SUMIF($N$4:$BW$4,$H$4,$N26:$BW26) -> 0 | I26: =+E26*H26 -> 0 | J26: =SUMIF($N$4:$BW$4,$J$4,$N26:$BW26) -> 1 | K26: =+E26*J26 -> 1.9916667 | L26: =+F26+H26-J26 -> 3 | M26: =+E26*L26 -> 5.975 | Q26: 1
A27: 25 | B27: 棉签 | D27: 个 | E27: 0.01681875 | F27: 642 | G27: =F27*E27 -> 10.797638 | H27: =SUMIF($N$4:$BW$4,$H$4,$N27:$BW27) -> 0 | I27: =+E27*H27 -> 0 | J27: =SUMIF($N$4:$BW$4,$J$4,$N27:$BW27) -> 211 | K27: =+E27*J27 -> 3.5487562 | L27: =+F27+H27-J27 -> 431 | M27: =+E27*L27 -> 7.2488813 | Q27: 30 | S27: 15 | W27: 10 | AA27: 15 | AK27: 20 | AM27: 5 | AO27: 15 | AS27: 20 | AW27: 5 | AY27: 5 | BC27: 15 | BE27: 3 | BG27: 2 | BI27: 1 | BK27: 10 | BM27: 10 | BQ27: 5 | BS27: 10 | BU27: 15
A28: 26 | B28: 胶带+切割器 | D28: 个 | E28: 0.69567568 | F28: 15 | G28: =F28*E28 -> 10.435135 | H28: =SUMIF($N$4:$BW$4,$H$4,$N28:$BW28) -> 0 | I28: =+E28*H28 -> 0 | J28: =SUMIF($N$4:$BW$4,$J$4,$N28:$BW28) -> 0 | K28: =+E28*J28 -> 0 | L28: =+F28+H28-J28 -> 15 | M28: =+E28*L28 -> 10.435135
A29: 27 | B29: 回形针 | D29: 个 | E29: 0.0109 | F29: 1483 | G29: =F29*E29 -> 16.1647 | H29: =SUMIF($N$4:$BW$4,$H$4,$N29:$BW29) -> 0 | I29: =+E29*H29 -> 0 | J29: =SUMIF($N$4:$BW$4,$J$4,$N29:$BW29) -> 255 | K29: =+E29*J29 -> 2.7795 | L29: =+F29+H29-J29 -> 1228 | M29: =+E29*L29 -> 13.3852 | O29: 50 | Q29: 50 | W29: 30 | AY29: 30 | BC29: 20 | BE29: 20 | BM29: 30 | BQ29: 10 | BU29: 15
A30: 29 | B30: 卷尺子 | D30: 个 | E30: 1.5475 | F30: 0 | G30: =F30*E30 -> 0 | H30: =SUMIF($N$4:$BW$4,$H$4,$N30:$BW30) -> 0 | I30: =+E30*H30 -> 0 | J30: =SUMIF($N$4:$BW$4,$J$4,$N30:$BW30) -> 0 | K30: =+E30*J30 -> 0 | L30: =+F30+H30-J30 -> 0 | M30: =+E30*L30 -> 0
A31: 30 | B31: 便利贴 | D31: 个 | E31: 0.6915 | F31: 7 | G31: =F31*E31 -> 4.8405 | H31: =SUMIF($N$4:$BW$4,$H$4,$N31:$BW31) -> 0 | I31: =+E31*H31 -> 0 | J31: =SUMIF($N$4:$BW$4,$J$4,$N31:$BW31) -> 4 | K31: =+E31*J31 -> 2.766 | L31: =+F31+H31-J31 -> 3 | M31: =+E31*L31 -> 2.0745 | BA31: 2 | BE31: 1 | BM31: 1
A32: 31 | B32: A4透明袋 | D32: 个 | E32: 0.408 | F32: 98 | G32: =F32*E32 -> 39.984 | H32: =SUMIF($N$4:$BW$4,$H$4,$N32:$BW32) -> 0 | I32: =+E32*H32 -> 0 | J32: =SUMIF($N$4:$BW$4,$J$4,$N32:$BW32) -> 48 | K32: =+E32*J32 -> 19.584 | L32: =+F32+H32-J32 -> 50 | M32: =+E32*L32 -> 20.4 | O32: 20 | S32: 10 | W32: 5 | AA32: 5 | BC32: 4 | BG32: 4
A33: 32 | B33: 文件夹 | D33: 个 | E33: 4.9 | F33: 3 | G33: =F33*E33 -> 14.7 | H33: =SUMIF($N$4:$BW$4,$H$4,$N33:$BW33) -> 0 | I33: =+E33*H33 -> 0 | J33: =SUMIF($N$4:$BW$4,$J$4,$N33:$BW33) -> 0 | K33: =+E33*J33 -> 0 | L33: =+F33+H33-J33 -> 3 | M33: =+E33*L33 -> 14.7
A34: 33 | B34: 发绳2 | D34: 个 | E34: 0.0298 | F34: 0 | G34: =F34*E34 -> 0 | H34: =SUMIF($N$4:$BW$4,$H$4,$N34:$BW34) -> 500 | I34: =+E34*H34 -> 14.9 | J34: =SUMIF($N$4:$BW$4,$J$4,$N34:$BW34) -> 69 | K34: =+E34*J34 -> 2.0562 | L34: =+F34+H34-J34 -> 431 | M34: =+E34*L34 -> 12.8438 | V34: 500 | AO34: 5 | AQ34: 5 | AS34: 10 | BC34: 5 | BE34: 5 | BG34: 5 | BK34: 20 | BM34: 5 | BO34: 3 | BQ34: 4 | BS34: 2
A35: 34 | B35: 文件袋 | D35: 个 | E35: 2.64 | F35: 20 | G35: =F35*E35 -> 52.8 | H35: =SUMIF($N$4:$BW$4,$H$4,$N35:$BW35) -> 0 | I35: =+E35*H35 -> 0 | J35: =SUMIF($N$4:$BW$4,$J$4,$N35:$BW35) -> 0 | K35: =+E35*J35 -> 0 | L35: =+F35+H35-J35 -> 20 | M35: =+E35*L35 -> 52.8
A36: 35 | B36: 燕尾夹 | D36: 个 | E36: 0.632 | F36: 3 | G36: =F36*E36 -> 1.896 | H36: =SUMIF($N$4:$BW$4,$H$4,$N36:$BW36) -> 0 | I36: =+E36*H36 -> 0 | J36: =SUMIF($N$4:$BW$4,$J$4,$N36:$BW36) -> 3 | K36: =+E36*J36 -> 1.896 | L36: =+F36+H36-J36 -> 0 | M36: =+E36*L36 -> 0 | BC36: 3
A37: 36 | B37: 笔筒 | D37: 个 | E37: 2.9925 | F37: 2 | G37: =F37*E37 -> 5.985 | H37: =SUMIF($N$4:$BW$4,$H$4,$N37:$BW37) -> 0 | I37: =+E37*H37 -> 0 | J37: =SUMIF($N$4:$BW$4,$J$4,$N37:$BW37) -> 0 | K37: =+E37*J37 -> 0 | L37: =+F37+H37-J37 -> 2 | M37: =+E37*L37 -> 5.985
A38: 37 | B38: 酒精棉签 | D38: 个 | E38: 0.0798 | F38: 901 | G38: =F38*E38 -> 71.8998 | H38: =SUMIF($N$4:$BW$4,$H$4,$N38:$BW38) -> 0 | I38: =+E38*H38 -> 0 | J38: =SUMIF($N$4:$BW$4,$J$4,$N38:$BW38) -> 300 | K38: =+E38*J38 -> 23.94 | L38: =+F38+H38-J38 -> 601 | M38: =+E38*L38 -> 47.9598 | O38: 30 | S38: 15 | W38: 20 | AA38: 25 | AC38: 15 | AE38: 15 | AG38: 10 | AK38: 10 | AS38: 10 | AU38: 10 | AW38: 15 | AY38: 10 | BA38: 15 | BE38: 20 | BI38: 15 | BK38: 15 | BM38: 10 | BQ38: 15 | BS38: 5 | BU38: 10 | BW38: 10
A39: 38 | B39: 柠檬汁 | D39: 瓶 | E39: 29.335 | F39: 0 | G39: =F39*E39 -> 0 | H39: =SUMIF($N$4:$BW$4,$H$4,$N39:$BW39) -> 2 | I39: =+E39*H39 -> 58.67 | J39: =SUMIF($N$4:$BW$4,$J$4,$N39:$BW39) -> 2 | K39: =+E39*J39 -> 58.67 | L39: =+F39+H39-J39 -> 0 | M39: =+E39*L39 -> 0 | V39: 2 | W39: 1 | BK39: 1
A40: 39 | B40: 火柴4 | D40: 个 | E40: 0.2071 | F40: 450 | G40: =F40*E40 -> 93.195 | H40: =SUMIF($N$4:$BW$4,$H$4,$N40:$BW40) -> 0 | I40: =+E40*H40 -> 0 | J40: =SUMIF($N$4:$BW$4,$J$4,$N40:$BW40) -> 192 | K40: =+E40*J40 -> 39.7632 | L40: =+F40+H40-J40 -> 258 | M40: =+E40*L40 -> 53.4318 | O40: 50 | S40: 20 | W40: 15 | AA40: 10 | AE40: 5 | AI40: 5 | AK40: 5 | AM40: 5 | AO40: 10 | AQ40: 5 | AS40: 10 | AU40: 6 | AW40: 5 | BA40: 4 | BC40: 5 | BE40: 5 | BG40: 3 | BI40: 5 | BK40: 10 | BQ40: 5 | BS40: 3 | BU40: 1
A41: 40 | B41: 雨伞 | D41: 个 | E41: 30 | F41: 2 | G41: =F41*E41 -> 60 | H41: =SUMIF($N$4:$BW$4,$H$4,$N41:$BW41) -> 0 | I41: =+E41*H41 -> 0 | J41: =SUMIF($N$4:$BW$4,$J$4,$N41:$BW41) -> 0 | K41: =+E41*J41 -> 0 | L41: =+F41+H41-J41 -> 2 | M41: =+E41*L41 -> 60
B42: 雨伞 | D42: 个 | E42: 10
A43: 41 | B43: 档案袋（底2.8） | D43: 个 | E43: 0.5 | F43: 16 | G43: =F43*E43 -> 8 | H43: =SUMIF($N$4:$BW$4,$H$4,$N43:$BW43) -> 0 | I43: =+E43*H43 -> 0 | J43: =SUMIF($N$4:$BW$4,$J$4,$N43:$BW43) -> 1 | K43: =+E43*J43 -> 0.5 | L43: =+F43+H43-J43 -> 15 | M43: =+E43*L43 -> 7.5 | BI43: 1
A44: 42 | B44: 夹板 | D44: 个 | E44: 4.5 | F44: 3 | G44: =F44*E44 -> 13.5 | H44: =SUMIF($N$4:$BW$4,$H$4,$N44:$BW44) -> 0 | I44: =+E44*H44 -> 0 | J44: =SUMIF($N$4:$BW$4,$J$4,$N44:$BW44) -> 1 | K44: =+E44*J44 -> 4.5 | L44: =+F44+H44-J44 -> 2 | M44: =+E44*L44 -> 9 | BK44: 1
A45: 43 | B45: 磨砂身份证套宽口 | D45: 个 | E45: 0.1 | F45: 1889 | G45: =F45*E45 -> 188.9 | H45: =SUMIF($N$4:$BW$4,$H$4,$N45:$BW45) -> 0 | I45: =+E45*H45 -> 0 | J45: =SUMIF($N$4:$BW$4,$J$4,$N45:$BW45) -> 250 | K45: =+E45*J45 -> 25 | L45: =+F45+H45-J45 -> 1639 | M45: =+E45*L45 -> 163.9 | O45: 100 | S45: 150
A46: 46 | B46: 指甲刀 | D46: 个 | E46: 0.506 | F46: 0 | G46: =F46*E46 -> 0 | H46: =SUMIF($N$4:$BW$4,$H$4,$N46:$BW46) -> 120 | I46: =+E46*H46 -> 60.72 | J46: =SUMIF($N$4:$BW$4,$J$4,$N46:$BW46) -> 14 | K46: =+E46*J46 -> 7.084 | L46: =+F46+H46-J46 -> 106 | M46: =+E46*L46 -> 53.636 | V46: 120 | AU46: 1 | AW46: 2 | AY46: 3 | BC46: 3 | BI46: 5
A47: 47 | B47: 量杯 | D47: 个 | E47: 9.04 | F47: 0 | G47: =F47*E47 -> 0 | H47: =SUMIF($N$4:$BW$4,$H$4,$N47:$BW47) -> 0 | I47: =+E47*H47 -> 0 | J47: =SUMIF($N$4:$BW$4,$J$4,$N47:$BW47) -> 0 | K47: =+E47*J47 -> 0 | L47: =+F47+H47-J47 -> 0 | M47: =+E47*L47 -> 0
A48: 48 | B48: 黑色发卡一字夹 | D48: 个 | E48: 0.1 | F48: 117 | G48: =F48*E48 -> 11.7 | H48: =SUMIF($N$4:$BW$4,$H$4,$N48:$BW48) -> 0 | I48: =+E48*H48 -> 0 | J48: =SUMIF($N$4:$BW$4,$J$4,$N48:$BW48) -> 65 | K48: =+E48*J48 -> 6.5 | L48: =+F48+H48-J48 -> 52 | M48: =+E48*L48 -> 5.2 | O48: 20 | S48: 15 | BA48: 10 | BI48: 5 | BM48: 10 | BQ48: 5
A49: 21 | B49: 创可贴 | D49: 个 | E49: 0.2 | F49: 100 | G49: =F49*E49 -> 20 | H49: =SUMIF($N$4:$BW$4,$H$4,$N49:$BW49) -> 0 | I49: =+E49*H49 -> 0 | J49: =SUMIF($N$4:$BW$4,$J$4,$N49:$BW49) -> 50 | K49: =+E49*J49 -> 10 | L49: =+F49+H49-J49 -> 50 | M49: =+E49*L49 -> 10 | O49: 5 | U49: 5 | AC49: 6 | AQ49: 1 | AS49: 2 | BA49: 5 | BC49: 5 | BE49: 10 | BG49: 4 | BI49: 1 | BM49: 6
A50: 51 | B50: 吸水纸 | D50: 片 | E50: 0.3975 | F50: 0 | G50: =F50*E50 -> 0 | H50: =SUMIF($N$4:$BW$4,$H$4,$N50:$BW50) -> 100 | I50: =+E50*H50 -> 39.75 | J50: =SUMIF($N$4:$BW$4,$J$4,$N50:$BW50) -> 60 | K50: =+E50*J50 -> 23.85 | L50: =+F50+H50-J50 -> 40 | M50: =+E50*L50 -> 15.9 | V50: 100 | BI50: 60
A51: 52 | B51: 文件盒宽 | D51: 个 | E51: 5 | F51: 6 | G51: =F51*E51 -> 30 | H51: =SUMIF($N$4:$BW$4,$H$4,$N51:$BW51) -> 0 | I51: =+E51*H51 -> 0 | J51: =SUMIF($N$4:$BW$4,$J$4,$N51:$BW51) -> 0 | K51: =+E51*J51 -> 0 | L51: =+F51+H51-J51 -> 6 | M51: =+E51*L51 -> 30
A52: 53 | B52: 垃圾桶 | D52: 个 | E52: 69.9 | F52: 0 | G52: =F52*E52 -> 0 | H52: =SUMIF($N$4:$BW$4,$H$4,$N52:$BW52) -> 1 | I52: =+E52*H52 -> 69.9 | J52: =SUMIF($N$4:$BW$4,$J$4,$N52:$BW52) -> 1 | K52: =+E52*J52 -> 69.9 | L52: =+F52+H52-J52 -> 0 | M52: =+E52*L52 -> 0 | R52: 1 | S52: 1
A53: 54 | B53: 黑色头绳 | D53: 个 | E53: 0.059 | F53: 50 | G53: =F53*E53 -> 2.95 | H53: =SUMIF($N$4:$BW$4,$H$4,$N53:$BW53) -> 0 | I53: =+E53*H53 -> 0 | J53: =SUMIF($N$4:$BW$4,$J$4,$N53:$BW53) -> 12 | K53: =+E53*J53 -> 0.708 | L53: =+F53+H53-J53 -> 38 | M53: =+E53*L53 -> 2.242 | O53: 2 | S53: 10
A54: 55 | B54: 白砂糖 | D54: 个 | E54: 0.1138 | F54: 748 | G54: =F54*E54 -> 85.1224 | H54: =SUMIF($N$4:$BW$4,$H$4,$N54:$BW54) -> 0 | I54: =+E54*H54 -> 0 | J54: =SUMIF($N$4:$BW$4,$J$4,$N54:$BW54) -> 748 | K54: =+E54*J54 -> 85.1224 | L54: =+F54+H54-J54 -> 0 | M54: =+E54*L54 -> 0 | O54: 100 | S54: 50 | W54: 100 | AA54: 40 | AE54: 100 | AK54: 100 | AQ54: 100 | BC54: 50 | BI54: 108
A55: 56 | B55: 杀虫剂 | D55: 个 | E55: 18.88 | F55: 0 | G55: =F55*E55 -> 0 | H55: =SUMIF($N$4:$BW$4,$H$4,$N55:$BW55) -> 1 | I55: =+E55*H55 -> 18.88 | J55: =SUMIF($N$4:$BW$4,$J$4,$N55:$BW55) -> 1 | K55: =+E55*J55 -> 18.88 | L55: =+F55+H55-J55 -> 0 | M55: =+E55*L55 -> 0 | R55: 1 | BI55: 1
A56: 57 | B56: 果酱 | D56: 个 | E56: 23.8 | F56: 0 | G56: =F56*E56 -> 0 | H56: =SUMIF($N$4:$BW$4,$H$4,$N56:$BW56) -> 1 | I56: =+E56*H56 -> 23.8 | J56: =SUMIF($N$4:$BW$4,$J$4,$N56:$BW56) -> 1 | K56: =+E56*J56 -> 23.8 | L56: =+F56+H56-J56 -> 0 | M56: =+E56*L56 -> 0 | V56: 1 | BI56: 1
A57: 58 | B57: 果酱2 | D57: 个 | E57: 13.8 | F57: 0 | G57: =F57*E57 -> 0 | H57: =SUMIF($N$4:$BW$4,$H$4,$N57:$BW57) -> 1 | I57: =+E57*H57 -> 13.8 | J57: =SUMIF($N$4:$BW$4,$J$4,$N57:$BW57) -> 1 | K57: =+E57*J57 -> 13.8 | L57: =+F57+H57-J57 -> 0 | M57: =+E57*L57 -> 0 | R57: 1 | BI57: 1
A58: 59 | B58: 剪指刀 | D58: 个 | E58: 0.85 | F58: 40 | G58: =F58*E58 -> 34 | H58: =SUMIF($N$4:$BW$4,$H$4,$N58:$BW58) -> 0 | I58: =+E58*H58 -> 0 | J58: =SUMIF($N$4:$BW$4,$J$4,$N58:$BW58) -> 40 | K58: =+E58*J58 -> 34 | L58: =+F58+H58-J58 -> 0 | M58: =+E58*L58 -> 0 | O58: 10 | W58: 5 | AU58: 5 | AW58: 5 | AY58: 5 | BA58: 10
A59: 63 | B59: 挖耳勺 | D59: 个 | E59: 0.228 | F59: 123 | G59: =F59*E59 -> 28.044 | H59: =SUMIF($N$4:$BW$4,$H$4,$N59:$BW59) -> 0 | I59: =+E59*H59 -> 0 | J59: =SUMIF($N$4:$BW$4,$J$4,$N59:$BW59) -> 23 | K59: =+E59*J59 -> 5.244 | L59: =+F59+H59-J59 -> 100 | M59: =+E59*L59 -> 22.8 | Q59: 3 | W59: 5 | AA59: 2 | AE59: 4 | AS59: 4 | AU59: 2 | AY59: 1 | BE59: 1 | BI59: 1
A60: 64 | B60: 笔壳 | D60: 个 | E60: 0.477 | F60: 0 | G60: =F60*E60 -> 0 | H60: =SUMIF($N$4:$BW$4,$H$4,$N60:$BW60) -> 10 | I60: =+E60*H60 -> 4.77 | J60: =SUMIF($N$4:$BW$4,$J$4,$N60:$BW60) -> 0 | K60: =+E60*J60 -> 0 | L60: =+F60+H60-J60 -> 10 | M60: =+E60*L60 -> 4.77 | R60: 10
A61: 65 | B61: 金超霸5号电池 | D61: 个 | E61: 1.1854 | F61: 15 | G61: =F61*E61 -> 17.781 | H61: =SUMIF($N$4:$BW$4,$H$4,$N61:$BW61) -> 0 | I61: =+E61*H61 -> 0 | J61: =SUMIF($N$4:$BW$4,$J$4,$N61:$BW61) -> 11 | K61: =+E61*J61 -> 13.0394 | L61: =+F61+H61-J61 -> 4 | M61: =+E61*L61 -> 4.7416 | S61: 2 | U61: 1 | W61: 1 | AA61: 3 | BM61: 4
A62: 66 | B62: 沥水垫 | D62: 个 | E62: 20.8 | F62: 1 | G62: =F62*E62 -> 20.8 | H62: =SUMIF($N$4:$BW$4,$H$4,$N62:$BW62) -> 0 | I62: =+E62*H62 -> 0 | J62: =SUMIF($N$4:$BW$4,$J$4,$N62:$BW62) -> 1 | K62: =+E62*J62 -> 20.8 | L62: =+F62+H62-J62 -> 0 | M62: =+E62*L62 -> 0 | O62: 1
A63: 71 | B63: 果盘 | D63: 个 | E63: 14.8 | F63: 1 | G63: =F63*E63 -> 14.8 | H63: =SUMIF($N$4:$BW$4,$H$4,$N63:$BW63) -> 0 | I63: =+E63*H63 -> 0 | J63: =SUMIF($N$4:$BW$4,$J$4,$N63:$BW63) -> 1 | K63: =+E63*J63 -> 14.8 | L63: =+F63+H63-J63 -> 0 | M63: =+E63*L63 -> 0 | Q63: 1
A64: 72 | B64: 花露水湿巾 | D64: 个 | E64: 0.033 | F64: 214 | G64: =F64*E64 -> 7.062 | H64: =SUMIF($N$4:$BW$4,$H$4,$N64:$BW64) -> 0 | I64: =+E64*H64 -> 0 | J64: =SUMIF($N$4:$BW$4,$J$4,$N64:$BW64) -> 39 | K64: =+E64*J64 -> 1.287 | L64: =+F64+H64-J64 -> 175 | M64: =+E64*L64 -> 5.775 | O64: 10 | U64: 5 | W64: 9 | AA64: 10 | AY64: 5
A65: 73 | B65: 椰子糖 | D65: 个 | E65: 0.0357 | F65: 350 | G65: =F65*E65 -> 12.495 | H65: =SUMIF($N$4:$BW$4,$H$4,$N65:$BW65) -> 0 | I65: =+E65*H65 -> 0 | J65: =SUMIF($N$4:$BW$4,$J$4,$N65:$BW65) -> 350 | K65: =+E65*J65 -> 12.495 | L65: =+F65+H65-J65 -> 0 | M65: =+E65*L65 -> 0 | Q65: 50 | W65: 50 | AE65: 50 | AY65: 100 | BC65: 100
A66: 75 | B66: 圣诞节包装纸 | D66: 个 | E66: 1.529 | F66: 10 | G66: =F66*E66 -> 15.29 | H66: =SUMIF($N$4:$BW$4,$H$4,$N66:$BW66) -> 0 | I66: =+E66*H66 -> 0 | J66: =SUMIF($N$4:$BW$4,$J$4,$N66:$BW66) -> 0 | K66: =+E66*J66 -> 0 | L66: =+F66+H66-J66 -> 10 | M66: =+E66*L66 -> 15.29
A67: 76 | B67: 礼袋 | D67: 个 | E67: 0.23 | F67: 937 | G67: =F67*E67 -> 215.51 | H67: =SUMIF($N$4:$BW$4,$H$4,$N67:$BW67) -> 0 | I67: =+E67*H67 -> 0 | J67: =SUMIF($N$4:$BW$4,$J$4,$N67:$BW67) -> 500 | K67: =+E67*J67 -> 115 | L67: =+F67+H67-J67 -> 437 | M67: =+E67*L67 -> 100.51 | S67: 50 | W67: 50 | AA67: 50 | AE67: 50 | AI67: 40 | AY67: 20 | BA67: 20 | BC67: 20 | BE67: 20 | BG67: 20 | BI67: 20 | BK67: 30 | BM67: 30 | BO67: 25 | BQ67: 25 | BS67: 30
A68: 97 | B68: 泡澡袋 | D68: 个 | E68: 0.495 | F68: 47 | G68: =F68*E68 -> 23.265 | H68: =SUMIF($N$4:$BW$4,$H$4,$N68:$BW68) -> 0 | I68: =+E68*H68 -> 0 | J68: =SUMIF($N$4:$BW$4,$J$4,$N68:$BW68) -> 47 | K68: =+E68*J68 -> 23.265 | L68: =+F68+H68-J68 -> 0 | M68: =+E68*L68 -> 0 | O68: 5 | Q68: 5 | U68: 7 | AA68: 10 | AC68: 10 | AE68: 10
A69: 98 | B69: 话梅糖 | D69: 袋 | E69: 0.031 | F69: 350 | G69: =F69*E69 -> 10.85 | H69: =SUMIF($N$4:$BW$4,$H$4,$N69:$BW69) -> 0 | I69: =+E69*H69 -> 0 | J69: =SUMIF($N$4:$BW$4,$J$4,$N69:$BW69) -> 350 | K69: =+E69*J69 -> 10.85 | L69: =+F69+H69-J69 -> 0 | M69: =+E69*L69 -> 0 | AA69: 50 | AE69: 50 | AI69: 40 | AU69: 10 | BA69: 100 | BG69: 100
A70: 99 | B70: 果汁硬糖 | D70: 个 | E70: 0.0992 | F70: 0 | G70: =F70*E70 -> 0 | H70: =SUMIF($N$4:$BW$4,$H$4,$N70:$BW70) -> 500 | I70: =+E70*H70 -> 49.6 | J70: =SUMIF($N$4:$BW$4,$J$4,$N70:$BW70) -> 300 | K70: =+E70*J70 -> 29.76 | L70: =+F70+H70-J70 -> 200 | M70: =+E70*L70 -> 19.84 | Z70: 500 | BK70: 300
A71: 100 | B71: 洗衣牌 | D71: 个 | E71: 0.12 | F71: 3870 | G71: =F71*E71 -> 464.4 | H71: =SUMIF($N$4:$BW$4,$H$4,$N71:$BW71) -> 0 | I71: =+E71*H71 -> 0 | J71: =SUMIF($N$4:$BW$4,$J$4,$N71:$BW71) -> 350 | K71: =+E71*J71 -> 42 | L71: =+F71+H71-J71 -> 3520 | M71: =+E71*L71 -> 422.4 | Q71: 100 | W71: 100 | AE71: 100 | BK71: 50
A72: 101 | B72: 卸妆湿巾 | D72: 个 | E72: 0.693 | F72: 0 | G72: =F72*E72 -> 0 | H72: =SUMIF($N$4:$BW$4,$H$4,$N72:$BW72) -> 0 | I72: =+E72*H72 -> 0 | J72: =SUMIF($N$4:$BW$4,$J$4,$N72:$BW72) -> 0 | K72: =+E72*J72 -> 0 | L72: =+F72+H72-J72 -> 0 | M72: =+E72*L72 -> 0
A73: 102 | B73: 茶包全季小种红 | D73: 包 | E73: 0.65 | F73: 49 | G73: =F73*E73 -> 31.85 | H73: =SUMIF($N$4:$BW$4,$H$4,$N73:$BW73) -> 15 | I73: =+E73*H73 -> 9.75 | J73: =SUMIF($N$4:$BW$4,$J$4,$N73:$BW73) -> 40 | K73: =+E73*J73 -> 26 | L73: =+F73+H73-J73 -> 24 | M73: =+E73*L73 -> 15.6 | X73: 15 | AA73: 15 | AE73: 15 | AU73: 10
A74: 103 | B74: 数据线 | D74: 根 | E74: 14.72 | F74: 0 | G74: =F74*E74 -> 0 | H74: =SUMIF($N$4:$BW$4,$H$4,$N74:$BW74) -> 5 | I74: =+E74*H74 -> 73.6 | J74: =SUMIF($N$4:$BW$4,$J$4,$N74:$BW74) -> 0 | K74: =+E74*J74 -> 0 | L74: =+F74+H74-J74 -> 5 | M74: =+E74*L74 -> 73.6 | AH74: 5
A75: 104 | B75: 咖啡糖 | D75: 个 | E75: 0.01693 | F75: 0 | G75: =F75*E75 -> 0 | H75: =SUMIF($N$4:$BW$4,$H$4,$N75:$BW75) -> 2000 | I75: =+E75*H75 -> 33.86 | J75: =SUMIF($N$4:$BW$4,$J$4,$N75:$BW75) -> 800 | K75: =+E75*J75 -> 13.544 | L75: =+F75+H75-J75 -> 1200 | M75: =+E75*L75 -> 20.316 | P75: 2000 | W75: 100 | AA75: 100 | AE75: 100 | BM75: 500
A76: 105 | B76: 雨伞 | D76: 把 | E76: 26.532 | F76: 0 | G76: =F76*E76 -> 0 | H76: =SUMIF($N$4:$BW$4,$H$4,$N76:$BW76) -> 10 | I76: =+E76*H76 -> 265.32 | J76: =SUMIF($N$4:$BW$4,$J$4,$N76:$BW76) -> 0 | K76: =+E76*J76 -> 0 | L76: =+F76+H76-J76 -> 10 | M76: =+E76*L76 -> 265.32 | AD76: 10
A77: 106 | B77: 洗脸巾 | D77: 个 | E77: 0.241 | F77: 30 | G77: =F77*E77 -> 7.23 | H77: =SUMIF($N$4:$BW$4,$H$4,$N77:$BW77) -> 0 | I77: =+E77*H77 -> 0 | J77: =SUMIF($N$4:$BW$4,$J$4,$N77:$BW77) -> 30 | K77: =+E77*J77 -> 7.23 | L77: =+F77+H77-J77 -> 0 | M77: =+E77*L77 -> 0 | Y77: 5 | AA77: 15 | AW77: 10
A78: 107 | B78: 咖啡伴侣 | D78: 个 | E78: 24.5 | F78: 0 | G78: =F78*E78 -> 0 | H78: =SUMIF($N$4:$BW$4,$H$4,$N78:$BW78) -> 4 | I78: =+E78*H78 -> 98 | J78: =SUMIF($N$4:$BW$4,$J$4,$N78:$BW78) -> 2 | K78: =+E78*J78 -> 49 | L78: =+F78+H78-J78 -> 2 | M78: =+E78*L78 -> 49 | AH78: 4 | BK78: 2
A79: 108 | B79: 咖啡豆 | D79: 袋 | E79: 33.5 | F79: 0 | G79: =F79*E79 -> 0 | H79: =SUMIF($N$4:$BW$4,$H$4,$N79:$BW79) -> 20 | I79: =+E79*H79 -> 670 | J79: =SUMIF($N$4:$BW$4,$J$4,$N79:$BW79) -> 4 | K79: =+E79*J79 -> 134 | L79: =+F79+H79-J79 -> 16 | M79: =+E79*L79 -> 536 | AD79: 20 | BM79: 2 | BO79: 1 | BQ79: 1
B80: 火柴3 | D80: 盒 | E80: 0.1864 | F80: 30 | G80: =F80*E80 -> 5.592 | H80: =SUMIF($N$4:$BW$4,$H$4,$N80:$BW80) -> 0 | I80: =+E80*H80 -> 0 | J80: =SUMIF($N$4:$BW$4,$J$4,$N80:$BW80) -> 30 | K80: =+E80*J80 -> 5.592 | L80: =+F80+H80-J80 -> 0 | M80: =+E80*L80 -> 0 | AA80: 10 | AE80: 10 | AG80: 10
A81: 109 | B81: 针线包 | D81: 个 | E81: 0.18 | F81: 180 | G81: =F81*E81 -> 32.4 | H81: =SUMIF($N$4:$BW$4,$H$4,$N81:$BW81) -> 0 | I81: =+E81*H81 -> 0 | J81: =SUMIF($N$4:$BW$4,$J$4,$N81:$BW81) -> 81 | K81: =+E81*J81 -> 14.58 | L81: =+F81+H81-J81 -> 99 | M81: =+E81*L81 -> 17.82 | O81: 5 | S81: 30 | U81: 30 | AU81: 3 | AW81: 4 | AY81: 1 | BA81: 1 | BC81: 4 | BE81: 3
A82: 110 | B82: 晨光K35黑色中性笔 | D82: 支 | E82: 0.9771 | F82: 30 | G82: =F82*E82 -> 29.313 | H82: =SUMIF($N$4:$BW$4,$H$4,$N82:$BW82) -> 0 | I82: =+E82*H82 -> 0 | J82: =SUMIF($N$4:$BW$4,$J$4,$N82:$BW82) -> 0 | K82: =+E82*J82 -> 0 | L82: =+F82+H82-J82 -> 30 | M82: =+E82*L82 -> 29.313
A83: 111 | B83: 印泥 | D83: 片 | E83: 9.15 | F83: 0 | G83: =F83*E83 -> 0 | H83: =SUMIF($N$4:$BW$4,$H$4,$N83:$BW83) -> 0 | I83: =+E83*H83 -> 0 | J83: =SUMIF($N$4:$BW$4,$J$4,$N83:$BW83) -> 0 | K83: =+E83*J83 -> 0 | L83: =+F83+H83-J83 -> 0 | M83: =+E83*L83 -> 0
A84: 112 | B84: 剃须刀（酒店） | D84: 个 | E84: 1.11 | F84: 0 | G84: =F84*E84 -> 0 | H84: =SUMIF($N$4:$BW$4,$H$4,$N84:$BW84) -> 0 | I84: =+E84*H84 -> 0 | J84: =SUMIF($N$4:$BW$4,$J$4,$N84:$BW84) -> 0 | K84: =+E84*J84 -> 0 | L84: =+F84+H84-J84 -> 0 | M84: =+E84*L84 -> 0
A85: 113 | B85: 青柠 | D85: 袋 | E85: 11.34 | F85: 0 | G85: =F85*E85 -> 0 | H85: =SUMIF($N$4:$BW$4,$H$4,$N85:$BW85) -> 0 | I85: =+E85*H85 -> 0 | J85: =SUMIF($N$4:$BW$4,$J$4,$N85:$BW85) -> 0 | K85: =+E85*J85 -> 0 | L85: =+F85+H85-J85 -> 0 | M85: =+E85*L85 -> 0
A86: 114 | B86: 未成年登记本 | D86: 本 | E86: 7.76 | F86: 2 | G86: =F86*E86 -> 15.52 | H86: =SUMIF($N$4:$BW$4,$H$4,$N86:$BW86) -> 0 | I86: =+E86*H86 -> 0 | J86: =SUMIF($N$4:$BW$4,$J$4,$N86:$BW86) -> 0 | K86: =+E86*J86 -> 0 | L86: =+F86+H86-J86 -> 2 | M86: =+E86*L86 -> 15.52
A87: 115 | B87: 抽纸盒 | D87: 个 | E87: 10.63 | F87: 0 | G87: =F87*E87 -> 0 | H87: =SUMIF($N$4:$BW$4,$H$4,$N87:$BW87) -> 0 | I87: =+E87*H87 -> 0 | J87: =SUMIF($N$4:$BW$4,$J$4,$N87:$BW87) -> 0 | K87: =+E87*J87 -> 0 | L87: =+F87+H87-J87 -> 0 | M87: =+E87*L87 -> 0
A88: 116 | B88: 旺旺果汁 | D88: 包 | E88: 0.6078 | F88: 0 | G88: =F88*E88 -> 0 | H88: =SUMIF($N$4:$BW$4,$H$4,$N88:$BW88) -> 0 | I88: =+E88*H88 -> 0 | J88: =SUMIF($N$4:$BW$4,$J$4,$N88:$BW88) -> 0 | K88: =+E88*J88 -> 0 | L88: =+F88+H88-J88 -> 0 | M88: =+E88*L88 -> 0
A89: 117 | B89: 一次性纸盘 | D89: 个 | E89: 0.34 | F89: 30 | G89: =F89*E89 -> 10.2 | H89: =SUMIF($N$4:$BW$4,$H$4,$N89:$BW89) -> 0 | I89: =+E89*H89 -> 0 | J89: =SUMIF($N$4:$BW$4,$J$4,$N89:$BW89) -> 10 | K89: =+E89*J89 -> 3.4 | L89: =+F89+H89-J89 -> 20 | M89: =+E89*L89 -> 6.8 | AY89: 10
A90: 118 | B90: 胶带 | D90: 个 | E90: 4.7 | F90: 4 | G90: =F90*E90 -> 18.8 | H90: =SUMIF($N$4:$BW$4,$H$4,$N90:$BW90) -> 0 | I90: =+E90*H90 -> 0 | J90: =SUMIF($N$4:$BW$4,$J$4,$N90:$BW90) -> 1 | K90: =+E90*J90 -> 4.7 | L90: =+F90+H90-J90 -> 3 | M90: =+E90*L90 -> 14.1 | BK90: 1
A91: 119 | B91: 电梯固体香薰 | D91: 个 | E91: 3.3 | F91: 18 | G91: =F91*E91 -> 59.4 | H91: =SUMIF($N$4:$BW$4,$H$4,$N91:$BW91) -> 0 | I91: =+E91*H91 -> 0 | J91: =SUMIF($N$4:$BW$4,$J$4,$N91:$BW91) -> 6 | K91: =+E91*J91 -> 19.8 | L91: =+F91+H91-J91 -> 12 | M91: =+E91*L91 -> 39.6 | AO91: 2 | AY91: 2 | BC91: 2
A92: 120 | B92: 转换器 | D92: 个 | E92: 17.31 | F92: 2 | G92: =F92*E92 -> 34.62 | H92: =SUMIF($N$4:$BW$4,$H$4,$N92:$BW92) -> 0 | I92: =+E92*H92 -> 0 | J92: =SUMIF($N$4:$BW$4,$J$4,$N92:$BW92) -> 2 | K92: =+E92*J92 -> 34.62 | L92: =+F92+H92-J92 -> 0 | M92: =+E92*L92 -> 0 | Y92: 2
A93: 121 | B93: 束口袋 | D93: 包 | E93: 0.543 | F93: 0 | G93: =F93*E93 -> 0 | H93: =SUMIF($N$4:$BW$4,$H$4,$N93:$BW93) -> 0 | I93: =+E93*H93 -> 0 | J93: =SUMIF($N$4:$BW$4,$J$4,$N93:$BW93) -> 0 | K93: =+E93*J93 -> 0 | L93: =+F93+H93-J93 -> 0 | M93: =+E93*L93 -> 0
A94: 122 | B94: 杀虫剂 | D94: 包 | E94: 13.9 | F94: 0 | G94: =F94*E94 -> 0 | H94: =SUMIF($N$4:$BW$4,$H$4,$N94:$BW94) -> 0 | I94: =+E94*H94 -> 0 | J94: =SUMIF($N$4:$BW$4,$J$4,$N94:$BW94) -> 0 | K94: =+E94*J94 -> 0 | L94: =+F94+H94-J94 -> 0 | M94: =+E94*L94 -> 0
A95: 123 | B95: 水果软糖 | D95: 包 | E95: 0.0466 | F95: 790 | G95: =F95*E95 -> 36.814 | H95: =SUMIF($N$4:$BW$4,$H$4,$N95:$BW95) -> 0 | I95: =+E95*H95 -> 0 | J95: =SUMIF($N$4:$BW$4,$J$4,$N95:$BW95) -> 790 | K95: =+E95*J95 -> 36.814 | L95: =+F95+H95-J95 -> 0 | M95: =+E95*L95 -> 0 | Y95: 150 | AA95: 150 | AC95: 200 | AE95: 290
A96: 124 | B96: 燕尾夹 | D96: 个 | E96: 14.89 | F96: 0 | G96: =F96*E96 -> 0 | H96: =SUMIF($N$4:$BW$4,$H$4,$N96:$BW96) -> 0 | I96: =+E96*H96 -> 0 | J96: =SUMIF($N$4:$BW$4,$J$4,$N96:$BW96) -> 0 | K96: =+E96*J96 -> 0 | L96: =+F96+H96-J96 -> 0 | M96: =+E96*L96 -> 0
A97: 125 | B97: 酸梅粉 | D97: 包 | E97: 17.227 | F97: 0 | G97: =F97*E97 -> 0 | H97: =SUMIF($N$4:$BW$4,$H$4,$N97:$BW97) -> 0 | I97: =+E97*H97 -> 0 | J97: =SUMIF($N$4:$BW$4,$J$4,$N97:$BW97) -> 0 | K97: =+E97*J97 -> 0 | L97: =+F97+H97-J97 -> 0 | M97: =+E97*L97 -> 0
A98: 126 | B98: 气球 | D98: 个 | E98: 0.216 | F98: 0 | G98: =F98*E98 -> 0 | H98: =SUMIF($N$4:$BW$4,$H$4,$N98:$BW98) -> 0 | I98: =+E98*H98 -> 0 | J98: =SUMIF($N$4:$BW$4,$J$4,$N98:$BW98) -> 0 | K98: =+E98*J98 -> 0 | L98: =+F98+H98-J98 -> 0 | M98: =+E98*L98 -> 0
A99: 127 | B99: 清风手帕纸 | D99: 个 | E99: 0.226 | F99: 0 | G99: =F99*E99 -> 0 | H99: =SUMIF($N$4:$BW$4,$H$4,$N99:$BW99) -> 0 | I99: =+E99*H99 -> 0 | J99: =SUMIF($N$4:$BW$4,$J$4,$N99:$BW99) -> 0 | K99: =+E99*J99 -> 0 | L99: =+F99+H99-J99 -> 0 | M99: =+E99*L99 -> 0
A100: 128 | B100: 香薰石膏 | D100: 个 | E100: 1.373 | F100: 0 | G100: =F100*E100 -> 0 | H100: =SUMIF($N$4:$BW$4,$H$4,$N100:$BW100) -> 0 | I100: =+E100*H100 -> 0 | J100: =SUMIF($N$4:$BW$4,$J$4,$N100:$BW100) -> 0 | K100: =+E100*J100 -> 0 | L100: =+F100+H100-J100 -> 0 | M100: =+E100*L100 -> 0
...

Sheet 会员卡提成录入
B1: 前台会员卡提成明细
B2: 酒店名称：
A3: 序号 | B3: 人员姓名 | C3: 平台 | D3: 单位 | E3: 单价（根据实际情况填写） | G3: 出库金额 | H3: 1号 | I3: 2号 | J3: 3号 | K3: 4号 | L3: 5号 | M3: 6号 | N3: 7号 | O3: 8号 | P3: 9号 | Q3: 10号 | R3: 11号 | S3: 12号 | T3: 13号 | U3: 14号 | V3: 15号 | W3: 16号 | X3: 17号 | Y3: 18号 | Z3: 19号 | AA3: 20号 | AB3: 21号 | AC3: 22号 | AD3: 23号 | AE3: 24号 | AF3: 25号 | AG3: 26号 | AH3: 27号 | AI3: 28号 | AJ3: 29号 | AK3: 30号 | AL3: 31号
F4: 张数 | H4: 张数 | I4: 张数 | J4: 张数 | K4: 张数 | L4: 张数 | M4: 张数 | N4: 张数 | O4: 张数 | P4: 张数 | Q4: 张数 | R4: 张数 | S4: 张数 | T4: 张数 | U4: 张数 | V4: 张数 | W4: 张数 | X4: 张数 | Y4: 张数 | Z4: 张数 | AA4: 张数 | AB4: 张数 | AC4: 张数 | AD4: 张数 | AE4: 张数 | AF4: 张数 | AG4: 张数 | AH4: 张数 | AI4: 张数 | AJ4: 张数 | AK4: 张数 | AL4: 张数
A5: 1 | B5: 李龙梅 | C5: 金卡 | D5: 张 | E5: 11 | F5: =SUMIF($H$4:$AL$4,$F$4,$H5:$AL5) -> 0 | G5: =+E5*F5 -> 0
A6: 2 | B6: 李龙梅 | C6: 银卡 | D6: 张 | E6: 5 | F6: =SUMIF($H$4:$AL$4,$F$4,$H6:$AL6) -> 1 | G6: =+E6*F6 -> 5 | O6: 1
A7: 3 | B7: 李龙梅 | C7: 白金卡 | D7: 张 | E7: 20 | F7: =SUMIF($H$4:$AL$4,$F$4,$H7:$AL7) -> 0 | G7: =+E7*F7 -> 0
A8: 4 | B8: 王增 | C8: 金卡 | D8: 张 | E8: 11 | F8: =SUMIF($H$4:$AL$4,$F$4,$H8:$AL8) -> 20 | G8: =+E8*F8 -> 220 | L8: 4 | N8: 1 | R8: 2 | S8: 2 | Y8: 1 | AD8: 1 | AE8: 2 | AG8: 1 | AK8: 2 | AL8: 4
A9: 5 | B9: 王增 | C9: 银卡 | D9: 张 | E9: 5 | F9: =SUMIF($H$4:$AL$4,$F$4,$H9:$AL9) -> 25 | G9: =+E9*F9 -> 125 | L9: 1 | N9: 3 | O9: 1 | Q9: 1 | R9: 3 | S9: 2 | U9: 1 | V9: 3 | X9: 4 | Y9: 1 | AA9: 1 | AD9: 1 | AH9: 1 | AK9: 2
A10: 5 | B10: 王增 | C10: 白金卡 | D10: 张 | E10: 20 | F10: =SUMIF($H$4:$AL$4,$F$4,$H10:$AL10) -> 1 | G10: =+E10*F10 -> 20 | AA10: 1
A11: 5 | B11: 翟芮瑶 | C11: 金卡 | D11: 张 | E11: 11 | F11: =SUMIF($H$4:$AL$4,$F$4,$H11:$AL11) -> 9 | G11: =+E11*F11 -> 99 | K11: 2 | Q11: 1 | W11: 2 | AC11: 2 | AI11: 1 | AJ11: 1
A12: 5 | B12: 翟芮瑶 | C12: 银卡 | D12: 张 | E12: 5 | F12: =SUMIF($H$4:$AL$4,$F$4,$H12:$AL12) -> 11 | G12: =+E12*F12 -> 55 | K12: 2 | P12: 2 | Q12: 1 | AB12: 1 | AD12: 2 | AE12: 1 | AI12: 2
A13: 9 | B13: 翟芮瑶 | C13: 白金卡 | D13: 张 | E13: 20 | F13: =SUMIF($H$4:$AL$4,$F$4,$H13:$AL13) -> 1 | G13: =+E13*F13 -> 20 | Q13: 1
A14: 10 | B14: 孙源 | C14: 金卡 | D14: 张 | E14: 11 | F14: =SUMIF($H$4:$AL$4,$F$4,$H14:$AL14) -> 7 | G14: =+E14*F14 -> 77 | H14: 1 | J14: 2 | L14: 1 | N14: 1 | AK14: 2
A15: 11 | B15: 孙源 | C15: 银卡 | D15: 张 | E15: 5 | F15: =SUMIF($H$4:$AL$4,$F$4,$H15:$AL15) -> 12 | G15: =+E15*F15 -> 60 | M15: 1 | P15: 4 | T15: 1 | V15: 3 | AB15: 3
A16: 12 | B16: 孙源 | C16: 白金卡 | D16: 张 | E16: 20 | F16: =SUMIF($H$4:$AL$4,$F$4,$H16:$AL16) -> 0 | G16: =+E16*F16 -> 0
A17: 13 | B17: 张馨月 | C17: 金卡 | D17: 张 | E17: 11 | F17: =SUMIF($H$4:$AL$4,$F$4,$H17:$AL17) -> 3 | G17: =+E17*F17 -> 33 | O17: 2 | X17: 1
A18: 14 | B18: 张馨月 | C18: 银卡 | D18: 张 | E18: 5 | F18: =SUMIF($H$4:$AL$4,$F$4,$H18:$AL18) -> 5 | G18: =+E18*F18 -> 25 | K18: 1 | N18: 1 | Q18: 1 | AG18: 1 | AJ18: 1
A19: 15 | B19: 张馨月 | C19: 白金卡 | D19: 张 | E19: 20 | F19: =SUMIF($H$4:$AL$4,$F$4,$H19:$AL19) -> 0 | G19: =+E19*F19 -> 0
A20: 16 | B20: 宋雨霏 | C20: 金卡 | D20: 张 | E20: 11 | F20: =SUMIF($H$4:$AL$4,$F$4,$H20:$AL20) -> 0 | G20: =+E20*F20 -> 0
A21: 17 | B21: 宋雨霏 | C21: 银卡 | D21: 张 | E21: 5 | F21: =SUMIF($H$4:$AL$4,$F$4,$H21:$AL21) -> 0 | G21: =+E21*F21 -> 0
A22: 18 | B22: 宋雨霏 | C22: 白金卡 | D22: 张 | E22: 20 | F22: =SUMIF($H$4:$AL$4,$F$4,$H22:$AL22) -> 1 | G22: =+E22*F22 -> 20 | I22: 1
A23: 19 | B23: 于子杭 | C23: 金卡 | D23: 张 | E23: 11 | F23: =SUMIF($H$4:$AL$4,$F$4,$H23:$AL23) -> 1 | G23: =+E23*F23 -> 11 | V23: 1
A24: 20 | B24: 于子杭 | C24: 银卡 | D24: 张 | E24: 5 | F24: =SUMIF($H$4:$AL$4,$F$4,$H24:$AL24) -> 1 | G24: =+E24*F24 -> 5 | AL24: 1
A25: 21 | B25: 于子杭 | C25: 白金卡 | D25: 张 | E25: 20 | F25: =SUMIF($H$4:$AL$4,$F$4,$H25:$AL25) -> 1 | G25: =+E25*F25 -> 20 | W25: 1
A26: 22 | B26: 徐嘉瑜 | C26: 金卡 | D26: 张 | E26: 11 | F26: =SUMIF($H$4:$AL$4,$F$4,$H26:$AL26) -> 5 | G26: =+E26*F26 -> 55 | N26: 1 | O26: 1 | U26: 1 | AC26: 1 | AF26: 1
A27: 23 | B27: 徐嘉瑜 | C27: 银卡 | D27: 张 | E27: 5 | F27: =SUMIF($H$4:$AL$4,$F$4,$H27:$AL27) -> 9 | G27: =+E27*F27 -> 45 | O27: 3 | P27: 1 | Z27: 1 | AF27: 1 | AL27: 3
A28: 24 | B28: 徐嘉瑜 | C28: 白金卡 | D28: 张 | E28: 20 | F28: =SUMIF($H$4:$AL$4,$F$4,$H28:$AL28) -> 0 | G28: =+E28*F28 -> 0
A29: 25 | B29: 吴怡 | C29: 金卡 | D29: 张 | E29: 11 | F29: =SUMIF($H$4:$AL$4,$F$4,$H29:$AL29) -> 2 | G29: =+E29*F29 -> 22 | W29: 1 | AG29: 1
A30: 26 | B30: 吴怡 | C30: 银卡 | D30: 张 | E30: 5 | F30: =SUMIF($H$4:$AL$4,$F$4,$H30:$AL30) -> 8 | G30: =+E30*F30 -> 40 | H30: 2 | K30: 1 | Q30: 2 | T30: 1 | AA30: 1 | AL30: 1
A31: 27 | B31: 吴怡 | C31: 白金卡 | D31: 张 | E31: 20 | F31: =SUMIF($H$4:$AL$4,$F$4,$H31:$AL31) -> 0 | G31: =+E31*F31 -> 0
A32: 28 | B32: 刘昕 | C32: 金卡 | D32: 张 | E32: 11 | F32: =SUMIF($H$4:$AL$4,$F$4,$H32:$AL32) -> 0 | G32: =+E32*F32 -> 0
A33: 29 | B33: 刘昕 | C33: 银卡 | D33: 张 | E33: 5 | F33: =SUMIF($H$4:$AL$4,$F$4,$H33:$AL33) -> 0 | G33: =+E33*F33 -> 0
A34: 30 | B34: 刘昕 | C34: 白金卡 | D34: 张 | E34: 20 | F34: =SUMIF($H$4:$AL$4,$F$4,$H34:$AL34) -> 0 | G34: =+E34*F34 -> 0
A35: 31 | F35: =SUMIF($H$4:$AL$4,$F$4,$H35:$AL35) -> 0 | G35: =+E35*F35 -> 0
A36: 32 | F36: =SUMIF($H$4:$AL$4,$F$4,$H36:$AL36) -> 0 | G36: =+E36*F36 -> 0
A37: 33 | F37: =SUMIF($H$4:$AL$4,$F$4,$H37:$AL37) -> 0 | G37: =+E37*F37 -> 0
A38: 34 | F38: =SUMIF($H$4:$AL$4,$F$4,$H38:$AL38) -> 0 | G38: =+E38*F38 -> 0
A39: 35 | F39: =SUMIF($H$4:$AL$4,$F$4,$H39:$AL39) -> 0 | G39: =+E39*F39 -> 0
A40: 36 | F40: =SUMIF($H$4:$AL$4,$F$4,$H40:$AL40) -> 0 | G40: =+E40*F40 -> 0
A41: 37 | F41: =SUMIF($H$4:$AL$4,$F$4,$H41:$AL41) -> 0 | G41: =+E41*F41 -> 0
A42: 38 | F42: =SUMIF($H$4:$AL$4,$F$4,$H42:$AL42) -> 0 | G42: =+E42*F42 -> 0
A43: 39 | F43: =SUMIF($H$4:$AL$4,$F$4,$H43:$AL43) -> 0 | G43: =+E43*F43 -> 0
A44: 40 | F44: =SUMIF($H$4:$AL$4,$F$4,$H44:$AL44) -> 0 | G44: =+E44*F44 -> 0
A45: 41 | F45: =SUMIF($H$4:$AL$4,$F$4,$H45:$AL45) -> 0 | G45: =+E45*F45 -> 0
A46: 42 | F46: =SUMIF($H$4:$AL$4,$F$4,$H46:$AL46) -> 0 | G46: =+E46*F46 -> 0
... A74: 70 | F74: =SUMIF($H$4:$AL$4,$F$4,$H74:$AL74) -> 0 | G74: =+E74*F74 -> 0
B75: 会员卡提成 | F75: =SUMIF($H$4:$AL$4,$F$4,$H75:$AL75) -> 123 | G75: =SUM(G5:G74) -> 957 | H75: =SUM(H5:H74) -> 3 | I75: =SUM(I5:I74) -> 1 | J75: =SUM(J5:J74) -> 2 | K75: =SUM(K5:K74) -> 6 | L75: =SUM(L5:L74) -> 6 | M75: =SUM(M5:M74) -> 1 | N75: =SUM(N5:N74) -> 7 | ... AL75: =SUM(AL5:AL74) -> 9

Sheet 商品录入
B1: 前台小商品出入库表
B2: 酒店名称： | N2: 周期：
A3: 序号 | B3: 货品名称 | C3: 规格型号 | D3: 单位 | E3: 单价 | F3: 上月 结存 | G3: 结存金额 | H3: 入库合计 | I3: 入库金额 | J3: 出库合计 | K3: 出库金额 | L3: 结存合计 | M3: 结存金额 | N3: 1号 | P3: 2号 | R3: 3号 | T3: 4号 | V3: 5号 | X3: 6号 | Z3: 7号 | AB3: 8号 | AD3: 9号 | AF3: 10号 | AH3: 11号 | AJ3: 12号 | AL3: 13号 | AN3: 14号 | AP3: 15号 | AR3: 16号 | AT3: 17号 | AV3: 18号 | AX3: 19号 | AZ3: 20号 | BB3: 21号 | BD3: 22号 | BF3: 23号 | BH3: 24号 | BJ3: 25号 | BL3: 26号 | BN3: 27号 | BP3: 28号 | BR3: 29号 | BT3: 30号 | BV3: 31号
H4: 入库 | I4: 金额 | J4: 出库 | L4: 结存 | N4: 入库 | O4: 出库 | P4: 入库 | Q4: 出库 | R4: 入库 | S4: 出库 | T4: 入库 | U4: 出库 | V4: 入库 | W4: 出库 | X4: 入库 | Y4: 出库 | Z4: 入库 | AA4: 出库 | AB4: 入库 | AC4: 出库 | AD4: 入库 | AE4: 出库 | AF4: 入库 | AG4: 出库 | AH4: 入库 | AI4: 出库 | AJ4: 入库 | AK4: 出库 | AL4: 入库 | AM4: 出库 | AN4: 入库 | AO4: 出库 | AP4: 入库 | AQ4: 出库 | AR4: 入库 | AS4: 出库 | AT4: 入库 | AU4: 出库 | AV4: 入库 | AW4: 出库 | AX4: 入库 | AY4: 出库 | AZ4: 入库 | BA4: 出库 | BB4: 入库 | BC4: 出库 | BD4: 入库 | BE4: 出库 | BF4: 入库 | BG4: 出库 | BH4: 入库 | BI4: 出库 | BJ4: 入库 | BK4: 出库 | BL4: 入库 | BM4: 出库 | BN4: 入库 | BO4: 出库 | BP4: 入库 | BQ4: 出库 | BR4: 入库 | BS4: 出库 | BT4: 入库 | BU4: 出库 | BV4: 入库 | BW4: 出库
A5: 1 | B5: 洗手液 | C5: 瓶 | E5: 7.9 | F5: 0 | G5: =F5*E5 -> 0 | H5: =SUMIF($N$4:$O$4,$H$4,$N5:$O5) -> 33 | I5: =+E5*H5 -> 260.7 | J5: =SUMIF($N$4:$BW$4,$J$4,$N5:$BW5) -> 1 | K5: =+E5*J5 -> 7.9 | L5: =+F5+H5-J5 -> 32 | M5: =+E5*L5 -> 252.8 | N5: 33 | Q5: 1
A6: 2 | B6: 洗发水 | C6: 瓶 | E6: 13.5 | F6: 0 | G6: =F6*E6 -> 0 | H6: =SUMIF($N$4:$O$4,$H$4,$N6:$O6) -> 27 | I6: =+E6*H6 -> 364.5 | J6: =SUMIF($N$4:$BW$4,$J$4,$N6:$BW6) -> 0 | K6: =+E6*J6 -> 0 | L6: =+F6+H6-J6 -> 27 | M6: =+E6*L6 -> 364.5 | N6: 27
A7: 3 | B7: 护发素 | C7: 瓶 | E7: 13.5 | F7: 0 | G7: =F7*E7 -> 0 | H7: =SUMIF($N$4:$O$4,$H$4,$N7:$O7) -> 28 | I7: =+E7*H7 -> 378 | J7: =SUMIF($N$4:$BW$4,$J$4,$N7:$BW7) -> 0 | K7: =+E7*J7 -> 0 | L7: =+F7+H7-J7 -> 28 | M7: =+E7*L7 -> 378 | N7: 28
A8: 4 | B8: 沐浴露 | C8: 瓶 | E8: 13.5 | F8: 0 | G8: =F8*E8 -> 0 | H8: =SUMIF($N$4:$O$4,$H$4,$N8:$O8) -> 30 | I8: =+E8*H8 -> 405 | J8: =SUMIF($N$4:$BW$4,$J$4,$N8:$BW8) -> 0 | K8: =+E8*J8 -> 0 | L8: =+F8+H8-J8 -> 30 | M8: =+E8*L8 -> 405 | N8: 30
A9: 5 | B9: 乳胶枕 | C9: 个 | E9: 66 | F9: 0 | G9: =F9*E9 -> 0 | H9: =SUMIF($N$4:$O$4,$H$4,$N9:$O9) -> 22 | I9: =+E9*H9 -> 1452 | J9: =SUMIF($N$4:$BW$4,$J$4,$N9:$BW9) -> 3 | K9: =+E9*J9 -> 198 | L9: =+F9+H9-J9 -> 19 | M9: =+E9*L9 -> 1254 | N9: 22 | AQ9: 1 | BA9: 2
A10: 6 | B10: 羽绒枕 | C10: 个 | E10: 113.5 | F10: 0 | G10: =F10*E10 -> 0 | H10: =SUMIF($N$4:$O$4,$H$4,$N10:$O10) -> 10 | I10: =+E10*H10 -> 1135 | J10: =SUMIF($N$4:$BW$4,$J$4,$N10:$BW10) -> 0 | K10: =+E10*J10 -> 0 | L10: =+F10+H10-J10 -> 10 | M10: =+E10*L10 -> 1135 | N10: 10
A11: 7 | B11: 香薰液 | C11: 瓶 | E11: 176 | F11: 0 | G11: =F11*E11 -> 0 | H11: =SUMIF($N$4:$O$4,$H$4,$N11:$O11) -> 9 | I11: =+E11*H11 -> 1584 | J11: =SUMIF($N$4:$BW$4,$J$4,$N11:$BW11) -> 0 | K11: =+E11*J11 -> 0 | L11: =+F11+H11-J11 -> 9 | M11: =+E11*L11 -> 1584 | N11: 9
A12: 8 | E12: 0 | F12: 0 | G12: =F12*E12 -> 0 | H12: =SUMIF($N$4:$O$4,$H$4,$N12:$O12) -> 0 | I12: =+E12*H12 -> 0 | J12: =SUMIF($N$4:$BW$4,$J$4,$N12:$BW12) -> 0 | K12: =+E12*J12 -> 0 | L12: =+F12+H12-J12 -> 0 | M12: =+E12*L12 -> 0
A13: 9 | E13: 0 | F13: 0 | G13: =F13*E13 -> 0 | H13: =SUMIF($N$4:$O$4,$H$4,$N13:$O13) -> 0 | I13: =+E13*H13 -> 0 | J13: =SUMIF($N$4:$BW$4,$J$4,$N13:$BW13) -> 0 | K13: =+E13*J13 -> 0 | L13: =+F13+H13-J13 -> 0 | M13: =+E13*L13 -> 0
A14: 10 | E14: 0 | F14: 0 | G14: =F14*E14 -> 0 | H14: =SUMIF($N$4:$O$4,$H$4,$N14:$O14) -> 0 | I14: =+E14*H14 -> 0 | J14: =SUMIF($N$4:$BW$4,$J$4,$N14:$BW14) -> 0 | K14: =+E14*J14 -> 0 | L14: =+F14+H14-J14 -> 0 | M14: =+E14*L14 -> 0
A15: 11 | E15: 0 | F15: 0 | G15: =F15*E15 -> 0 | H15: =SUMIF($N$4:$O$4,$H$4,$N15:$O15) -> 0 | I15: =+E15*H15 -> 0 | J15: =SUMIF($N$4:$BW$4,$J$4,$N15:$BW15) -> 0 | K15: =+E15*J15 -> 0 | L15: =+F15+H15-J15 -> 0 | M15: =+E15*L15 -> 0
A16: 12 | E16: 0 | F16: 0 | G16: =F16*E16 -> 0 | H16: =SUMIF($N$4:$O$4,$H$4,$N16:$O16) -> 0 | I16: =+E16*H16 -> 0 | J16: =SUMIF($N$4:$BW$4,$J$4,$N16:$BW16) -> 0 | K16: =+E16*J16 -> 0 | L16: =+F16+H16-J16 -> 0 | M16: =+E16*L16 -> 0
A17: 13 | E17: 0 | F17: 0 | G17: =F17*E17 -> 0 | H17: =SUMIF($N$4:$O$4,$H$4,$N17:$O17) -> 0 | I17: =+E17*H17 -> 0 | J17: =SUMIF($N$4:$BW$4,$J$4,$N17:$BW17) -> 0 | K17: =+E17*J17 -> 0 | L17: =+F17+H17-J17 -> 0 | M17: =+E17*L17 -> 0
A18: 14 | E18: 0 | F18: 0 | G18: =F18*E18 -> 0 | H18: =SUMIF($N$4:$O$4,$H$4,$N18:$O18) -> 0 | I18: =+E18*H18 -> 0 | J18: =SUMIF($N$4:$BW$4,$J$4,$N18:$BW18) -> 0 | K18: =+E18*J18 -> 0 | L18: =+F18+H18-J18 -> 0 | M18: =+E18*L18 -> 0
A19: 15 | E19: 0 | F19: 0 | G19: =F19*E19 -> 0 | H19: =SUMIF($N$4:$O$4,$H$4,$N19:$O19) -> 0 | I19: =+E19*H19 -> 0 | J19: =SUMIF($N$4:$BW$4,$J$4,$N19:$BW19) -> 0 | K19: =+E19*J19 -> 0 | L19: =+F19+H19-J19 -> 0 | M19: =+E19*L19 -> 0
A20: 16 | E20: 0 | F20: 0 | G20: =F20*E20 -> 0 | H20: =SUMIF($N$4:$O$4,$H$4,$N20:$O20) -> 0 | I20: =+E20*H20 -> 0 | J20: =SUMIF($N$4:$BW$4,$J$4,$N20:$BW20) -> 0 | K20: =+E20*J20 -> 0 | L20: =+F20+H20-J20 -> 0 | M20: =+E20*L20 -> 0
A21: 17 | E21: 0 | F21: 0 | G21: =F21*E21 -> 0 | H21: =SUMIF($N$4:$O$4,$H$4,$N21:$O21) -> 0 | I21: =+E21*H21 -> 0 | J21: =SUMIF($N$4:$BW$4,$J$4,$N21:$BW21) -> 0 | K21: =+E21*J21 -> 0 | L21: =+F21+H21-J21 -> 0 | M21: =+E21*L21 -> 0
A22: 18 | F22: 0 | G22: =F22*E22 -> 0 | H22: =SUMIF($N$4:$O$4,$H$4,$N22:$O22) -> 0 | I22: =+E22*H22 -> 0 | J22: =SUMIF($N$4:$BW$4,$J$4,$N22:$BW22) -> 0 | K22: =+E22*J22 -> 0 | L22: =+F22+H22-J22 -> 0 | M22: =+E22*L22 -> 0
A23: 19 | F23: 0 | G23: =F23*E23 -> 0 | H23: =SUMIF($N$4:$O$4,$H$4,$N23:$O23) -> 0 | I23: =+E23*H23 -> 0 | J23: =SUMIF($N$4:$BW$4,$J$4,$N23:$BW23) -> 0 | K23: =+E23*J23 -> 0 | L23: =+F23+H23-J23 -> 0 | M23: =+E23*L23 -> 0
A24: 20 | F24: 0 | G24: =F24*E24 -> 0 | H24: =SUMIF($N$4:$O$4,$H$4,$N24:$O24) -> 0 | I24: =+E24*H24 -> 0 | J24: =SUMIF($N$4:$BW$4,$J$4,$N24:$BW24) -> 0 | K24: =+E24*J24 -> 0 | L24: 0 | M24: =+E24*L24 -> 0
A25: 21 | F25: 0 | G25: =F25*E25 -> 0 | H25: =SUMIF($N$4:$O$4,$H$4,$N25:$O25) -> 0 | I25: =+E25*H25 -> 0 | J25: =SUMIF($N$4:$BW$4,$J$4,$N25:$BW25) -> 0 | K25: =+E25*J25 -> 0 | L25: =+F25+H25-J25 -> 0 | M25: =+E25*L25 -> 0
A26: 22 | F26: 0 | G26: =F26*E26 -> 0 | H26: =SUMIF($N$4:$O$4,$H$4,$N26:$O26) -> 0 | I26: =+E26*H26 -> 0 | J26: =SUMIF($N$4:$BW$4,$J$4,$N26:$BW26) -> 0 | K26: =+E26*J26 -> 0 | L26: =+F26+H26-J26 -> 0 | M26: =+E26*L26 -> 0
A27: 23 | F27: 0 | G27: =F27*E27 -> 0 | H27: =SUMIF($N$4:$O$4,$H$4,$N27:$O27) -> 0 | I27: =+E27*H27 -> 0 | J27: =SUMIF($N$4:$BW$4,$J$4,$N27:$BW27) -> 0 | K27: =+E27*J27 -> 0 | L27: =+F27+H27-J27 -> 0 | M27: =+E27*L27 -> 0
A28: 24 | F28: 0 | G28: =F28*E28 -> 0 | H28: =SUMIF($N$4:$O$4,$H$4,$N28:$O28) -> 0 | I28: =+E28*H28 -> 0 | J28: =SUMIF($N$4:$BW$4,$J$4,$N28:$BW28) -> 0 | K28: =+E28*J28 -> 0 | L28: =+F28+H28-J28 -> 0 | M28: =+E28*L28 -> 0
A29: 25 | F29: 0 | G29: =F29*E29 -> 0 | H29: =SUMIF($N$4:$O$4,$H$4,$N29:$O29) -> 0 | I29: =+E29*H29 -> 0 | J29: =SUMIF($N$4:$BW$4,$J$4,$N29:$BW29) -> 0 | K29: =+E29*J29 -> 0 | L29: =+F29+H29-J29 -> 0 | M29: =+E29*L29 -> 0
A30: 26 | F30: 0 | G30: =F30*E30 -> 0 | H30: =SUMIF($N$4:$O$4,$H$4,$N30:$O30) -> 0 | I30: =+E30*H30 -> 0 | J30: =SUMIF($N$4:$BW$4,$J$4,$N30:$BW30) -> 0 | K30: =+E30*J30 -> 0 | L30: =+F30+H30-J30 -> 0 | M30: =+E30*L30 -> 0
A31: 27 | F31: 0 | G31: =F31*E31 -> 0 | H31: =SUMIF($N$4:$O$4,$H$4,$N31:$O31) -> 0 | I31: =+E31*H31 -> 0 | J31: =SUMIF($N$4:$BW$4,$J$4,$N31:$BW31) -> 0 | K31: =+E31*J31 -> 0 | L31: =+F31+H31-J31 -> 0 | M31: =+E31*L31 -> 0
A32: 28 | F32: 0 | G32: =F32*E32 -> 0 | H32: =SUMIF($N$4:$O$4,$H$4,$N32:$O32) -> 0 | I32: =+E32*H32 -> 0 | J32: =SUMIF($N$4:$BW$4,$J$4,$N32:$BW32) -> 0 | K32: =+E32*J32 -> 0 | L32: =+F32+H32-J32 -> 0 | M32: =+E32*L32 -> 0
A33: 29 | F33: 0 | G33: =F33*E33 -> 0 | H33: =SUMIF($N$4:$O$4,$H$4,$N33:$O33) -> 0 | I33: =+E33*H33 -> 0 | J33: =SUMIF($N$4:$BW$4,$J$4,$N33:$BW33) -> 0 | K33: =+E33*J33 -> 0 | L33: =+F33+H33-J33 -> 0 | M33: =+E33*L33 -> 0
A34: 30 | F34: 0 | G34: =F34*E34 -> 0 | H34: =SUMIF($N$4:$O$4,$H$4,$N34:$O34) -> 0 | I34: =+E34*H34 -> 0 | J34: =SUMIF($N$4:$BW$4,$J$4,$N34:$BW34) -> 0 | K34: =+E34*J34 -> 0 | L34: =+F34+H34-J34 -> 0 | M34: =+E34*L34 -> 0
A35: 31 | F35: 0 | G35: =F35*E35 -> 0 | H35: =SUMIF($N$4:$O$4,$H$4,$N35:$O35) -> 0 | I35: =+E35*H35 -> 0 | J35: =SUMIF($N$4:$BW$4,$J$4,$N35:$BW35) -> 0 | K35: =+E35*J35 -> 0 | L35: =+F35+H35-J35 -> 0 | M35: =+E35*L35 -> 0
A36: 32 | F36: 0 | G36: =F36*E36 -> 0 | H36: =SUMIF($N$4:$O$4,$H$4,$N36:$O36) -> 0 | I36: =+E36*H36 -> 0 | J36: =SUMIF($N$4:$BW$4,$J$4,$N36:$BW36) -> 0 | K36: =+E36*J36 -> 0 | L36: =+F36+H36-J36 -> 0 | M36: =+E36*L36 -> 0
... A42: 38 | F42: 0 | G42: =F42*E42 -> 0 | H42: =SUMIF($N$4:$O$4,$H$4,$N42:$O42) -> 0 | I42: =+E42*H42 -> 0 | J42: =SUMIF($N$4:$BW$4,$J$4,$N42:$BW42) -> 0 | K42: =+E42*J42 -> 0 | L42: =+F42+H42-J42 -> 0 | M42: =+E42*L42 -> 0
A43: 39 | F43: 0 | G43: =+E43*F43 -> 0 | H43: =SUMIF($N$4:$O$4,$H$4,$N43:$O43) -> 0 | I43: =+E43*H43 -> 0 | J43: =SUMIF($N$4:$BW$4,$J$4,$N43:$BW43) -> 0 | K43: =+E43*J43 -> 0 | L43: =+F43+H43-J43 -> 0 | M43: =+E43*L43 -> 0
A44: 40 | G44: =+E44*F44 -> 0 | H44: =SUMIF($N$4:$O$4,$H$4,$N44:$O44) -> 0 | I44: =+E44*H44 -> 0 | J44: =SUMIF($N$4:$BW$4,$J$4,$N44:$BW44) -> 0 | K44: =+E44*J44 -> 0 | L44: =+F44+H44-J44 -> 0 | M44: =+E44*L44 -> 0
A45: 41 | G45: =+E45*F45 -> 0 | H45: =SUMIF($N$4:$O$4,$H$4,$N45:$O45) -> 0 | I45: =+E45*H45 -> 0 | J45: =SUMIF($N$4:$BW$4,$J$4,$N45:$BW45) -> 0 | K45: =+E45*J45 -> 0 | L45: =+F45+H45-J45 -> 0 | M45: =+E45*L45 -> 0
A46: 42 | G46: =+E46*F46 -> 0 | H46: =SUMIF($N$4:$O$4,$H$4,$N46:$O46) -> 0 | I46: =+E46*H46 -> 0 | J46: =SUMIF($N$4:$BW$4,$J$4,$N46:$BW46) -> 0 | K46: =+E46*J46 -> 0 | L46: =+F46+H46-J46 -> 0 | M46: =+E46*L46 -> 0
A47: 43 | G47: =+E47*F47 -> 0 | H47: =SUMIF($N$4:$O$4,$H$4,$N47:$O47) -> 0 | I47: =+E47*H47 -> 0 | J47: =SUMIF($N$4:$BW$4,$J$4,$N47:$BW47) -> 0 | K47: =+E47*J47 -> 0 | L47: =+F47+H47-J47 -> 0 | M47: =+E47*L47 -> 0
A48: 44 | G48: =+E48*F48 -> 0 | H48: =SUMIF($N$4:$O$4,$H$4,$N48:$O48) -> 0 | I48: =+E48*H48 -> 0 | J48: =SUMIF($N$4:$BW$4,$J$4,$N48:$BW48) -> 0 | K48: =+E48*J48 -> 0 | L48: =+F48+H48-J48 -> 0 | M48: =+E48*L48 -> 0
A49: 45 | G49: =+E49*F49 -> 0 | H49: =SUMIF($N$4:$O$4,$H$4,$N49:$O49) -> 0 | I49: =+E49*H49 -> 0 | J49: =SUMIF($N$4:$BW$4,$J$4,$N49:$BW49) -> 0 | K49: =+E49*J49 -> 0 | L49: =+F49+H49-J49 -> 0 | M49: =+E49*L49 -> 0
A50: 46 | G50: =+E50*F50 -> 0 | H50: =SUMIF($N$4:$O$4,$H$4,$N50:$O50) -> 0 | I50: =+E50*H50 -> 0 | J50: =SUMIF($N$4:$BW$4,$J$4,$N50:$BW50) -> 0 | K50: =+E50*J50 -> 0 | L50: =+F50+H50-J50 -> 0 | M50: =+E50*L50 -> 0
A51: 47 | G51: =+E51*F51 -> 0 | H51: =SUMIF($N$4:$O$4,$H$4,$N51:$O51) -> 0 | I51: =+E51*H51 -> 0 | J51: =SUMIF($N$4:$BW$4,$J$4,$N51:$BW51) -> 0 | K51: =+E51*J51 -> 0 | L51: =+F51+H51-J51 -> 0 | M51: =+E51*L51 -> 0
A52: 48 | G52: =+E52*F52 -> 0 | H52: =SUMIF($N$4:$O$4,$H$4,$N52:$O52) -> 0 | I52: =+E52*H52 -> 0 | J52: =SUMIF($N$4:$BW$4,$J$4,$N52:$BW52) -> 0 | K52: =+E52*J52 -> 0 | L52: =+F52+H52-J52 -> 0 | M52: =+E52*L52 -> 0
A53: 49 | G53: =+E53*F53 -> 0 | H53: =SUMIF($N$4:$O$4,$H$4,$N53:$O53) -> 0 | I53: =+E53*H53 -> 0 | J53: =SUMIF($N$4:$BW$4,$J$4,$N53:$BW53) -> 0 | K53: =+E53*J53 -> 0 | L53: =+F53+H53-J53 -> 0 | M53: =+E53*L53 -> 0
A54: 50 | G54: =+E54*F54 -> 0 | H54: =SUMIF($N$4:$O$4,$H$4,$N54:$O54) -> 0 | I54: =+E54*H54 -> 0 | J54: =SUMIF($N$4:$BW$4,$J$4,$N54:$BW54) -> 0 | K54: =+E54*J54 -> 0 | L54: =+F54+H54-J54 -> 0 | M54: =+E54*L54 -> 0
A55: 51 | G55: =+E55*F55 -> 0 | H55: =SUMIF($N$4:$O$4,$H$4,$N55:$O55) -> 0 | I55: =+E55*H55 -> 0 | J55: =SUMIF($N$4:$BW$4,$J$4,$N55:$BW55) -> 0 | K55: =+E55*J55 -> 0 | L55: =+F55+H55-J55 -> 0 | M55: =+E55*L55 -> 0
... A144: 140 | G144: =+E144*F144 -> 0 | H144: =SUMIF($N$4:$O$4,$H$4,$N144:$O144) -> 0 | I144: =+E144*H144 -> 0 | J144: =SUMIF($N$4:$BW$4,$J$4,$N144:$BW144) -> 0 | K144: =+E144*J144 -> 0 | L144: =+F144+H144-J144 -> 0 | M144: =+E144*L144 -> 0
B145: 小商品成本 | F145: =SUM(F5:F144) -> 0 | G145: =SUM(G5:G144) -> 0 | H145: =SUM(H5:H144) -> 159 | I145: =SUM(I5:I144) -> 5579.2 | J145: =SUMIF($N$4:$BW$4,$J$4,$N145:$BW145) -> 4 | K145: =SUM(K5:K144) -> 205.9 | L145: =SUM(L5:L144) -> 155 | M145: =SUM(M5:M144) -> 5373.3 | N145: =SUM(N4:N144) -> 159 | O145: =SUM(O4:O144) -> 0 | P145: =SUM(P4:P144) -> 0 | Q145: =SUM(Q4:Q144) -> 1 | R145: =SUM(R4:R144) -> 0 | S145: =SUM(S4:S144) -> 0 | T145: =SUM(T4:T144) -> 0 | U145: =SUM(U4:U144) -> 0 | ... BW145: =SUM(BW4:BW144) -> 0

Sheet 客房耗材出入库录入
B1: 客房耗材物品出入库表
B2: 酒店名称： | N2: 周期：
A3: 序号 | B3: 货品名称 | C3: 规格型号 | D3: 单位 | E3: 单价 | F3: 上月 结存 | G3: 结存金额 | H3: 入库合计 | I3: 入库金额 | J3: 出库合计 | K3: 出库金额 | L3: 结存合计 | M3: 结存金额 | N3: 1号 | O3: 1号 | P3: 2号 | Q3: 2号 | R3: 3号 | S3: 3号 | T3: 4号 | U3: 4号 | V3: 5号 | W3: 5号 | X3: 6号 | Y3: 6号 | Z3: 7号 | AA3: 7号 | AB3: 8号 | AC3: 8号 | AD3: 9号 | AE3: 9号 | AF3: 10号 | AG3: 10号 | AH3: 11号 | AI3: 11号 | AJ3: 12号 | AK3: 12号 | AL3: 13号 | AM3: 13号 | AN3: 14号 | AO3: 14号 | AP3: 15号 | AQ3: 15号 | AR3: 16号 | AS3: 16号 | AT3: 17号 | AU3: 17号 | AV3: 18号 | AW3: 18号 | AX3: 19号 | AY3: 19号 | AZ3: 20号 | BA3: 20号 | BB3: 21号 | BC3: 21号 | BD3: 22号 | BE3: 22号 | BF3: 23号 | BG3: 23号 | BH3: 24号 | BI3: 24号 | BJ3: 25号 | BK3: 25号 | BL3: 26号 | BM3: 26号 | BN3: 27号 | BO3: 27号 | BP3: 28号 | BQ3: 28号 | BR3: 29号 | BS3: 29号 | BT3: 30号 | BU3: 30号 | BV3: 31号 | BW3: 31号
H4: 入库 | J4: 出库 | N4: 入库 | O4: 出库 | P4: 入库 | Q4: 出库 | R4: 入库 | S4: 出库 | T4: 入库 | U4: 出库 | V4: 入库 | W4: 出库 | X4: 入库 | Y4: 出库 | Z4: 入库 | AA4: 出库 | AB4: 入库 | AC4: 出库 | AD4: 入库 | AE4: 出库 | AF4: 入库 | AG4: 出库 | AH4: 入库 | AI4: 出库 | AJ4: 入库 | AK4: 出库 | AL4: 入库 | AM4: 出库 | AN4: 入库 | AO4: 出库 | AP4: 入库 | AQ4: 出库 | AR4: 入库 | AS4: 出库 | AT4: 入库 | AU4: 出库 | AV4: 入库 | AW4: 出库 | AX4: 入库 | AY4: 出库 | AZ4: 入库 | BA4: 出库 | BB4: 入库 | BC4: 出库 | BD4: 入库 | BE4: 出库 | BF4: 入库 | BG4: 出库 | BH4: 入库 | BI4: 出库 | BJ4: 入库 | BK4: 出库 | BL4: 入库 | BM4: 出库 | BN4: 入库 | BO4: 出库 | BP4: 入库 | BQ4: 出库 | BR4: 入库 | BS4: 出库 | BT4: 入库 | BU4: 出库 | BV4: 入库 | BW4: 出库
A5: 1 | B5: 牙刷 | D5: 支 | E5: 0.39 | F5: 5400 | G5: =F5*E5 -> 2106 | H5: =SUMIF($N$4:$BW$4,$H$4,$N5:$BW5) -> 0 | I5: =+E5*H5 -> 0 | J5: =SUMIF($N$4:$BW$4,$J$4,N5:$BW5) -> 3784 | K5: =+E5*J5 -> 1475.76 | L5: =+F5+H5-J5 -> 1616 | M5: =+E5*L5 -> 630.24 | O5: 98 | Q5: 106 | S5: 120 | U5: 102 | W5: 123 | Y5: 98 | AA5: 132 | AC5: 126 | AE5: 124 | AG5: 142 | AI5: 131 | AK5: 123 | AM5: 138 | AO5: 96 | AQ5: 119 | AS5: 123 | AU5: 114 | AW5: 120 | AY5: 116 | BA5: 127 | BC5: 122 | BE5: 118 | BG5: 123 | BI5: 119 | BK5: 132 | BM5: 118 | BO5: 120 | BQ5: 130 | BS5: 136 | BU5: 142 | BW5: 146
A6: 2 | B6: 牙膏 | D6: 支 | E6: 0.16 | F6: 6407 | G6: =F6*E6 -> 1025.12 | H6: =SUMIF($N$4:$BW$4,$H$4,$N6:$BW6) -> 0 | I6: =+E6*H6 -> 0 | J6: =SUMIF($N$4:$BW$4,$J$4,N6:$BW6) -> 3399 | K6: =+E6*J6 -> 543.84 | L6: =+F6+H6-J6 -> 3008 | M6: =+E6*L6 -> 481.28 | O6: 90 | Q6: 95 | S6: 113 | U6: 94 | W6: 106 | Y6: 88 | AA6: 112 | AC6: 118 | AE6: 105 | AG6: 127 | AI6: 118 | AK6: 108 | AM6: 124 | AO6: 88 | AQ6: 105 | AS6: 111 | AU6: 101 | AW6: 116 | AY6: 106 | BA6: 112 | BC6: 117 | BE6: 106 | BG6: 112 | BI6: 107 | BK6: 117 | BM6: 106 | BO6: 103 | BQ6: 114 | BS6: 124 | BU6: 126 | BW6: 130
A7: 3 | B7: 梳子 | D7: 把 | E7: 0.3 | F7: 3959 | G7: =F7*E7 -> 1187.7 | H7: =SUMIF($N$4:$BW$4,$H$4,$N7:$BW7) -> 0 | I7: =+E7*H7 -> 0 | J7: =SUMIF($N$4:$BW$4,$J$4,N7:$BW7) -> 2501 | K7: =+E7*J7 -> 750.3 | L7: =+F7+H7-J7 -> 1458 | M7: =+E7*L7 -> 437.4 | O7: 76 | Q7: 80 | S7: 85 | U7: 71 | W7: 78 | Y7: 88 | AA7: 68 | AC7: 80 | AE7: 78 | AG7: 92 | AI7: 88 | AK7: 82 | AM7: 90 | AO7: 52 | AQ7: 76 | AS7: 79 | AU7: 74 | AW7: 86 | AY7: 83 | BA7: 80 | BC7: 85 | BE7: 75 | BG7: 79 | BI7: 80 | BK7: 86 | BM7: 76 | BO7: 80 | BQ7: 86 | BS7: 92 | BU7: 86 | BW7: 90
A8: 4 | B8: 护理包 | D8: 包 | E8: 0.3 | F8: 4755 | G8: =F8*E8 -> 1426.5 | H8: =SUMIF($N$4:$BW$4,$H$4,$N8:$BW8) -> 0 | I8: =+E8*H8 -> 0 | J8: =SUMIF($N$4:$BW$4,$J$4,N8:$BW8) -> 2243 | K8: =+E8*J8 -> 672.9 | L8: =+F8+H8-J8 -> 2512 | M8: =+E8*L8 -> 753.6 | O8: 65 | Q8: 78 | S8: 75 | U8: 62 | W8: 78 | Y8: 79 | AA8: 65 | AC8: 75 | AE8: 69 | AG8: 73 | AI8: 68 | AK8: 70 | AM8: 72 | AO8: 50 | AQ8: 66 | AS8: 70 | AU8: 69 | AW8: 75 | AY8: 73 | BA8: 71 | BC8: 76 | BE8: 68 | BG8: 66 | BI8: 71 | BK8: 75 | BM8: 72 | BO8: 71 | BQ8: 84 | BS8: 84 | BU8: 87 | BW8: 86
A9: 5 | B9: 浴帽 | D9: 包 | E9: 0.21 | F9: 5900 | G9: =F9*E9 -> 1239 | H9: =SUMIF($N$4:$BW$4,$H$4,$N9:$BW9) -> 0 | I9: =+E9*H9 -> 0 | J9: =SUMIF($N$4:$BW$4,$J$4,N9:$BW9) -> 1912 | K9: =+E9*J9 -> 401.52 | L9: =+F9+H9-J9 -> 3988 | M9: =+E9*L9 -> 837.48 | O9: 50 | Q9: 66 | S9: 65 | U9: 53 | W9: 52 | Y9: 63 | AA9: 50 | AC9: 58 | AE9: 62 | AG9: 60 | AI9: 63 | AK9: 58 | AM9: 68 | AO9: 42 | AQ9: 54 | AS9: 61 | AU9: 58 | AW9: 63 | AY9: 64 | BA9: 68 | BC9: 60 | BE9: 62 | BG9: 65 | BI9: 63 | BK9: 68 | BM9: 63 | BO9: 62 | BQ9: 68 | BS9: 72 | BU9: 76 | BW9: 75
A10: 6 | B10: 拖鞋 | D10: 双 | E10: 1.59 | F10: 7546 | G10: =F10*E10 -> 11998.14 | H10: =SUMIF($N$4:$BW$4,$H$4,$N10:$BW10) -> 0 | I10: =+E10*H10 -> 0 | J10: =SUMIF($N$4:$BW$4,$J$4,N10:$BW10) -> 4101 | K10: =+E10*J10 -> 6520.59 | L10: =+F10+H10-J10 -> 3445 | M10: =+E10*L10 -> 5477.55 | O10: 114 | Q10: 122 | S10: 126 | U10: 118 | W10: 132 | Y10: 124 | AA10: 136 | AC10: 127 | AE10: 125 | AG10: 130 | AI10: 134 | AK10: 142 | AM10: 158 | AO10: 104 | AQ10: 128 | AS10: 135 | AU10: 122 | AW10: 139 | AY10: 127 | BA10: 137 | BC10: 132 | BE10: 125 | BG10: 134 | BI10: 129 | BK10: 136 | BM10: 121 | BO10: 126 | BQ10: 136 | BS10: 153 | BU10: 162 | BW10: 167
A11: 7 | B11: 儿童牙刷 | D11: 支 | E11: 1 | F11: 500 | G11: =F11*E11 -> 500 | H11: =SUMIF($N$4:$BW$4,$H$4,$N11:$BW11) -> 0 | I11: =+E11*H11 -> 0 | J11: =SUMIF($N$4:$BW$4,$J$4,N11:$BW11) -> 89 | K11: =+E11*J11 -> 89 | L11: =+F11+H11-J11 -> 411 | M11: =+E11*L11 -> 411 | O11: 1 | Q11: 4 | S11: 2 | U11: 2 | W11: 3 | AA11: 2 | AC11: 2 | AE11: 4 | AI11: 3 | AK11: 3 | AM11: 1 | AO11: 2 | AS11: 3 | AU11: 1 | AW11: 4 | AY11: 1 | BA11: 3 | BC11: 2 | BE11: 3 | BG11: 4 | BI11: 3 | BK11: 5 | BM11: 2 | BO11: 3 | BQ11: 5 | BS11: 6 | BU11: 7 | BW11: 8
A12: 8 | B12: 儿童拖鞋 | D12: 双 | E12: 1.8 | F12: 500 | G12: =F12*E12 -> 900 | H12: =SUMIF($N$4:$BW$4,$H$4,$N12:$BW12) -> 0 | I12: =+E12*H12 -> 0 | J12: =SUMIF($N$4:$BW$4,$J$4,N12:$BW12) -> 92 | K12: =+E12*J12 -> 165.6 | L12: =+F12+H12-J12 -> 408 | M12: =+E12*L12 -> 734.4 | O12: 1 | Q12: 4 | S12: 2 | U12: 2 | W12: 4 | AA12: 2 | AC12: 2 | AE12: 3 | AI12: 2 | AK12: 3 | AM12: 1 | AO12: 2 | AS12: 3 | AU12: 1 | AW12: 4 | AY12: 1 | BA12: 3 | BC12: 2 | BE12: 2 | BG12: 4 | BI12: 3 | BK12: 5 | BM12: 3 | BO12: 4 | BQ12: 6 | BS12: 8 | BU12: 7 | BW12: 8
A13: 9 | B13: 洗衣液 | D13: 瓶 | E13: 7.9 | F13: 21 | G13: =F13*E13 -> 165.9 | H13: =SUMIF($N$4:$BW$4,$H$4,$N13:$BW13) -> 0 | I13: =+E13*H13 -> 0 | J13: =SUMIF($N$4:$BW$4,$J$4,N13:$BW13) -> 11 | K13: =+E13*J13 -> 86.9 | L13: =+F13+H13-J13 -> 10 | M13: =+E13*L13 -> 79 | AA13: 1 | AE13: 1 | AO13: 1 | AU13: 1 | BA13: 1 | BG13: 1 | BO13: 1 | BQ13: 2 | BS13: 1 | BU13: 1
A14: 10 | B14: 洗手液 | D14: 瓶 | E14: 7.9 | F14: 83 | G14: =F14*E14 -> 655.7 | H14: =SUMIF($N$4:$BW$4,$H$4,$N14:$BW14) -> 0 | I14: =+E14*H14 -> 0 | J14: =SUMIF($N$4:$BW$4,$J$4,N14:$BW14) -> 28 | K14: =+E14*J14 -> 221.2 | L14: =+F14+H14-J14 -> 55 | M14: =+E14*L14 -> 434.5 | O14: 1 | Q14: 1 | S14: 1 | U14: 2 | W14: 1 | AA14: 1 | AE14: 2 | AG14: 1 | AI14: 1 | AM14: 2 | AO14: 1 | AS14: 1 | AW14: 1 | BA14: 1 | BC14: 2 | BE14: 2 | BI14: 1 | BK14: 1 | BO14: 2 | BS14: 1 | BW14: 2
A15: 11 | B15: 洗衣液补充液 | D15: 桶 | E15: 48 | F15: 23 | G15: =F15*E15 -> 1104 | H15: =SUMIF($N$4:$BW$4,$H$4,$N15:$BW15) -> 0 | I15: =+E15*H15 -> 0 | J15: =SUMIF($N$4:$BW$4,$J$4,N15:$BW15) -> 10 | K15: =+E15*J15 -> 480 | L15: =+F15+H15-J15 -> 13 | M15: =+E15*L15 -> 624 | S15: 1 | W15: 1 | AA15: 1 | AI15: 1 | AM15: 1 | AQ15: 1 | BA15: 1 | BG15: 1 | BS15: 1 | BU15: 1
A16: 12 | B16: 环保袋 | D16: 个 | E16: 0.75 | F16: 3159 | G16: =F16*E16 -> 2369.25 | H16: =SUMIF($N$4:$BW$4,$H$4,$N16:$BW16) -> 0 | I16: =+E16*H16 -> 0 | J16: =SUMIF($N$4:$BW$4,$J$4,N16:$BW16) -> 1101 | K16: =+E16*J16 -> 825.75 | L16: =+F16+H16-J16 -> 2058 | M16: =+E16*L16 -> 1543.5 | O16: 25 | Q16: 23 | S16: 38 | U16: 30 | W16: 39 | Y16: 34 | AA16: 30 | AC16: 38 | AE16: 32 | AG16: 41 | AI16: 26 | AK16: 36 | AM16: 43 | AO16: 29 | AQ16: 25 | AS16: 31 | AU16: 24 | AW16: 33 | AY16: 24 | BA16: 36 | BC16: 41 | BE16: 36 | BG16: 43 | BI16: 37 | BK16: 31 | BM16: 32 | BO16: 36 | BQ16: 40 | BS16: 52 | BU16: 56 | BW16: 60
A17: 13 | B17: 红茶 | D17: 包 | E17: 0.39 | F17: 772 | G17: =F17*E17 -> 301.08 | H17: =SUMIF($N$4:$BW$4,$H$4,$N17:$BW17) -> 0 | I17: =+E17*H17 -> 0 | J17: =SUMIF($N$4:$BW$4,$J$4,N17:$BW17) -> 565 | K17: =+E17*J17 -> 220.35 | L17: =+F17+H17-J17 -> 207 | M17: =+E17*L17 -> 80.73 | O17: 17 | Q17: 18 | S17: 19 | U17: 15 | W17: 16 | Y17: 19 | AA17: 17 | AC17: 21 | AE17: 18 | AG17: 23 | AI17: 18 | AK17: 20 | AM17: 24 | AO17: 17 | AQ17: 20 | AS17: 14 | AU17: 13 | AW17: 18 | AY17: 15 | BA17: 18 | BC17: 22 | BE17: 18 | BG17: 15 | BI17: 18 | BK17: 17 | BM17: 15 | BO17: 17 | BQ17: 19 | BS17: 21 | BU17: 22 | BW17: 21
A18: 14 | B18: 绿茶 | D18: 包 | E18: 0.39 | F18: 857 | G18: =F18*E18 -> 334.23 | H18: =SUMIF($N$4:$BW$4,$H$4,$N18:$BW18) -> 0 | I18: =+E18*H18 -> 0 | J18: =SUMIF($N$4:$BW$4,$J$4,N18:$BW18) -> 557 | K18: =+E18*J18 -> 217.23 | L18: =+F18+H18-J18 -> 300 | M18: =+E18*L18 -> 117 | O18: 19 | Q18: 16 | S18: 17 | U18: 16 | W18: 16 | Y18: 14 | AA18: 17 | AC18: 22 | AE18: 20 | AG18: 20 | AI18: 17 | AK18: 18 | AM18: 23 | AO18: 18 | AQ18: 19 | AS18: 16 | AU18: 15 | AW18: 19 | AY18: 13 | BA18: 19 | BC18: 23 | BE18: 16 | BG18: 15 | BI18: 17 | BK18: 19 | BM18: 13 | BO18: 17 | BQ18: 17 | BS18: 23 | BU18: 20 | BW18: 23
A19: 15 | B19: 洗发液 | D19: 瓶 | E19: 13.5 | F19: 422 | G19: =F19*E19 -> 5697 | H19: =SUMIF($N$4:$BW$4,$H$4,$N19:$BW19) -> 0 | I19: =+E19*H19 -> 0 | J19: =SUMIF($N$4:$BW$4,$J$4,N19:$BW19) -> 254 | K19: =+E19*J19 -> 3429 | L19: =+F19+H19-J19 -> 168 | M19: =+E19*L19 -> 2268 | O19: 6 | Q19: 7 | S19: 7 | U19: 8 | W19: 8 | Y19: 7 | AA19: 8 | AC19: 8 | AE19: 6 | AG19: 7 | AI19: 9 | AK19: 8 | AM19: 9 | AO19: 8 | AQ19: 9 | AS19: 8 | AU19: 8 | AW19: 10 | AY19: 8 | BA19: 10 | BC19: 11 | BE19: 9 | BG19: 10 | BI19: 8 | BK19: 9 | BM19: 8 | BO19: 8 | BQ19: 7 | BS19: 11 | BU19: 7 | BW19: 7
A20: 16 | B20: 沐浴液 | D20: 瓶 | E20: 13.5 | F20: 447 | G20: =F20*E20 -> 6034.5 | H20: =SUMIF($N$4:$BW$4,$H$4,$N20:$BW20) -> 0 | I20: =+E20*H20 -> 0 | J20: =SUMIF($N$4:$BW$4,$J$4,N20:$BW20) -> 248 | K20: =+E20*J20 -> 3348 | L20: =+F20+H20-J20 -> 199 | M20: =+E20*L20 -> 2686.5 | O20: 6 | Q20: 6 | S20: 7 | U20: 8 | W20: 7 | Y20: 8 | AA20: 6 | AC20: 6 | AE20: 7 | AG20: 8 | AI20: 7 | AK20: 8 | AM20: 7 | AO20: 8 | AQ20: 8 | AS20: 8 | AU20: 7 | AW20: 9 | AY20: 9 | BA20: 10 | BC20: 10 | BE20: 9 | BG20: 9 | BI20: 10 | BK20: 9 | BM20: 7 | BO20: 9 | BQ20: 7 | BS20: 12 | BU20: 10 | BW20: 6
A21: 17 | B21: 护发素 | D21: 瓶 | E21: 13.5 | F21: 476 | G21: =F21*E21 -> 6426 | H21: =SUMIF($N$4:$BW$4,$H$4,$N21:$BW21) -> 0 | I21: =+E21*H21 -> 0 | J21: =SUMIF($N$4:$BW$4,$J$4,N21:$BW21) -> 146 | K21: =+E21*J21 -> 1971 | L21: =+F21+H21-J21 -> 330 | M21: =+E21*L21 -> 4455 | O21: 5 | Q21: 4 | S21: 5 | U21: 4 | W21: 4 | Y21: 5 | AA21: 3 | AC21: 4 | AE21: 5 | AG21: 4 | AI21: 5 | AK21: 4 | AM21: 6 | AO21: 5 | AQ21: 4 | AS21: 5 | AU21: 5 | AW21: 6 | AY21: 4 | BA21: 6 | BC21: 4 | BE21: 6 | BG21: 5 | BI21: 6 | BK21: 5 | BM21: 4 | BO21: 4 | BQ21: 3 | BS21: 7 | BU21: 4 | BW21: 5
A22: 18 | B22: 厕纸 | D22: 卷 | E22: 0.75 | F22: 4725 | G22: =F22*E22 -> 3543.75 | H22: =SUMIF($N$4:$BW$4,$H$4,$N22:$BW22) -> 0 | I22: =+E22*H22 -> 0 | J22: =SUMIF($N$4:$BW$4,$J$4,N22:$BW22) -> 2883 | K22: =+E22*J22 -> 2162.25 | L22: =+F22+H22-J22 -> 1842 | M22: =+E22*L22 -> 1381.5 | O22: 81 | Q22: 98 | S22: 96 | U22: 83 | W22: 93 | Y22: 92 | AA22: 91 | AC22: 93 | AE22: 89 | AG22: 90 | AI22: 90 | AK22: 92 | AM22: 96 | AO22: 75 | AQ22: 86 | AS22: 92 | AU22: 82 | AW22: 96 | AY22: 89 | BA22: 93 | BC22: 95 | BE22: 97 | BG22: 93 | BI22: 97 | BK22: 102 | BM22: 93 | BO22: 92 | BQ22: 101 | BS22: 108 | BU22: 106 | BW22: 102
A23: 19 | B23: 抽纸 | D23: 包 | E23: 0.45 | F23: 4436 | G23: =F23*E23 -> 1996.2 | H23: =SUMIF($N$4:$BW$4,$H$4,$N23:$BW23) -> 0 | I23: =+E23*H23 -> 0 | J23: =SUMIF($N$4:$BW$4,$J$4,N23:$BW23) -> 3689 | K23: =+E23*J23 -> 1660.05 | L23: =+F23+H23-J23 -> 747 | M23: =+E23*L23 -> 336.15 | O23: 93 | Q23: 90 | S23: 921 | U23: 88 | W23: 89 | Y23: 94 | AA23: 92 | AC23: 95 | AE23: 92 | AG23: 92 | AI23: 85 | AK23: 88 | AM23: 91 | AO23: 80 | AQ23: 88 | AS23: 93 | AU23: 86 | AW23: 95 | AY23: 91 | BA23: 90 | BC23: 91 | BE23: 95 | BG23: 92 | BI23: 93 | BK23: 97 | BM23: 90 | BO23: 93 | BQ23: 99 | BS23: 106 | BU23: 102 | BW23: 98
A24: 20 | B24: 矿泉水 | D24: 瓶 | E24: 0.667 | F24: 15786 | G24: =F24*E24 -> 10529.262 | H24: =SUMIF($N$4:$BW$4,$H$4,$N24:$BW24) -> 0 | I24: =+E24*H24 -> 0 | J24: =SUMIF($N$4:$BW$4,$J$4,N24:$BW24) -> 10137 | K24: =+E24*J24 -> 6761.379 | L24: =+F24+H24-J24 -> 5649 | M24: =+E24*L24 -> 3767.883 | O24: 318 | Q24: 286 | S24: 325 | U24: 274 | W24: 287 | Y24: 345 | AA24: 330 | AC24: 336 | AE24: 352 | AG24: 340 | AI24: 333 | AK24: 332 | AM24: 343 | AO24: 314 | AQ24: 333 | AS24: 347 | AU24: 316 | AW24: 322 | AY24: 344 | BA24: 333 | BC24: 311 | BE24: 298 | BG24: 322 | BI24: 310 | BK24: 311 | BM24: 320 | BO24: 354 | BQ24: 331 | BS24: 342 | BU24: 341 | BW24: 387
A25: 21 | B25: 大黑垃圾袋 | D25: 个 | E25: 0.36 | F25: 1541 | G25: =F25*E25 -> 554.76 | H25: =SUMIF($N$4:$BW$4,$H$4,$N25:$BW25) -> 0 | I25: =+E25*H25 -> 0 | J25: =SUMIF($N$4:$BW$4,$J$4,N25:$BW25) -> 941 | K25: =+E25*J25 -> 338.76 | L25: =+F25+H25-J25 -> 600 | M25: =+E25*L25 -> 216 | O25: 28 | Q25: 32 | S25: 35 | U25: 32 | W25: 35 | Y25: 24 | AA25: 26 | AC25: 23 | AE25: 27 | AG25: 30 | AI25: 32 | AK25: 34 | AM25: 38 | AO25: 20 | AQ25: 29 | AS25: 26 | AU25: 22 | AW25: 29 | AY25: 27 | BA25: 30 | BC25: 32 | BE25: 33 | BG25: 35 | BI25: 32 | BK25: 36 | BM25: 32 | BO25: 29 | BQ25: 31 | BS25: 36 | BU25: 34 | BW25: 32
A26: 22 | B26: 小白垃圾袋 | D26: 个 | E26: 0.027 | F26: 15272 | G26: =F26*E26 -> 412.344 | H26: =SUMIF($N$4:$BW$4,$H$4,$N26:$BW26) -> 0 | I26: =+E26*H26 -> 0 | J26: =SUMIF($N$4:$BW$4,$J$4,N26:$BW26) -> 6862 | K26: =+E26*J26 -> 185.274 | L26: =+F26+H26-J26 -> 8410 | M26: =+E26*L26 -> 227.07 | O26: 204 | Q26: 211 | S26: 222 | U26: 217 | W26: 210 | Y26: 198 | AA26: 213 | AC26: 214 | AE26: 218 | AG26: 215 | AI26: 213 | AK26: 224 | AM26: 236 | AO26: 199 | AQ26: 217 | AS26: 223 | AU26: 208 | AW26: 221 | AY26: 227 | BA26: 231 | BC26: 236 | BE26: 228 | BG26: 231 | BI26: 221 | BK26: 234 | BM26: 227 | BO26: 224 | BQ26: 228 | BS26: 234 | BU26: 238 | BW26: 240
A27: 23 | B27: 茶颜悦色绿茶 | D27: 包 | E27: 0.43 | F27: 780 | G27: =F27*E27 -> 335.4 | H27: =SUMIF($N$4:$BW$4,$H$4,$N27:$BW27) -> 0 | I27: =+E27*H27 -> 0 | J27: =SUMIF($N$4:$BW$4,$J$4,N27:$BW27) -> 599 | K27: =+E27*J27 -> 257.57 | L27: =+F27+H27-J27 -> 181 | M27: =+E27*L27 -> 77.83 | O27: 18 | Q27: 19 | S27: 19 | U27: 23 | W27: 24 | Y27: 20 | AA27: 19 | AC27: 16 | AE27: 24 | AG27: 18 | AI27: 23 | AK27: 21 | AM27: 26 | AO27: 15 | AQ27: 18 | AS27: 21 | AU27: 16 | AW27: 22 | AY27: 23 | BA27: 24 | BC27: 19 | BE27: 16 | BG27: 14 | BI27: 17 | BK27: 18 | BM27: 15 | BO27: 18 | BQ27: 16 | BS27: 19 | BU27: 20 | BW27: 18
... A30: 26 | B30: 咖啡 | D30: 袋 | E30: 0.6 | F30: 3494 | G30: =F30*E30 -> 2096.4 | H30: =SUMIF($N$4:$BW$4,$H$4,$N30:$BW30) -> 0 | I30: =+E30*H30 -> 0 | J30: =SUMIF($N$4:$BW$4,$J$4,N30:$BW30) -> 2545 | K30: =+E30*J30 -> 1527 | L30: =+F30+H30-J30 -> 949 | M30: =+E30*L30 -> 569.4 | O30: 75 | Q30: 80 | S30: 83 | U30: 85 | W30: 82 | Y30: 76 | AA30: 80 | AC30: 78 | AE30: 84 | AG30: 81 | AI30: 83 | AK30: 86 | AM30: 75 | AO30: 69 | AQ30: 72 | AS30: 76 | AU30: 71 | AW30: 84 | AY30: 82 | BA30: 89 | BC30: 83 | BE30: 82 | BG30: 88 | BI30: 84 | BK30: 83 | BM30: 82 | BO30: 81 | BQ30: 83 | BS30: 93 | BU30: 97 | BW30: 98
A31: 27 | B31: 饮料维他水溶 | D31: 瓶 | E31: 1.5 | G31: =F31*E31 -> 0 | H31: =SUMIF($N$4:$BW$4,$H$4,$N31:$BW31) -> 3600 | I31: =+E31*H31 -> 5400 | J31: =SUMIF($N$4:$BW$4,$J$4,N31:$BW31) -> 2641 | K31: =+E31*J31 -> 3961.5 | L31: =+F31+H31-J31 -> 959 | M31: =+E31*L31 -> 1438.5 | AL31: 1200 | AO31: 266 | AQ31: 128 | AS31: 137 | AU31: 152 | AW31: 142 | AY31: 135 | AZ31: 2400 | BA31: 130 | BC31: 141 | BE31: 145 | BG31: 147 | BI31: 127 | BK31: 137 | BM31: 122 | BO31: 137 | BQ31: 133 | BS31: 154 | BU31: 148 | BW31: 160
A32: 28 | G32: =F32*E32 -> 0 | H32: =SUMIF($N$4:$BW$4,$H$4,$N32:$BW32) -> 0 | I32: =+E32*H32 -> 0 | J32: =SUMIF($N$4:$BW$4,$J$4,N32:$BW32) -> 0 | K32: =+E32*J32 -> 0 | L32: =+F32+H32-J32 -> 0 | M32: =+E32*L32 -> 0
A33: 29 | G33: =F33*E33 -> 0 | H33: =SUMIF($N$4:$BW$4,$H$4,$N33:$BW33) -> 0 | I33: =+E33*H33 -> 0 | J33: =SUMIF($N$4:$BW$4,$J$4,N33:$BW33) -> 0 | K33: =+E33*J33 -> 0 | L33: =+F33+H33-J33 -> 0 | M33: =+E33*L33 -> 0
A34: 30 | G34: =F34*E34 -> 0 | H34: =SUMIF($N$4:$BW$4,$H$4,$N34:$BW34) -> 0 | I34: =+E34*H34 -> 0 | J34: =SUMIF($N$4:$BW$4,$J$4,N34:$BW34) -> 0 | K34: =+E34*J34 -> 0 | L34: =+F34+H34-J34 -> 0 | M34: =+E34*L34 -> 0
A35: 31 | G35: =F35*E35 -> 0 | H35: =SUMIF($N$4:$BW$4,$H$4,$N35:$BW35) -> 0 | I35: =+E35*H35 -> 0 | J35: =SUMIF($N$4:$BW$4,$J$4,N35:$BW35) -> 0 | K35: =+E35*J35 -> 0 | L35: =+F35+H35-J35 -> 0 | M35: =+E35*L35 -> 0
A36: 32 | G36: =F36*E36 -> 0 | H36: =SUMIF($N$4:$BW$4,$H$4,$N36:$BW36) -> 0 | I36: =+E36*H36 -> 0 | J36: =SUMIF($N$4:$BW$4,$J$4,N36:$BW36) -> 0 | K36: =+E36*J36 -> 0 | L36: =+F36+H36-J36 -> 0 | M36: =+E36*L36 -> 0
A37: 33 | G37: =F37*E37 -> 0 | H37: =SUMIF($N$4:$BW$4,$H$4,$N37:$BW37) -> 0 | I37: =+E37*H37 -> 0 | J37: =SUMIF($N$4:$BW$4,$J$4,N37:$BW37) -> 0 | K37: =+E37*J37 -> 0 | L37: =+F37+H37-J37 -> 0 | M37: =+E37*L37 -> 0
A38: 34 | G38: =F38*E38 -> 0 | H38: =SUMIF($N$4:$BW$4,$H$4,$N38:$BW38) -> 0 | I38: =+E38*H38 -> 0 | J38: =SUMIF($N$4:$BW$4,$J$4,N38:$BW38) -> 0 | K38: =+E38*J38 -> 0 | L38: =+F38+H38-J38 -> 0 | M38: =+E38*L38 -> 0
A39: 35 | G39: =F39*E39 -> 0 | H39: =SUMIF($N$4:$BW$4,$H$4,$N39:$BW39) -> 0 | I39: =+E39*H39 -> 0 | J39: =SUMIF($N$4:$BW$4,$J$4,N39:$BW39) -> 0 | K39: =+E39*J39 -> 0 | L39: =+F39+H39-J39 -> 0 | M39: =+E39*L39 -> 0
A40: 36 | G40: =F40*E40 -> 0 | H40: =SUMIF($N$4:$BW$4,$H$4,$N40:$BW40) -> 0 | I40: =+E40*H40 -> 0 | J40: =SUMIF($N$4:$BW$4,$J$4,N40:$BW40) -> 0 | K40: =+E40*J40 -> 0 | L40: =+F40+H40-J40 -> 0 | M40: =+E40*L40 -> 0
A41: 37 | G41: =F41*E41 -> 0 | H41: =SUMIF($N$4:$BW$4,$H$4,$N41:$BW41) -> 0 | I41: =+E41*H41 -> 0 | J41: =SUMIF($N$4:$BW$4,$J$4,N41:$BW41) -> 0 | K41: =+E41*J41 -> 0 | L41: =+F41+H41-J41 -> 0 | M41: =+E41*L41 -> 0
A42: 38 | G42: =F42*E42 -> 0 | H42: =SUMIF($N$4:$BW$4,$H$4,$N42:$BW42) -> 0 | I42: =+E42*H42 -> 0 | J42: =SUMIF($N$4:$BW$4,$J$4,N42:$BW42) -> 0 | K42: =+E42*J42 -> 0 | L42: =+F42+H42-J42 -> 0 | M42: =+E42*L42 -> 0
A43: 39 | G43: =F43*E43 -> 0 | H43: =SUMIF($N$4:$BW$4,$H$4,$N43:$BW43) -> 0 | I43: =+E43*H43 -> 0 | J43: =SUMIF($N$4:$BW$4,$J$4,N43:$BW43) -> 0 | K43: =+E43*J43 -> 0 | L43: =+F43+H43-J43 -> 0 | M43: =+E43*L43 -> 0
... A69: 65 | G69: =F69*E69 -> 0 | H69: =SUMIF($N$4:$BW$4,$H$4,$N69:$BW69) -> 0 | I69: =+E69*H69 -> 0 | J69: =SUMIF($N$4:$BW$4,$J$4,N69:$BW69) -> 0 | K69: =+E69*J69 -> 0 | L69: =+F69+H69-J69 -> 0 | M69: =+E69*L69 -> 0
B70: 合计 | F70: =SUM(F5:F49) -> 91230 | G70: =SUM(G5:G49) -> 66857.786 | J70: =SUM(J5:J33) -> 54658 | K70: =SUM(K5:K33) -> 41603.928 | L70: =SUM(L5:L49) -> 40172 | M70: =SUM(M5:M49) -> 30653.858 | N70: =SUM(N5:N69) -> 0 | O70: =SUM(O5:O69) -> 1495 | P70: =SUM(P5:P69) -> 0 | Q70: =SUM(Q5:Q69) -> 1549 | R70: =SUM(R5:R69) -> 0 | S70: =SUM(S5:S69) -> 2492 | T70: =SUM(T5:T69) -> 0 | U70: =SUM(U5:U69) -> 1481 | ... BW70: =SUM(BW5:BW69) -> 2093

Sheet 客房提成录入
U1: 填写说明：
F2: 倍数 | G2: 1 | H2: 1.2 | I2: 1.5 | J2: 2 | K2: 2 | L2: 2 | M2: 1 | U2: 1、倍数为做房1间房核算提成时算多少间房，比如做普通房1间算1间，亲子房一间算1.5间；
A3: 日期 | B3: 姓名 | C3: 岗位 | D3: 薪级 | E3: 提成标准（根据实际情况填写） | F3: 班次 | G3: 标准房型 | H3: 双床 | I3: 浴缸房 | J3: 亲子房 | K3: 大清 | L3: 套房 | M3: 跨楼 | N3: 做房数量合计 | O3: 做房基数（根据实际情况填写） | P3: 全天房提成金额 | Q3: 钟点房数量 | R3: 钟点房提成金额 | S3: 提成总金额 | T3: 备注 | U3: 2、班次必须根据实际排班情况填写上班班次，如中班、晚班；
A4: 46204 | B4: 韩愈 | C4: 客房经理 | E4: 5 | F4: A | N4: =SUMPRODUCT($G$2:$M$2,G4:M4) -> 0 | O4: 0 | P4: =IFERROR(IF((N4*E4-O4*E4)<0,0,(N4*E4-O4*E4)),"") -> 0 | R4: =IF(Q4="",0,Q4*5) -> 0 | S4: =IF(B4="","",P4+R4) -> 0
A5: 46205 | B5: 韩愈 | C5: 客房经理 | E5: 5 | N5: =SUMPRODUCT($G$2:$M$2,G5:M5) -> 0 | O5: 0 | P5: =IFERROR(IF((N5*E5-O5*E5)<0,0,(N5*E5-O5*E5)),"") -> 0 | R5: =IF(Q5="",0,Q5*5) -> 0 | S5: =IF(B5="","",P5+R5) -> 0
A6: 46206 | B6: 韩愈 | C6: 客房经理 | E6: 5 | N6: =SUMPRODUCT($G$2:$M$2,G6:M6) -> 0 | O6: 0 | P6: =IFERROR(IF((N6*E6-O6*E6)<0,0,(N6*E6-O6*E6)),"") -> 0 | R6: =IF(Q6="",0,Q6*5) -> 0 | S6: =IF(B6="","",P6+R6) -> 0 | U6: 3、做房基数根据制度基数填写，如跨楼层基数与不跨楼层基数不一致。
A7: 46207 | B7: 韩愈 | C7: 客房经理 | E7: 5 | N7: =SUMPRODUCT($G$2:$M$2,G7:M7) -> 0 | O7: 0 | P7: =IFERROR(IF((N7*E7-O7*E7)<0,0,(N7*E7-O7*E7)),"") -> 0 | R7: =IF(Q7="",0,Q7*5) -> 0 | S7: =IF(B7="","",P7+R7) -> 0 | U7: 4、提成金额已固定公式，无需填写，但须首查核对；
A8: 46208 | B8: 韩愈 | C8: 客房经理 | E8: 5 | N8: =SUMPRODUCT($G$2:$M$2,G8:M8) -> 0 | O8: 0 | P8: =IFERROR(IF((N8*E8-O8*E8)<0,0,(N8*E8-O8*E8)),"") -> 0 | R8: =IF(Q8="",0,Q8*5) -> 0 | S8: =IF(B8="","",P8+R8) -> 0
A9: 46209 | B9: 韩愈 | C9: 客房经理 | E9: 5 | N9: =SUMPRODUCT($G$2:$M$2,G9:M9) -> 0 | O9: 0 | P9: =IFERROR(IF((N9*E9-O9*E9)<0,0,(N9*E9-O9*E9)),"") -> 0 | R9: =IF(Q9="",0,Q9*5) -> 0 | S9: =IF(B9="","",P9+R9) -> 0 | V9: 客房人员提成金额汇总
A10: 46210 | B10: 韩愈 | C10: 客房经理 | E10: 5 | N10: =SUMPRODUCT($G$2:$M$2,G10:M10) -> 0 | O10: 0 | P10: =IFERROR(IF((N10*E10-O10*E10)<0,0,(N10*E10-O10*E10)),"") -> 0 | R10: =IF(Q10="",0,Q10*5) -> 0 | S10: =IF(B10="","",P10+R10) -> 0 | V10: 序号 | W10: 客房人员姓名 | X10: 提成金额
A11: 46211 | B11: 韩愈 | C11: 客房经理 | E11: 5 | N11: =SUMPRODUCT($G$2:$M$2,G11:M11) -> 0 | O11: 0 | P11: =IFERROR(IF((N11*E11-O11*E11)<0,0,(N11*E11-O11*E11)),"") -> 0 | R11: =IF(Q11="",0,Q11*5) -> 0 | S11: =IF(B11="","",P11+R11) -> 0 | V11: 1 | W11: 韩愈 | X11: =SUMIF($B:$B,$W11,$S:$S) -> 55
A12: 46212 | B12: 韩愈 | C12: 客房经理 | E12: 5 | N12: =SUMPRODUCT($G$2:$M$2,G12:M12) -> 0 | O12: 0 | P12: =IFERROR(IF((N12*E12-O12*E12)<0,0,(N12*E12-O12*E12)),"") -> 0 | R12: =IF(Q12="",0,Q12*5) -> 0 | S12: =IF(B12="","",P12+R12) -> 0 | V12: 2 | W12: 张凯娜 | X12: =SUMIF($B:$B,$W12,$S:$S) -> 580 | Z12: 292
A13: 46213 | B13: 韩愈 | C13: 客房经理 | E13: 5 | N13: =SUMPRODUCT($G$2:$M$2,G13:M13) -> 0 | O13: 0 | P13: =IFERROR(IF((N13*E13-O13*E13)<0,0,(N13*E13-O13*E13)),"") -> 0 | R13: =IF(Q13="",0,Q13*5) -> 0 | S13: =IF(B13="","",P13+R13) -> 0 | V13: 3 | W13: 初立玲 | X13: =SUMIF($B:$B,$W13,$S:$S) -> 985 | Z13: 1550
A14: 46214 | B14: 韩愈 | C14: 客房经理 | E14: 5 | N14: =SUMPRODUCT($G$2:$M$2,G14:M14) -> 0 | O14: 0 | P14: =IFERROR(IF((N14*E14-O14*E14)<0,0,(N14*E14-O14*E14)),"") -> 0 | R14: =IF(Q14="",0,Q14*5) -> 0 | S14: =IF(B14="","",P14+R14) -> 0 | V14: 4 | W14: 姜敏 | X14: =SUMIF($B:$B,$W14,$S:$S) -> 940 | Z14: 1774
A15: 46215 | B15: 韩愈 | C15: 客房经理 | E15: 5 | N15: =SUMPRODUCT($G$2:$M$2,G15:M15) -> 0 | O15: 0 | P15: =IFERROR(IF((N15*E15-O15*E15)<0,0,(N15*E15-O15*E15)),"") -> 0 | R15: =IF(Q15="",0,Q15*5) -> 0 | S15: =IF(B15="","",P15+R15) -> 0 | V15: 5 | W15: 张淑萍 | X15: =SUMIF($B:$B,$W15,$S:$S) -> 1895 | Z15: 1025
A16: 46216 | B16: 韩愈 | C16: 客房经理 | E16: 5 | N16: =SUMPRODUCT($G$2:$M$2,G16:M16) -> 0 | O16: 0 | P16: =IFERROR(IF((N16*E16-O16*E16)<0,0,(N16*E16-O16*E16)),"") -> 0 | R16: =IF(Q16="",0,Q16*5) -> 0 | S16: =IF(B16="","",P16+R16) -> 0 | V16: 6 | W16: 姜洪英 | X16: =SUMIF($B:$B,$W16,$S:$S) -> 1210 | Z16: 1167
A17: 46217 | B17: 韩愈 | C17: 客房经理 | E17: 5 | N17: =SUMPRODUCT($G$2:$M$2,G17:M17) -> 0 | O17: 0 | P17: =IFERROR(IF((N17*E17-O17*E17)<0,0,(N17*E17-O17*E17)),"") -> 0 | R17: =IF(Q17="",0,Q17*5) -> 0 | S17: =IF(B17="","",P17+R17) -> 0 | V17: 7 | W17: 石见见 | X17: =SUMIF($B:$B,$W17,$S:$S) -> 1250 | Z17: 785
A18: 46218 | B18: 韩愈 | C18: 客房经理 | E18: 5 | N18: =SUMPRODUCT($G$2:$M$2,G18:M18) -> 0 | O18: 0 | P18: =IFERROR(IF((N18*E18-O18*E18)<0,0,(N18*E18-O18*E18)),"") -> 0 | R18: =IF(Q18="",0,Q18*5) -> 0 | S18: =IF(B18="","",P18+R18) -> 0 | V18: 8 | W18: 王小宁 | X18: =SUMIF($B:$B,$W18,$S:$S) -> 710 | Z18: 1116
A19: 46219 | B19: 韩愈 | C19: 客房经理 | E19: 5 | N19: =SUMPRODUCT($G$2:$M$2,G19:M19) -> 0 | O19: 0 | P19: =IFERROR(IF((N19*E19-O19*E19)<0,0,(N19*E19-O19*E19)),"") -> 0 | R19: =IF(Q19="",0,Q19*5) -> 0 | S19: =IF(B19="","",P19+R19) -> 0 | V19: 9 | W19: 丁春艳 | X19: =SUMIF($B:$B,$W19,$S:$S) -> 1030
A20: 46220 | B20: 韩愈 | C20: 客房经理 | E20: 5 | N20: =SUMPRODUCT($G$2:$M$2,G20:M20) -> 0 | O20: 0 | P20: =IFERROR(IF((N20*E20-O20*E20)<0,0,(N20*E20-O20*E20)),"") -> 0 | R20: =IF(Q20="",0,Q20*5) -> 0 | S20: =IF(B20="","",P20+R20) -> 0 | V20: 10 | W20: 沈庆玲 | X20: =SUMIF($B:$B,$W20,$S:$S) -> 870
A21: 46221 | B21: 韩愈 | C21: 客房经理 | E21: 5 | N21: =SUMPRODUCT($G$2:$M$2,G21:M21) -> 0 | O21: 0 | P21: =IFERROR(IF((N21*E21-O21*E21)<0,0,(N21*E21-O21*E21)),"") -> 0 | R21: =IF(Q21="",0,Q21*5) -> 0 | S21: =IF(B21="","",P21+R21) -> 0 | V21: 11 | W21: 曹薇 | X21: =SUMIF($B:$B,$W21,$S:$S) -> 355
A22: 46222 | B22: 韩愈 | C22: 客房经理 | E22: 5 | N22: =SUMPRODUCT($G$2:$M$2,G22:M22) -> 0 | O22: 0 | P22: =IFERROR(IF((N22*E22-O22*E22)<0,0,(N22*E22-O22*E22)),"") -> 0 | R22: =IF(Q22="",0,Q22*5) -> 0 | S22: =IF(B22="","",P22+R22) -> 0 | V22: 12 | X22: =SUMIF($B:$B,$W22,$S:$S) -> 0
A23: 46223 | B23: 韩愈 | C23: 客房经理 | E23: 5 | N23: =SUMPRODUCT($G$2:$M$2,G23:M23) -> 0 | O23: 0 | P23: =IFERROR(IF((N23*E23-O23*E23)<0,0,(N23*E23-O23*E23)),"") -> 0 | R23: =IF(Q23="",0,Q23*5) -> 0 | S23: =IF(B23="","",P23+R23) -> 0 | V23: 13 | X23: =SUMIF($B:$B,$W23,$S:$S) -> 0
A24: 46224 | B24: 韩愈 | C24: 客房经理 | E24: 5 | N24: =SUMPRODUCT($G$2:$M$2,G24:M24) -> 0 | O24: 0 | P24: =IFERROR(IF((N24*E24-O24*E24)<0,0,(N24*E24-O24*E24)),"") -> 0 | R24: =IF(Q24="",0,Q24*5) -> 0 | S24: =IF(B24="","",P24+R24) -> 0 | V24: 14 | X24: =SUMIF($B:$B,$W24,$S:$S) -> 0
A25: 46225 | B25: 韩愈 | C25: 客房经理 | E25: 5 | N25: =SUMPRODUCT($G$2:$M$2,G25:M25) -> 0 | O25: 0 | P25: =IFERROR(IF((N25*E25-O25*E25)<0,0,(N25*E25-O25*E25)),"") -> 0 | R25: =IF(Q25="",0,Q25*5) -> 0 | S25: =IF(B25="","",P25+R25) -> 0 | W25: 合计 | X25: =SUM(X11:X24) -> 9880
A26: 46226 | B26: 韩愈 | C26: 客房经理 | E26: 5 | G26: 4 | N26: =SUMPRODUCT($G$2:$M$2,G26:M26) -> 4 | O26: 0 | P26: =IFERROR(IF((N26*E26-O26*E26)<0,0,(N26*E26-O26*E26)),"") -> 20 | R26: =IF(Q26="",0,Q26*5) -> 0 | S26: =IF(B26="","",P26+R26) -> 20
A27: 46227 | B27: 韩愈 | C27: 客房经理 | E27: 5 | G27: 7 | N27: =SUMPRODUCT($G$2:$M$2,G27:M27) -> 7 | O27: 0 | P27: =IFERROR(IF((N27*E27-O27*E27)<0,0,(N27*E27-O27*E27)),"") -> 35 | R27: =IF(Q27="",0,Q27*5) -> 0 | S27: =IF(B27="","",P27+R27) -> 35 | V27: 做房数合计 | W27: 实际开房数
A28: 46228 | B28: 韩愈 | C28: 客房经理 | E28: 5 | N28: =SUMPRODUCT($G$2:$M$2,G28:M28) -> 0 | O28: 0 | P28: =IFERROR(IF((N28*E28-O28*E28)<0,0,(N28*E28-O28*E28)),"") -> 0 | R28: =IF(Q28="",0,Q28*5) -> 0 | S28: =IF(B28="","",P28+R28) -> 0 | V28: =SUM(G4:M803,Q4:Q93) -> 3739 | W28: 3709
A29: 46229 | B29: 韩愈 | C29: 客房经理 | E29: 5 | N29: =SUMPRODUCT($G$2:$M$2,G29:M29) -> 0 | O29: 0 | P29: =IFERROR(IF((N29*E29-O29*E29)<0,0,(N29*E29-O29*E29)),"") -> 0 | R29: =IF(Q29="",0,Q29*5) -> 0 | S29: =IF(B29="","",P29+R29) -> 0 | V29: 差异 | W29: =+W28-V28 -> -30
A30: 46230 | B30: 韩愈 | C30: 客房经理 | E30: 5 | N30: =SUMPRODUCT($G$2:$M$2,G30:M30) -> 0 | O30: 0 | P30: =IFERROR(IF((N30*E30-O30*E30)<0,0,(N30*E30-O30*E30)),"") -> 0 | R30: =IF(Q30="",0,Q30*5) -> 0 | S30: =IF(B30="","",P30+R30) -> 0
A31: 46231 | B31: 韩愈 | C31: 客房经理 | E31: 5 | N31: =SUMPRODUCT($G$2:$M$2,G31:M31) -> 0 | O31: 0 | P31: =IFERROR(IF((N31*E31-O31*E31)<0,0,(N31*E31-O31*E31)),"") -> 0 | R31: =IF(Q31="",0,Q31*5) -> 0 | S31: =IF(B31="","",P31+R31) -> 0 | V31: 日期 | W31: 金额
A32: 46232 | B32: 韩愈 | C32: 客房经理 | E32: 5 | N32: =SUMPRODUCT($G$2:$M$2,G32:M32) -> 0 | O32: 0 | P32: =IFERROR(IF((N32*E32-O32*E32)<0,0,(N32*E32-O32*E32)),"") -> 0 | R32: =IF(Q32="",0,Q32*5) -> 0 | S32: =IF(B32="","",P32+R32) -> 0 | V32: 46204 | W32: =SUMIF(A:A,V32,S:S) -> 165
A33: 46233 | B33: 韩愈 | C33: 客房经理 | E33: 5 | N33: =SUMPRODUCT($G$2:$M$2,G33:M33) -> 0 | O33: 0 | P33: =IFERROR(IF((N33*E33-O33*E33)<0,0,(N33*E33-O33*E33)),"") -> 0 | R33: =IF(Q33="",0,Q33*5) -> 0 | S33: =IF(B33="","",P33+R33) -> 0 | V33: 46205 | W33: =SUMIF(A:A,V33,S:S) -> 220
A34: 46234 | B34: 韩愈 | C34: 客房经理 | E34: 5 | N34: =SUMPRODUCT($G$2:$M$2,G34:M34) -> 0 | O34: 0 | P34: =IFERROR(IF((N34*E34-O34*E34)<0,0,(N34*E34-O34*E34)),"") -> 0 | R34: 0 | S34: =IF(B34="","",P34+R34) -> 0 | V34: 46206 | W34: =SUMIF(A:A,V34,S:S) -> 250
A35: 46204 | B35: 张凯娜 | C35: 客房主管 | E35: 5 | N35: =SUMPRODUCT($G$2:$M$2,G35:M35) -> 0 | O35: 0 | P35: =IFERROR(IF((N35*E35-O35*E35)<0,0,(N35*E35-O35*E35)),"") -> 0 | R35: =IF(Q35="",0,Q35*5) -> 0 | S35: =IF(B35="","",P35+R35) -> 0 | V35: 46207 | W35: =SUMIF(A:A,V35,S:S) -> 335
A36: 46205 | B36: 张凯娜 | C36: 客房主管 | E36: 5 | N36: =SUMPRODUCT($G$2:$M$2,G36:M36) -> 0 | O36: 0 | P36: =IFERROR(IF((N36*E36-O36*E36)<0,0,(N36*E36-O36*E36)),"") -> 0 | R36: =IF(Q36="",0,Q36*5) -> 0 | S36: =IF(B36="","",P36+R36) -> 0 | V36: 46208 | W36: =SUMIF(A:A,V36,S:S) -> 355
A37: 46206 | B37: 张凯娜 | C37: 客房主管 | E37: 5 | N37: =SUMPRODUCT($G$2:$M$2,G37:M37) -> 0 | O37: 0 | P37: =IFERROR(IF((N37*E37-O37*E37)<0,0,(N37*E37-O37*E37)),"") -> 0 | R37: =IF(Q37="",0,Q37*5) -> 0 | S37: =IF(B37="","",P37+R37) -> 0 | V37: 46209 | W37: =SUMIF(A:A,V37,S:S) -> 330
A38: 46207 | B38: 张凯娜 | C38: 客房主管 | E38: 5 | N38: =SUMPRODUCT($G$2:$M$2,G38:M38) -> 0 | O38: 0 | P38: =IFERROR(IF((N38*E38-O38*E38)<0,0,(N38*E38-O38*E38)),"") -> 0 | R38: =IF(Q38="",0,Q38*5) -> 0 | S38: =IF(B38="","",P38+R38) -> 0 | V38: 46210 | W38: =SUMIF(A:A,V38,S:S) -> 280
A39: 46208 | B39: 张凯娜 | C39: 客房主管 | E39: 5 | N39: =SUMPRODUCT($G$2:$M$2,G39:M39) -> 0 | O39: 0 | P39: =IFERROR(IF((N39*E39-O39*E39)<0,0,(N39*E39-O39*E39)),"") -> 0 | R39: =IF(Q39="",0,Q39*5) -> 0 | S39: =IF(B39="","",P39+R39) -> 0 | V39: 46211 | W39: =SUMIF($A:$A,V39,$S:$S) -> 445
A40: 46209 | B40: 张凯娜 | C40: 客房主管 | E40: 5 | N40: =SUMPRODUCT($G$2:$M$2,G40:M40) -> 0 | O40: 0 | P40: =IFERROR(IF((N40*E40-O40*E40)<0,0,(N40*E40-O40*E40)),"") -> 0 | R40: =IF(Q40="",0,Q40*5) -> 0 | S40: =IF(B40="","",P40+R40) -> 0 | V40: 46212 | W40: =SUMIF($A:$A,V40,$S:$S) -> 400
A41: 46210 | B41: 张凯娜 | C41: 客房主管 | E41: 5 | N41: =SUMPRODUCT($G$2:$M$2,G41:M41) -> 0 | O41: 0 | P41: =IFERROR(IF((N41*E41-O41*E41)<0,0,(N41*E41-O41*E41)),"") -> 0 | R41: =IF(Q41="",0,Q41*5) -> 0 | S41: =IF(B41="","",P41+R41) -> 0 | V41: 46213 | W41: =SUMIF($A:$A,V41,$S:$S) -> 450
A42: 46211 | B42: 张凯娜 | C42: 客房主管 | E42: 5 | N42: =SUMPRODUCT($G$2:$M$2,G42:M42) -> 0 | O42: 0 | P42: =IFERROR(IF((N42*E42-O42*E42)<0,0,(N42*E42-O42*E42)),"") -> 0 | R42: =IF(Q42="",0,Q42*5) -> 0 | S42: =IF(B42="","",P42+R42) -> 0 | V42: 46214 | W42: =SUMIF($A:$A,V42,$S:$S) -> 485
A43: 46212 | B43: 张凯娜 | C43: 客房主管 | E43: 5 | N43: =SUMPRODUCT($G$2:$M$2,G43:M43) -> 0 | O43: 0 | P43: =IFERROR(IF((N43*E43-O43*E43)<0,0,(N43*E43-O43*E43)),"") -> 0 | R43: =IF(Q43="",0,Q43*5) -> 0 | S43: =IF(B43="","",P43+R43) -> 0 | V43: 46215 | W43: =SUMIF($A:$A,V43,$S:$S) -> 320
A44: 46213 | B44: 张凯娜 | C44: 客房主管 | E44: 5 | N44: =SUMPRODUCT($G$2:$M$2,G44:M44) -> 0 | O44: 0 | P44: =IFERROR(IF((N44*E44-O44*E44)<0,0,(N44*E44-O44*E44)),"") -> 0 | R44: =IF(Q44="",0,Q44*5) -> 0 | S44: =IF(B44="","",P44+R44) -> 0 | V44: 46216 | W44: =SUMIF($A:$A,V44,$S:$S) -> 240
A45: 46214 | B45: 张凯娜 | C45: 客房主管 | E45: 5 | N45: =SUMPRODUCT($G$2:$M$2,G45:M45) -> 0 | O45: 0 | P45: =IFERROR(IF((N45*E45-O45*E45)<0,0,(N45*E45-O45*E45)),"") -> 0 | R45: =IF(Q45="",0,Q45*5) -> 0 | S45: =IF(B45="","",P45+R45) -> 0 | V45: 46217 | W45: =SUMIF($A:$A,V45,$S:$S) -> 210
A46: 46215 | B46: 张凯娜 | C46: 客房主管 | E46: 5 | N46: =SUMPRODUCT($G$2:$M$2,G46:M46) -> 0 | O46: 0 | P46: =IFERROR(IF((N46*E46-O46*E46)<0,0,(N46*E46-O46*E46)),"") -> 0 | R46: =IF(Q46="",0,Q46*5) -> 0 | S46: =IF(B46="","",P46+R46) -> 0 | V46: 46218 | W46: =SUMIF($A:$A,V46,$S:$S) -> 300
A47: 46216 | B47: 张凯娜 | C47: 客房主管 | E47: 5 | N47: =SUMPRODUCT($G$2:$M$2,G47:M47) -> 0 | O47: 0 | P47: =IFERROR(IF((N47*E47-O47*E47)<0,0,(N47*E47-O47*E47)),"") -> 0 | R47: =IF(Q47="",0,Q47*5) -> 0 | S47: =IF(B47="","",P47+R47) -> 0 | V47: 46219 | W47: =SUMIF($A:$A,V47,$S:$S) -> 375
A48: 46217 | B48: 张凯娜 | C48: 客房主管 | E48: 5 | N48: =SUMPRODUCT($G$2:$M$2,G48:M48) -> 0 | O48: 0 | P48: =IFERROR(IF((N48*E48-O48*E48)<0,0,(N48*E48-O48*E48)),"") -> 0 | R48: =IF(Q48="",0,Q48*5) -> 0 | S48: =IF(B48="","",P48+R48) -> 0 | V48: 46220 | W48: =SUMIF($A:$A,V48,$S:$S) -> 295
A49: 46218 | B49: 张凯娜 | C49: 客房主管 | E49: 5 | N49: =SUMPRODUCT($G$2:$M$2,G49:M49) -> 0 | O49: 0 | P49: =IFERROR(IF((N49*E49-O49*E49)<0,0,(N49*E49-O49*E49)),"") -> 0 | R49: =IF(Q49="",0,Q49*5) -> 0 | S49: =IF(B49="","",P49+R49) -> 0 | V49: 46221 | W49: =SUMIF($A:$A,V49,$S:$S) -> 295
A50: 46219 | B50: 张凯娜 | C50: 客房主管 | E50: 5 | N50: =SUMPRODUCT($G$2:$M$2,G50:M50) -> 0 | O50: 0 | P50: =IFERROR(IF((N50*E50-O50*E50)<0,0,(N50*E50-O50*E50)),"") -> 0 | R50: =IF(Q50="",0,Q50*5) -> 0 | S50: =IF(B50="","",P50+R50) -> 0 | V50: 46222 | W50: =SUMIF($A:$A,V50,$S:$S) -> 265
... A52: 46221 | B52: 张凯娜 | C52: 客房主管 | E52: 5 | N52: =SUMPRODUCT($G$2:$M$2,G52:M52) -> 0 | O52: 0 | P52: =IFERROR(IF((N52*E52-O52*E52)<0,0,(N52*E52-O52*E52)),"") -> 0 | R52: =IF(Q52="",0,Q52*5) -> 0 | S52: =IF(B52="","",P52+R52) -> 0 | V52: 46224 | W52: =SUMIF($A:$A,V52,$S:$S) -> 260
A53: 46222 | B53: 张凯娜 | C53: 客房主管 | E53: 5 | G53: 16 | N53: =SUMPRODUCT($G$2:$M$2,G53:M53) -> 16 | O53: 0 | P53: =IFERROR(IF((N53*E53-O53*E53)<0,0,(N53*E53-O53*E53)),"") -> 80 | R53: =IF(Q53="",0,Q53*5) -> 0 | S53: =IF(B53="","",P53+R53) -> 80 | V53: 46225 | W53: =SUMIF($A:$A,V53,$S:$S) -> 365
A54: 46223 | B54: 张凯娜 | C54: 客房主管 | E54: 5 | G54: 8 | N54: =SUMPRODUCT($G$2:$M$2,G54:M54) -> 8 | O54: 0 | P54: =IFERROR(IF((N54*E54-O54*E54)<0,0,(N54*E54-O54*E54)),"") -> 40 | R54: =IF(Q54="",0,Q54*5) -> 0 | S54: =IF(B54="","",P54+R54) -> 40 | V54: 46226 | W54: =SUMIF($A:$A,V54,$S:$S) -> 345
A55: 46224 | B55: 张凯娜 | C55: 客房主管 | E55: 5 | G55: 8 | N55: =SUMPRODUCT($G$2:$M$2,G55:M55) -> 8 | O55: 0 | P55: =IFERROR(IF((N55*E55-O55*E55)<0,0,(N55*E55-O55*E55)),"") -> 40 | R55: =IF(Q55="",0,Q55*5) -> 0 | S55: =IF(B55="","",P55+R55) -> 40 | V55: 46227 | W55: =SUMIF($A:$A,V55,$S:$S) -> 375
A56: 46225 | B56: 张凯娜 | C56: 客房主管 | E56: 5 | G56: 13 | N56: =SUMPRODUCT($G$2:$M$2,G56:M56) -> 13 | O56: 0 | P56: =IFERROR(IF((N56*E56-O56*E56)<0,0,(N56*E56-O56*E56)),"") -> 65 | R56: =IF(Q56="",0,Q56*5) -> 0 | S56: =IF(B56="","",P56+R56) -> 65 | V56: 46228 | W56: =SUMIF($A:$A,V56,$S:$S) -> 320
A57: 46226 | B57: 张凯娜 | C57: 客房主管 | E57: 5 | G57: 7 | N57: =SUMPRODUCT($G$2:$M$2,G57:M57) -> 7 | O57: 0 | P57: =IFERROR(IF((N57*E57-O57*E57)<0,0,(N57*E57-O57*E57)),"") -> 35 | R57: =IF(Q57="",0,Q57*5) -> 0 | S57: =IF(B57="","",P57+R57) -> 35 | V57: 46229 | W57: =SUMIF($A:$A,V57,$S:$S) -> 380
A58: 46227 | B58: 张凯娜 | C58: 客房主管 | E58: 5 | G58: 11 | N58: =SUMPRODUCT($G$2:$M$2,G58:M58) -> 11 | O58: 0 | P58: =IFERROR(IF((N58*E58-O58*E58)<0,0,(N58*E58-O58*E58)),"") -> 55 | R58: =IF(Q58="",0,Q58*5) -> 0 | S58: =IF(B58="","",P58+R58) -> 55 | V58: 46230 | W58: =SUMIF($A:$A,V58,$S:$S) -> 245
A59: 46228 | B59: 张凯娜 | C59: 客房主管 | E59: 5 | G59: 8 | N59: =SUMPRODUCT($G$2:$M$2,G59:M59) -> 8 | O59: 0 | P59: =IFERROR(IF((N59*E59-O59*E59)<0,0,(N59*E59-O59*E59)),"") -> 40 | R59: =IF(Q59="",0,Q59*5) -> 0 | S59: =IF(B59="","",P59+R59) -> 40 | V59: 46231 | W59: =SUMIF($A:$A,V59,$S:$S) -> 265
A60: 46229 | B60: 张凯娜 | C60: 客房主管 | E60: 5 | G60: 8 | N60: =SUMPRODUCT($G$2:$M$2,G60:M60) -> 8 | O60: 0 | P60: =IFERROR(IF((N60*E60-O60*E60)<0,0,(N60*E60-O60*E60)),"") -> 40 | R60: =IF(Q60="",0,Q60*5) -> 0 | S60: =IF(B60="","",P60+R60) -> 40 | V60: 46232 | W60: =SUMIF($A:$A,V60,$S:$S) -> 390
A61: 46230 | B61: 张凯娜 | C61: 客房主管 | E61: 5 | N61: =SUMPRODUCT($G$2:$M$2,G61:M61) -> 0 | O61: 0 | P61: =IFERROR(IF((N61*E61-O61*E61)<0,0,(N61*E61-O61*E61)),"") -> 0 | R61: =IF(Q61="",0,Q61*5) -> 0 | S61: =IF(B61="","",P61+R61) -> 0 | V61: 46233 | W61: =SUMIF($A:$A,V61,$S:$S) -> 365
A62: 46231 | B62: 张凯娜 | C62: 客房主管 | E62: 5 | G62: 13 | N62: =SUMPRODUCT($G$2:$M$2,G62:M62) -> 13 | O62: 0 | P62: =IFERROR(IF((N62*E62-O62*E62)<0,0,(N62*E62-O62*E62)),"") -> 65 | R62: =IF(Q62="",0,Q62*5) -> 0 | S62: =IF(B62="","",P62+R62) -> 65 | V62: 46234 | W62: =SUMIF($A:$A,V62,$S:$S) -> 340
A63: 46232 | B63: 张凯娜 | C63: 客房主管 | E63: 5 | G63: 8 | N63: =SUMPRODUCT($G$2:$M$2,G63:M63) -> 8 | O63: 0 | P63: =IFERROR(IF((N63*E63-O63*E63)<0,0,(N63*E63-O63*E63)),"") -> 40 | R63: =IF(Q63="",0,Q63*5) -> 0 | S63: =IF(B63="","",P63+R63) -> 40
A64: 46233 | B64: 张凯娜 | C64: 客房主管 | E64: 5 | G64: 16 | N64: =SUMPRODUCT($G$2:$M$2,G64:M64) -> 16 | O64: 0 | P64: =IFERROR(IF((N64*E64-O64*E64)<0,0,(N64*E64-O64*E64)),"") -> 80 | R64: =IF(Q64="",0,Q64*5) -> 0 | S64: =IF(B64="","",P64+R64) -> 80 | W64: =SUM(W32:W63) -> 9880
A65: 46234 | B65: 张凯娜 | C65: 客房主管 | E65: 5 | G65: 8 | L65: 1 | N65: 0 | O65: 0 | P65: 0 | R65: 0 | S65: 0
A66: 46204 | B66: 初立玲 | C66: 客房服务员 | E66: 5 | G66: 14 | N66: =SUMPRODUCT($G$2:$M$2,G66:M66) -> 14 | O66: 8 | P66: =IFERROR(IF((N66*E66-O66*E66)<0,0,(N66*E66-O66*E66)),"") -> 30 | R66: =IF(Q66="",0,Q66*5) -> 0 | S66: =IF(B66="","",P66+R66) -> 30
A67: 46205 | B67: 初立玲 | C67: 客房服务员 | E67: 5 | G67: 12 | N67: =SUMPRODUCT($G$2:$M$2,G67:M67) -> 12 | O67: 8 | P67: =IFERROR(IF((N67*E67-O67*E67)<0,0,(N67*E67-O67*E67)),"") -> 20 | R67: =IF(Q67="",0,Q67*5) -> 0 | S67: =IF(B67="","",P67+R67) -> 20
A68: 46206 | B68: 初立玲 | C68: 客房服务员 | E68: 5 | N68: =SUMPRODUCT($G$2:$M$2,G68:M68) -> 0 | O68: 8 | P68: =IFERROR(IF((N68*E68-O68*E68)<0,0,(N68*E68-O68*E68)),"") -> 0 | R68: =IF(Q68="",0,Q68*5) -> 0 | S68: =IF(B68="","",P68+R68) -> 0
A69: 46207 | B69: 初立玲 | C69: 客房服务员 | E69: 5 | G69: 16 | N69: =SUMPRODUCT($G$2:$M$2,G69:M69) -> 16 | O69: 8 | P69: =IFERROR(IF((N69*E69-O69*E69)<0,0,(N69*E69-O69*E69)),"") -> 40 | R69: =IF(Q69="",0,Q69*5) -> 0 | S69: =IF(B69="","",P69+R69) -> 40
A70: 46208 | B70: 初立玲 | C70: 客房服务员 | E70: 5 | G70: 18 | N70: =SUMPRODUCT($G$2:$M$2,G70:M70) -> 18 | O70: 8 | P70: =IFERROR(IF((N70*E70-O70*E70)<0,0,(N70*E70-O70*E70)),"") -> 50 | R70: =IF(Q70="",0,Q70*5) -> 0 | S70: =IF(B70="","",P70+R70) -> 50
A71: 46209 | B71: 初立玲 | C71: 客房服务员 | E71: 5 | G71: 18 | N71: =SUMPRODUCT($G$2:$M$2,G71:M71) -> 18 | O71: 8 | P71: =IFERROR(IF((N71*E71-O71*E71)<0,0,(N71*E71-O71*E71)),"") -> 50 | R71: =IF(Q71="",0,Q71*5) -> 0 | S71: =IF(B71="","",P71+R71) -> 50
A72: 46210 | B72: 初立玲 | C72: 客房服务员 | E72: 5 | G72: 18 | N72: =SUMPRODUCT($G$2:$M$2,G72:M72) -> 18 | O72: 8 | P72: =IFERROR(IF((N72*E72-O72*E72)<0,0,(N72*E72-O72*E72)),"") -> 50 | R72: =IF(Q72="",0,Q72*5) -> 0 | S72: =IF(B72="","",P72+R72) -> 50
A73: 46211 | B73: 初立玲 | C73: 客房服务员 | E73: 5 | G73: 18 | N73: =SUMPRODUCT($G$2:$M$2,G73:M73) -> 18 | O73: 8 | P73: =IFERROR(IF((N73*E73-O73*E73)<0,0,(N73*E73-O73*E73)),"") -> 50 | R73: =IF(Q73="",0,Q73*5) -> 0 | S73: =IF(B73="","",P73+R73) -> 50
A74: 46212 | B74: 初立玲 | C74: 客房服务员 | E74: 5 | G74: 18 | L74: 1 | N74: =SUMPRODUCT($G$2:$M$2,G74:M74) -> 20 | O74: 8 | P74: =IFERROR(IF((N74*E74-O74*E74)<0,0,(N74*E74-O74*E74)),"") -> 60 | R74: =IF(Q74="",0,Q74*5) -> 0 | S74: =IF(B74="","",P74+R74) -> 60
A75: 46213 | B75: 初立玲 | C75: 客房服务员 | E75: 5 | G75: 17 | N75: =SUMPRODUCT($G$2:$M$2,G75:M75) -> 17 | O75: 8 | P75: =IFERROR(IF((N75*E75-O75*E75)<0,0,(N75*E75-O75*E75)),"") -> 45 | R75: =IF(Q75="",0,Q75*5) -> 0 | S75: =IF(B75="","",P75+R75) -> 45
A76: 46214 | B76: 初立玲 | C76: 客房服务员 | E76: 5 | N76: =SUMPRODUCT($G$2:$M$2,G76:M76) -> 0 | O76: 8 | P76: =IFERROR(IF((N76*E76-O76*E76)<0,0,(N76*E76-O76*E76)),"") -> 0 | R76: =IF(Q76="",0,Q76*5) -> 0 | S76: =IF(B76="","",P76+R76) -> 0
A77: 46215 | B77: 初立玲 | C77: 客房服务员 | E77: 5 | N77: =SUMPRODUCT($G$2:$M$2,G77:M77) -> 0 | O77: 8 | P77: =IFERROR(IF((N77*E77-O77*E77)<0,0,(N77*E77-O77*E77)),"") -> 0 | R77: =IF(Q77="",0,Q77*5) -> 0 | S77: =IF(B77="","",P77+R77) -> 0
A78: 46216 | B78: 初立玲 | C78: 客房服务员 | E78: 5 | N78: =SUMPRODUCT($G$2:$M$2,G78:M78) -> 0 | O78: 8 | P78: =IFERROR(IF((N78*E78-O78*E78)<0,0,(N78*E78-O78*E78)),"") -> 0 | R78: =IF(Q78="",0,Q78*5) -> 0 | S78: =IF(B78="","",P78+R78) -> 0
A79: 46217 | B79: 初立玲 | C79: 客房服务员 | E79: 5 | N79: =SUMPRODUCT($G$2:$M$2,G79:M79) -> 0 | O79: 8 | P79: =IFERROR(IF((N79*E79-O79*E79)<0,0,(N79*E79-O79*E79)),"") -> 0 | R79: =IF(Q79="",0,Q79*5) -> 0 | S79: =IF(B79="","",P79+R79) -> 0
A80: 46218 | B80: 初立玲 | C80: 客房服务员 | E80: 5 | G80: 18 | N80: =SUMPRODUCT($G$2:$M$2,G80:M80) -> 18 | O80: 8 | P80: =IFERROR(IF((N80*E80-O80*E80)<0,0,(N80*E80-O80*E80)),"") -> 50 | R80: =IF(Q80="",0,Q80*5) -> 0 | S80: =IF(B80="","",P80+R80) -> 50
A81: 46219 | B81: 初立玲 | C81: 客房服务员 | E81: 5 | G81: 17 | L81: 1 | N81: =SUMPRODUCT($G$2:$M$2,G81:M81) -> 19 | O81: 8 | P81: =IFERROR(IF((N81*E81-O81*E81)<0,0,(N81*E81-O81*E81)),"") -> 55 | R81: =IF(Q81="",0,Q81*5) -> 0 | S81: =IF(B81="","",P81+R81) -> 55
A82: 46220 | B82: 初立玲 | C82: 客房服务员 | E82: 5 | G82: 17 | L82: 1 | N82: =SUMPRODUCT($G$2:$M$2,G82:M82) -> 19 | O82: 8 | P82: =IFERROR(IF((N82*E82-O82*E82)<0,0,(N82*E82-O82*E82)),"") -> 55 | R82: =IF(Q82="",0,Q82*5) -> 0 | S82: =IF(B82="","",P82+R82) -> 55
A83: 46221 | B83: 初立玲 | C83: 客房服务员 | E83: 5 | G83: 8 | L83: 1 | N83: =SUMPRODUCT($G$2:$M$2,G83:M83) -> 10 | O83: 8 | P83: =IFERROR(IF((N83*E83-O83*E83)<0,0,(N83*E83-O83*E83)),"") -> 10 | R83: =IF(Q83="",0,Q83*5) -> 0 | S83: =IF(B83="","",P83+R83) -> 10
A84: 46222 | B84: 初立玲 | C84: 客房服务员 | E84: 5 | N84: =SUMPRODUCT($G$2:$M$2,G84:M84) -> 0 | O84: 8 | P84: =IFERROR(IF((N84*E84-O84*E84)<0,0,(N84*E84-O84*E84)),"") -> 0 | R84: =IF(Q84="",0,Q84*5) -> 0 | S84: =IF(B84="","",P84+R84) -> 0
A85: 46223 | B85: 初立玲 | C85: 客房服务员 | E85: 5 | G85: 13 | L85: 1 | N85: 0 | O85: 8 | P85: 0 | R85: =IF(Q85="",0,Q85*5) -> 0 | S85: =IF(B85="","",P85+R85) -> 0
A86: 46224 | B86: 初立玲 | C86: 客房服务员 | E86: 5 | G86: 16 | N86: =SUMPRODUCT($G$2:$M$2,G86:M86) -> 16 | O86: 8 | P86: =IFERROR(IF((N86*E86-O86*E86)<0,0,(N86*E86-O86*E86)),"") -> 40 | R86: =IF(Q86="",0,Q86*5) -> 0 | S86: =IF(B86="","",P86+R86) -> 40
A87: 46225 | B87: 初立玲 | C87: 客房服务员 | E87: 5 | G87: 18 | L87: 1 | N87: =SUMPRODUCT($G$2:$M$2,G87:M87) -> 20 | O87: 8 | P87: =IFERROR(IF((N87*E87-O87*E87)<0,0,(N87*E87-O87*E87)),"") -> 60 | R87: =IF(Q87="",0,Q87*5) -> 0 | S87: =IF(B87="","",P87+R87) -> 60
A88: 46226 | B88: 初立玲 | C88: 客房服务员 | E88: 5 | G88: 17 | L88: 1 | N88: =SUMPRODUCT($G$2:$M$2,G88:M88) -> 19 | O88: 8 | P88: =IFERROR(IF((N88*E88-O88*E88)<0,0,(N88*E88-O88*E88)),"") -> 55 | R88: =IF(Q88="",0,Q88*5) -> 0 | S88: =IF(B88="","",P88+R88) -> 55
A89: 46227 | B89: 初立玲 | C89: 客房服务员 | E89: 5 | G89: 15 | L89: 1 | N89: =SUMPRODUCT($G$2:$M$2,G89:M89) -> 17 | O89: 8 | P89: =IFERROR(IF((N89*E89-O89*E89)<0,0,(N89*E89-O89*E89)),"") -> 45 | R89: =IF(Q89="",0,Q89*5) -> 0 | S89: =IF(B89="","",P89+R89) -> 45
A90: 46228 | B90: 初立玲 | C90: 客房服务员 | E90: 5 | G90: 17 | N90: =SUMPRODUCT($G$2:$M$2,G90:M90) -> 17 | O90: 8 | P90: =IFERROR(IF((N90*E90-O90*E90)<0,0,(N90*E90-O90*E90)),"") -> 45 | R90: =IF(Q90="",0,Q90*5) -> 0 | S90: =IF(B90="","",P90+R90) -> 45
A91: 46229 | B91: 初立玲 | C91: 客房服务员 | E91: 5 | G91: 15 | N91: =SUMPRODUCT($G$2:$M$2,G91:M91) -> 15 | O91: 8 | P91: =IFERROR(IF((N91*E91-O91*E91)<0,0,(N91*E91-O91*E91)),"") -> 35 | R91: =IF(Q91="",0,Q91*5) -> 0 | S91: =IF(B91="","",P91+R91) -> 35
A92: 46230 | B92: 初立玲 | C92: 客房服务员 | E92: 5 | N92: =SUMPRODUCT($G$2:$M$2,G92:M92) -> 0 | O92: 8 | P92: =IFERROR(IF((N92*E92-O92*E92)<0,0,(N92*E92-O92*E92)),"") -> 0 | R92: =IF(Q92="",0,Q92*5) -> 0 | S92: =IF(B92="","",P92+R92) -> 0
A93: 46231 | B93: 初立玲 | C93: 客房服务员 | E93: 5 | N93: =SUMPRODUCT($G$2:$M$2,G93:M93) -> 0 | O93: 8 | P93: =IFERROR(IF((N93*E93-O93*E93)<0,0,(N93*E93-O93*E93)),"") -> 0 | R93: =IF(Q93="",0,Q93*5) -> 0 | S93: =IF(B93="","",P93+R93) -> 0
C94: 29 | E94: 8 | N94: =SUMPRODUCT($G$2:$M$2,G94:M94) -> 0 | O94: 8 | P94: =IFERROR(IF((N94*E94-O94*E94)<0,0,(N94*E94-O94*E94)),"") -> 0 | R94: =IF(Q94="",0,Q94*5) -> 0 | S94: =IF(B94="","",P94+R94)
E95: 8 | N95: =SUMPRODUCT($G$2:$M$2,G95:M95) -> 0 | O95: 8 | P95: =IFERROR(IF((N95*E95-O95*E95)<0,0,(N95*E95-O95*E95)),"") -> 0 | R95: =IF(Q95="",0,Q95*5) -> 0 | S95: =IF(B95="","",P95+R95)
E96: 8 | N96: =SUMPRODUCT($G$2:$M$2,G96:M96) -> 0 | O96: 8 | P96: =IFERROR(IF((N96*E96-O96*E96)<0,0,(N96*E96-O96*E96)),"") -> 0 | R96: =IF(Q96="",0,Q96*5) -> 0 | S96: =IF(B96="","",P96+R96)
E97: 8 | N97: =SUMPRODUCT($G$2:$M$2,G97:M97) -> 0 | O97: 8 | P97: =IFERROR(IF((N97*E97-O97*E97)<0,0,(N97*E97-O97*E97)),"") -> 0 | R97: =IF(Q97="",0,Q97*5) -> 0 | S97: =IF(B97="","",P97+R97)
E98: 8 | N98: =SUMPRODUCT($G$2:$M$2,G98:M98) -> 0 | O98: 8 | P98: =IFERROR(IF((N98*E98-O98*E98)<0,0,(N98*E98-O98*E98)),"") -> 0 | R98: =IF(Q98="",0,Q98*5) -> 0 | S98: =IF(B98="","",P98+R98)
E99: 8 | N99: =SUMPRODUCT($G$2:$M$2,G99:M99) -> 0 | O99: 8 | P99: =IFERROR(IF((N99*E99-O99*E99)<0,0,(N99*E99-O99*E99)),"") -> 0 | R99: =IF(Q99="",0,Q99*5) -> 0 | S99: =IF(B99="","",P99+R99)
E100: 8 | N100: =SUMPRODUCT($G$2:$M$2,G100:M100) -> 0 | O100: 8 | P100: =IFERROR(IF((N100*E100-O100*E100)<0,0,(N100*E100-O100*E100)),"") -> 0 | R100: =IF(Q100="",0,Q100*5) -> 0 | S100: =IF(B100="","",P100+R100)
E101: 8 | N101: =SUMPRODUCT($G$2:$M$2,G101:M101) -> 0 | O101: 8 | P101: =IFERROR(IF((N101*E101-O101*E101)<0,0,(N101*E101-O101*E101)),"") -> 0 | R101: =IF(Q101="",0,Q101*5) -> 0 | S101: =IF(B101="","",P101+R101)
...

Sheet 洗涤费录入
B1: 布草洗涤表
B2: 酒店名称：
A3: 序号 | B3: 货品名称 | C3: 规格型号 | D3: 单位 | E3: 单价（根据实际情况填写） | F3: 洗涤合计 | G3: 出库金额 | H3: 1号 | I3: 2号 | J3: 3号 | K3: 4号 | L3: 5号 | M3: 6号 | N3: 7号 | O3: 8号 | P3: 9号 | Q3: 10号 | R3: 11号 | S3: 12号 | T3: 13号 | U3: 14号 | V3: 15号 | W3: 16号 | X3: 17号 | Y3: 18号 | Z3: 19号 | AA3: 20号 | AB3: 21号 | AC3: 22号 | AD3: 23号 | AE3: 24号 | AF3: 25号 | AG3: 26号 | AH3: 27号 | AI3: 28号 | AJ3: 29号 | AK3: 30号 | AL3: 31号
F4: 出库 | H4: 出库 | I4: 出库 | J4: 出库 | K4: 出库 | L4: 出库 | M4: 出库 | N4: 出库 | O4: 出库 | P4: 出库 | Q4: 出库 | R4: 出库 | S4: 出库 | T4: 出库 | U4: 出库 | V4: 出库 | W4: 出库 | X4: 出库 | Y4: 出库 | Z4: 出库 | AA4: 出库 | AB4: 出库 | AC4: 出库 | AD4: 出库 | AE4: 出库 | AF4: 出库 | AG4: 出库 | AH4: 出库 | AI4: 出库 | AJ4: 出库 | AK4: 出库 | AL4: 出库
A5: 1 | B5: （大、小）床单 | E5: 1.43 | F5: =SUMIF($H$4:$BQ$4,$F$4,$H5:$BQ5) -> 3496 | G5: =+E5*F5 -> 4999.28 | H5: 104 | I5: 77 | J5: 73 | K5: 93 | L5: 128 | M5: 148 | N5: 105 | O5: 109 | P5: 130 | Q5: 110 | R5: 146 | S5: 151 | T5: 117 | U5: 105 | V5: 89 | W5: 85 | X5: 127 | Y5: 145 | Z5: 124 | AA5: 139 | AB5: 113 | AC5: 87 | AD5: 97 | AE5: 88 | AF5: 121 | AG5: 104 | AH5: 152 | AI5: 78 | AJ5: 98 | AK5: 138 | AL5: 115
A6: 2 | B6: （大、小被罩） | E6: 1.69 | F6: =SUMIF($H$4:$BQ$4,$F$4,$H6:$BQ6) -> 3589 | G6: =+E6*F6 -> 6065.41 | H6: 112 | I6: 75 | J6: 77 | K6: 96 | L6: 134 | M6: 143 | N6: 107 | O6: 113 | P6: 134 | Q6: 117 | R6: 146 | S6: 155 | T6: 121 | U6: 105 | V6: 88 | W6: 87 | X6: 135 | Y6: 153 | Z6: 131 | AA6: 142 | AB6: 119 | AC6: 93 | AD6: 100 | AE6: 90 | AF6: 116 | AG6: 103 | AH6: 150 | AI6: 74 | AJ6: 95 | AK6: 154 | AL6: 124
A7: 3 | B7: 枕套 | E7: 0.71 | F7: =SUMIF($H$4:$BQ$4,$F$4,$H7:$BQ7) -> 10169 | G7: =+E7*F7 -> 7219.99 | H7: 430 | I7: 220 | J7: 270 | K7: 267 | L7: 370 | M7: 403 | N7: 380 | O7: 311 | P7: 373 | Q7: 308 | R7: 430 | S7: 404 | T7: 345 | U7: 317 | V7: 257 | W7: 286 | X7: 390 | Y7: 422 | Z7: 377 | AA7: 361 | AB7: 287 | AC7: 270 | AD7: 270 | AE7: 265 | AF7: 326 | AG7: 266 | AH7: 395 | AI7: 223 | AJ7: 266 | AK7: 343 | AL7: 337
A8: 4 | B8: 浴巾 | E8: 0.98 | F8: =SUMIF($H$4:$BQ$4,$F$4,$H8:$BQ8) -> 4754 | G8: =+E8*F8 -> 4658.92 | H8: 101 | I8: 112 | J8: 124 | K8: 134 | L8: 174 | M8: 164 | N8: 137 | O8: 152 | P8: 172 | Q8: 141 | R8: 158 | S8: 191 | T8: 185 | U8: 148 | V8: 131 | W8: 131 | X8: 172 | Y8: 207 | Z8: 179 | AA8: 209 | AB8: 180 | AC8: 163 | AD8: 147 | AE8: 128 | AF8: 150 | AG8: 158 | AH8: 176 | AI8: 115 | AJ8: 113 | AK8: 153 | AL8: 149
A9: 5 | B9: 毛巾 | E9: 0.62 | F9: =SUMIF($H$4:$BQ$4,$F$4,$H9:$BQ9) -> 4005 | G9: =+E9*F9 -> 2483.1 | H9: 103 | I9: 92 | J9: 110 | K9: 114 | L9: 124 | M9: 122 | N9: 123 | O9: 142 | P9: 149 | Q9: 131 | R9: 142 | S9: 140 | T9: 167 | U9: 138 | V9: 128 | W9: 109 | X9: 181 | Y9: 115 | Z9: 158 | AA9: 162 | AB9: 162 | AC9: 151 | AD9: 135 | AE9: 119 | AF9: 100 | AG9: 139 | AH9: 130 | AI9: 87 | AJ9: 100 | AK9: 113 | AL9: 119
A10: 6 | B10: 方巾 | E10: 0.4 | F10: =SUMIF($H$4:$BQ$4,$F$4,$H10:$BQ10) -> 3689 | G10: =+E10*F10 -> 1475.6 | H10: 117 | I10: 94 | J10: 104 | K10: 116 | L10: 134 | M10: 127 | N10: 113 | O10: 131 | P10: 123 | Q10: 145 | R10: 122 | S10: 116 | T10: 133 | U10: 102 | V10: 95 | W10: 103 | X10: 144 | Y10: 112 | Z10: 135 | AA10: 143 | AB10: 119 | AC10: 120 | AD10: 123 | AE10: 118 | AF10: 94 | AG10: 106 | AH10: 152 | AI10: 96 | AJ10: 101 | AK10: 141 | AL10: 110
A11: 7 | B11: 地巾 | E11: 0.44 | F11: =SUMIF($H$4:$BQ$4,$F$4,$H11:$BQ11) -> 2585 | G11: =+E11*F11 -> 1137.4 | H11: 66 | I11: 65 | J11: 63 | K11: 75 | L11: 96 | M11: 94 | N11: 73 | O11: 95 | P11: 98 | Q11: 101 | R11: 94 | S11: 110 | T11: 101 | U11: 78 | V11: 73 | W11: 88 | X11: 98 | Y11: 82 | Z11: 88 | AA11: 81 | AB11: 78 | AC11: 76 | AD11: 88 | AE11: 78 | AF11: 79 | AG11: 76 | AH11: 91 | AI11: 55 | AJ11: 73 | AK11: 87 | AL11: 85
A12: 8 | B12: 浴袍 | E12: 3 | F12: =SUMIF($H$4:$BQ$4,$F$4,$H12:$BQ12) -> 926 | G12: =+E12*F12 -> 2778 | H12: 28 | I12: 25 | J12: 27 | K12: 24 | L12: 30 | M12: 34 | N12: 28 | O12: 29 | P12: 28 | Q12: 22 | R12: 27 | S12: 25 | T12: 43 | U12: 27 | V12: 22 | W12: 23 | X12: 44 | Y12: 48 | Z12: 39 | AA12: 37 | AB12: 45 | AC12: 25 | AD12: 19 | AE12: 27 | AF12: 31 | AG12: 35 | AH12: 34 | AI12: 23 | AJ12: 28 | AK12: 26 | AL12: 23
A13: 9 | B13: 保护垫 | E13: 7.2 | F13: =SUMIF($H$4:$BQ$4,$F$4,$H13:$BQ13) -> 26 | G13: =+E13*F13 -> 187.2 | I13: 2 | J13: 1 | K13: 1 | L13: 2 | M13: 3 | N13: 2 | P13: 2 | Q13: 1 | U13: 2 | W13: 2 | Z13: 1 | AA13: 1 | AB13: 2 | AD13: 2 | AF13: 1 | AG13: 1
A14: 10 | B14: 被芯 | E14: 9 | F14: =SUMIF($H$4:$BQ$4,$F$4,$H14:$BQ14) -> 4 | G14: =+E14*F14 -> 36 | AB14: 4
A15: 11 | B15: 枕芯 | E15: 2.7 | F15: =SUMIF($H$4:$BQ$4,$F$4,$H15:$BQ15) -> 0 | G15: =+E15*F15 -> 0
A16: 12 | B16: 重污处理 | E16: 10 | F16: =SUMIF($H$4:$BQ$4,$F$4,$H16:$BQ16) -> 8 | G16: =+E16*F16 -> 80 | I16: 1 | M16: 2 | N16: 1 | U16: 1 | AB16: 2 | AF16: 1
A17: 13 | F17: =SUMIF($H$4:$BQ$4,$F$4,$H17:$BQ17) -> 0 | G17: =+E17*F17 -> 0
A18: 14 | F18: =SUMIF($H$4:$BQ$4,$F$4,$H18:$BQ18) -> 0 | G18: =+E18*F18 -> 0
A19: 15 | F19: =SUMIF($H$4:$BQ$4,$F$4,$H19:$BQ19) -> 0 | G19: =+E19*F19 -> 0
A20: 16 | F20: =SUMIF($H$4:$BQ$4,$F$4,$H20:$BQ20) -> 0 | G20: =+E20*F20 -> 0
A21: 17 | F21: =SUMIF($H$4:$BQ$4,$F$4,$H21:$BQ21) -> 0 | G21: =+E21*F21 -> 0
A22: 18 | F22: =SUMIF($H$4:$BQ$4,$F$4,$H22:$BQ22) -> 0 | G22: =+E22*F22 -> 0
A23: 19 | F23: =SUMIF($H$4:$BQ$4,$F$4,$H23:$BQ23) -> 0 | G23: =+E23*F23 -> 0
A24: 20 | F24: =SUMIF($H$4:$BQ$4,$F$4,$H24:$BQ24) -> 0 | G24: =+E24*F24 -> 0
A25: 21 | F25: =SUMIF($H$4:$BQ$4,$F$4,$H25:$BQ25) -> 0 | G25: =+E25*F25 -> 0
A26: 22 | F26: =SUMIF($H$4:$I$4,$F$4,$H26:$I26) -> 0 | G26: =+E26*F26 -> 0
A27: 23 | F27: =SUMIF($H$4:$I$4,$F$4,$H27:$I27) -> 0 | G27: =+E27*F27 -> 0
A28: 24 | F28: =SUMIF($H$4:$I$4,$F$4,$H28:$I28) -> 0 | G28: =+E28*F28 -> 0
A29: 25 | F29: =SUMIF($H$4:$I$4,$F$4,$H29:$I29) -> 0 | G29: =+E29*F29 -> 0
A30: 26 | F30: =SUMIF($H$4:$I$4,$F$4,$H30:$I30) -> 0 | G30: =+E30*F30 -> 0
A31: 27 | F31: =SUMIF($H$4:$I$4,$F$4,$H31:$I31) -> 0 | G31: =+E31*F31 -> 0
A32: 28 | F32: =SUMIF($H$4:$I$4,$F$4,$H32:$I32) -> 0 | G32: =+E32*F32 -> 0
A33: 29 | F33: =SUMIF($H$4:$I$4,$F$4,$H33:$I33) -> 0 | G33: =+E33*F33 -> 0
A34: 30 | F34: =SUMIF($H$4:$I$4,$F$4,$H34:$I34) -> 0 | G34: =+E34*F34 -> 0
A35: 31 | F35: =SUMIF($H$4:$I$4,$F$4,$H35:$I35) -> 0 | G35: =+E35*F35 -> 0
A36: 32 | F36: =SUMIF($H$4:$I$4,$F$4,$H36:$I36) -> 0 | G36: =+E36*F36 -> 0
A37: 33 | F37: =SUMIF($H$4:$I$4,$F$4,$H37:$I37) -> 0 | G37: =+E37*F37 -> 0
... A44: 40 | F44: =SUMIF($H$4:$I$4,$F$4,$H44:$I44) -> 0 | G44: =+E44*F44 -> 0
B45: 洗涤费 | F45: =SUM(F5:F44) -> 33251 | G45: =SUM(G5:G44) -> 31120.9 | H45: =SUM(H5:H44) -> 1061 | I45: =SUM(I5:I44) -> 763 | J45: =SUM(J5:J44) -> 849 | K45: =SUM(K5:K44) -> 920 | L45: =SUM(L5:L44) -> 1192 | M45: =SUM(M5:M44) -> 1240 | ... AL45: =SUM(AL5:AL44) -> 1062

Sheet 客房工资录入
A1: 姓名 | B1: 部门 | C1: 岗位 | D1: 是否转正 | E1: 薪等 | F1: 薪级 | G1: 总工资 | H1: 基本工资 | I1: 岗位工资 | J1: 绩效工资 | K1: 出勤天数 | L1: 1号工作时长 | M1: 2号工作时长 | N1: 3号工作时长 | O1: 4号工作时长 | P1: 5号工作时长 | Q1: 6号工作时长 | R1: 7号工作时长 | S1: 8号工作时长 | T1: 9号工作时长 | U1: 10号工作时长 | V1: 11号工作时长 | W1: 12号工作时长 | X1: 13号工作时长 | Y1: 14号工作时长 | Z1: 15号工作时长 | AA1: 16号工作时长 | AB1: 17号工作时长 | AC1: 18号工作时长 | AD1: 19号工作时长 | AE1: 20号工作时长 | AF1: 21号工作时长 | AG1: 22号工作时长 | AH1: 23号工作时长 | AI1: 24号工作时长 | AJ1: 25号工作时长 | AK1: 26号工作时长 | AL1: 27号工作时长 | AM1: 28号工作时长 | AN1: 29号工作时长 | AO1: 30号工作时长 | AP1: 31号工作时长
A2: 韩愈 | B2: 客房 | C2: 经理 | D2: 是 | G2: 5500 | H2: 4950 | J2: 550 | K2: 25 | L2: 0 | M2: 8 | N2: 8 | O2: 8 | P2: 0 | Q2: 0 | R2: 0 | S2: 0 | T2: 8 | U2: 8 | V2: 8 | W2: 8 | X2: 8 | Y2: 8 | Z2: 8 | AA2: 8 | AB2: 8 | AC2: 8 | AD2: 8 | AE2: 8 | AF2: 8 | AG2: 8 | AH2: 8 | AI2: 8 | AJ2: 8 | AK2: 8 | AL2: 8 | AM2: 8 | AN2: 8 | AO2: 8 | AP2: 8
A3: 张凯娜 | B3: 客房 | C3: 领班 | D3: 是 | G3: 4000 | H3: 4600 | J3: 400 | K3: 25 | L3: 8 | M3: 8 | N3: 0 | O3: 8 | P3: 9 | Q3: 8 | R3: 8 | S3: 8 | T3: 0 | U3: 8 | V3: 8 | W3: 8 | X3: 8 | Y3: 8 | Z3: 0 | AA3: 8 | AB3: 8 | AC3: 8 | AD3: 8 | AE3: 8 | AF3: 8 | AG3: 8 | AH3: 8 | AI3: 8 | AJ3: 8 | AK3: 8 | AL3: 8 | AM3: 8 | AN3: 8 | AO3: 8 | AP3: 8
A4: 初立玲 | B4: 客房 | C4: 客房服务员 | D4: 是 | G4: 3200 | H4: 2200 | I4: 1000 | K4: 25 | L4: 8 | M4: 0 | N4: 8 | O4: 8 | P4: 8 | Q4: 8 | R4: 8 | S4: 8 | T4: 8 | U4: 8 | V4: 0 | W4: 0 | X4: 0 | Y4: 0 | Z4: 8 | AA4: 8 | AB4: 8 | AC4: 8 | AD4: 0 | AE4: 8 | AF4: 8 | AG4: 8 | AH4: 8 | AI4: 8 | AJ4: 8 | AK4: 8 | AL4: 0 | AM4: 0 | AN4: 8 | AO4: 8 | AP4: 8
A5: 张淑萍 | B5: 客房 | C5: 客房服务员 | D5: 是 | G5: 3200 | H5: 2200 | I5: 1000 | K5: 25 | L5: 8 | M5: 8 | N5: 8 | O5: 10.5 | P5: 7.5 | Q5: 8 | R5: 8 | S5: 8 | T5: 8 | U5: 8 | V5: 8 | W5: 8.5 | X5: 0 | Y5: 8 | Z5: 8 | AA5: 8 | AB5: 8 | AC5: 8 | AD5: 8 | AE5: 8 | AF5: 0 | AG5: 8 | AH5: 8 | AI5: 8 | AJ5: 8 | AK5: 13 | AL5: 8 | AM5: 13.5 | AN5: 8 | AO5: 8 | AP5: 8
A6: 姜洪英 | B6: 客房 | C6: 客房服务员 | D6: 是 | G6: 3200 | H6: 2200 | I6: 1000 | K6: 25 | L6: 0 | M6: 8 | N6: 8 | O6: 8 | P6: 8 | Q6: 8 | R6: 8 | S6: 16 | T6: 0 | U6: 8 | V6: 8 | W6: 8 | X6: 8 | Y6: 8 | Z6: 8 | AA6: 9.5 | AB6: 0 | AC6: 8 | AD6: 8 | AE6: 8 | AF6: 8 | AG6: 8 | AH6: 8 | AI6: 9 | AJ6: 0 | AK6: 8 | AL6: 8 | AM6: 8 | AN6: 8 | AO6: 11.5 | AP6: 9.5
A7: 姜敏 | B7: 客房 | C7: 客房服务员 | D7: 是 | G7: 3200 | H7: 2200 | I7: 1000 | K7: 25 | L7: 8 | M7: 0 | N7: 8 | O7: 8 | P7: 8 | Q7: 8 | R7: 8 | S7: 0 | T7: 8 | U7: 0 | V7: 8 | W7: 8 | X7: 8 | Y7: 8 | Z7: 8 | AA7: 8 | AB7: 9 | AC7: 8 | AD7: 8 | AE7: 8 | AF7: 8 | AG7: 8 | AH7: 0 | AI7: 0 | AJ7: 8 | AK7: 8 | AL7: 8 | AM7: 8 | AN7: 8 | AO7: 8 | AP7: 8
A8: 石见见 | B8: 客房 | C8: 客房服务员 | D8: 是 | G8: 3200 | H8: 2200 | I8: 1000 | K8: 25 | L8: 8 | M8: 0 | N8: 8 | O8: 0 | P8: 0 | Q8: 8 | R8: 8 | S8: 8 | T8: 8 | U8: 8 | V8: 9 | W8: 8 | X8: 8 | Y8: 8 | Z8: 8 | AA8: 8 | AB8: 8 | AC8: 8 | AD8: 8 | AE8: 0 | AF8: 8 | AG8: 8 | AH8: 8 | AI8: 8 | AJ8: 8 | AK8: 8 | AL8: 8 | AM8: 0 | AN8: 8 | AO8: 8 | AP8: 8
A9: 王小宁 | B9: 客房 | C9: 客房服务员 | D9: 是 | G9: 3200 | H9: 2200 | I9: 1000 | K9: 25 | L9: 8 | M9: 8 | N9: 0 | O9: 8 | P9: 8 | Q9: 0 | R9: 8 | S9: 8 | T9: 8 | U9: 8 | V9: 8 | W9: 8 | X9: 8 | Y9: 0 | Z9: 8 | AA9: 8 | AB9: 8 | AC9: 8 | AD9: 8 | AE9: 8 | AF9: 8 | AG9: 0 | AH9: 0 | AI9: 0 | AJ9: 0 | AK9: 8 | AL9: 0 | AM9: 0 | AN9: 0 | AO9: 0 | AP9: 0
A10: 丁春艳 | B10: 客房 | C10: 客房服务员 | D10: 是 | G10: 3200 | H10: 2200 | I10: 1000 | K10: 25 | L10: 0 | M10: 8 | N10: 8 | O10: 8 | P10: 8 | Q10: 8 | R10: 10 | S10: 8 | T10: 8 | U10: 8 | V10: 8 | W10: 8 | X10: 8 | Y10: 8 | Z10: 8 | AA10: 0 | AB10: 8 | AC10: 8 | AD10: 8 | AE10: 8 | AF10: 8 | AG10: 8 | AH10: 10 | AI10: 0 | AJ10: 8 | AK10: 8 | AL10: 8 | AM10: 8 | AN10: 8 | AO10: 8.5 | AP10: 8
A11: 于凤春 | B11: 客房 | C11: PA | D11: 是 | G11: 3800 | H11: 3800 | K11: 25 | L11: 8 | M11: 8 | N11: 8 | O11: 8 | P11: 8 | Q11: 8 | R11: 0 | S11: 8 | T11: 0 | U11: 8 | V11: 8 | W11: 8 | X11: 8 | Y11: 0 | Z11: 8 | AA11: 8 | AB11: 8 | AC11: 8 | AD11: 8 | AE11: 8 | AF11: 8 | AG11: 8 | AH11: 8 | AI11: 8 | AJ11: 8 | AK11: 8 | AL11: 8 | AM11: 0 | AN11: 8 | AO11: 8
A12: 沈庆玲 | B12: 客房 | C12: 客房服务员 | G12: 3200 | H12: 2200 | I12: 1000 | K12: 25 | L12: 8 | M12: 8 | N12: 8 | O12: 8 | P12: 13 | Q12: 8 | R12: 0 | S12: 8 | T12: 8 | U12: 8 | V12: 8 | W12: 8 | X12: 8 | Y12: 8 | Z12: 0 | AA12: 8 | AB12: 8 | AC12: 8 | AD12: 8 | AE12: 8 | AF12: 8 | AG12: 8 | AH12: 0 | AI12: 8 | AJ12: 8 | AK12: 8 | AL12: 8 | AM12: 8 | AN12: 8 | AO12: 0 | AP12: 8
A13: 曹薇 | B13: 客房 | C13: 客房服务员 | D13: 是 | G13: 3200 | H13: 2200 | I13: 1000 | K13: 25 | L13: 0 | M13: 8 | N13: 8 | O13: 8 | P13: 8 | Q13: 0 | R13: 0 | S13: 0 | T13: 8 | U13: 8 | V13: 8 | W13: 8 | X13: 8 | Y13: 8 | Z13: 8 | AA13: 8 | AB13: 8 | AC13: 8 | AD13: 8 | AE13: 8 | AF13: 8 | AG13: 8 | AH13: 8 | AI13: 8 | AJ13: 8 | AK13: 8 | AL13: 8 | AM13: 8 | AN13: 8 | AO13: 8 | AP13: 8
A15: 合计 | L15: =SUM(L2:L14) -> 64 | M15: =SUM(M2:M14) -> 72 | N15: =SUM(N2:N14) -> 80 | O15: =SUM(O2:O14) -> 90.5 | P15: =SUM(P2:P14) -> 85.5 | Q15: =SUM(Q2:Q14) -> 72 | R15: =SUM(R2:R14) -> 66 | S15: =SUM(S2:S14) -> 80 | ... AP15: =SUM(AP2:AP14) -> 81.5

Sheet 餐厅成本录入
B1: 餐厅物品出入库明细
B2: 酒店名称： | N2: 周期：
A3: 序号 | B3: 货品名称 | C3: 规格型号 | D3: 单位 | E3: 单价 | F3: 结存合计 | G3: 结存金额 | H3: 入库合计 | I3: 入库金额 | J3: 出库合计 | K3: 出库金额 | L3: 结存合计 | M3: 结存金额 | N3: 1号 | P3: 2号 | R3: 3号 | T3: 4号 | V3: 5号 | X3: 6号 | Z3: 7号 | AB3: 8号 | AD3: 9号 | AF3: 10号 | AH3: 11号 | AJ3: 12号 | AL3: 13号 | AN3: 14号 | AP3: 15号 | AR3: 16号 | AT3: 17号 | AV3: 18号 | AX3: 19号 | AZ3: 20号 | BB3: 21号 | BD3: 22号 | BF3: 23号 | BH3: 24号 | BJ3: 25号 | BL3: 26号 | BN3: 27号 | BP3: 28号 | BR3: 29号 | BT3: 30号 | BV3: 31号
F4: 结存 | H4: 入库 | I4: 金额 | J4: 出库 | L4: 结存 | N4: 入库 | O4: 出库 | P4: 入库 | Q4: 出库 | R4: 入库 | S4: 出库 | T4: 入库 | U4: 出库 | V4: 入库 | W4: 出库 | X4: 入库 | Y4: 出库 | Z4: 入库 | AA4: 出库 | AB4: 入库 | AC4: 出库 | AD4: 入库 | AE4: 出库 | AF4: 入库 | AG4: 出库 | AH4: 入库 | AI4: 出库 | AJ4: 入库 | AK4: 出库 | AL4: 入库 | AM4: 出库 | AN4: 入库 | AO4: 出库 | AP4: 入库 | AQ4: 出库 | AR4: 入库 | AS4: 出库 | AT4: 入库 | AU4: 出库 | AV4: 入库 | AW4: 出库 | AX4: 入库 | AY4: 出库 | AZ4: 入库 | BA4: 出库 | BB4: 入库 | BC4: 出库 | BD4: 入库 | BE4: 出库 | BF4: 入库 | BG4: 出库 | BH4: 入库 | BI4: 出库 | BJ4: 入库 | BK4: 出库 | BL4: 入库 | BM4: 出库 | BN4: 入库 | BO4: 出库 | BP4: 入库 | BQ4: 出库 | BR4: 入库 | BS4: 出库 | BT4: 入库 | BU4: 出库 | BV4: 入库 | BW4: 出库
A5: 1 | B5: 刺黄瓜 | D5: 斤 | E5: 1.8 | G5: =+E5*F5 -> 0 | H5: =SUMIF($N$4:$BW$4,$H$4,$N5:$BW5) -> 71.4 | I5: =+E5*H5 -> 128.52 | J5: =SUMIF($N$4:$BW$4,$J$4,$N5:$BW5) -> 71.4 | K5: =+E5*J5 -> 128.52 | L5: =+F5+H5-J5 -> 0 | M5: =+E5*L5 -> 0 | P5: 10 | Q5: 10 | V5: 9.9 | W5: 9.9 | AH5: 10 | AI5: 10 | AP5: 20 | AQ5: 20 | AT5: 10.7 | AU5: 10.7 | AX5: 10.8 | AY5: 10.8
A6: 2 | B6: 西红柿 | E6: 3.8 | G6: =+E6*F6 -> 0 | H6: =SUMIF($N$4:$BW$4,$H$4,$N6:$BW6) -> 49.7 | I6: =+E6*H6 -> 188.86 | J6: =SUMIF($N$4:$BW$4,$J$4,$N6:$BW6) -> 49.7 | K6: =+E6*J6 -> 188.86 | L6: =+F6+H6-J6 -> 0 | M6: =+E6*L6 -> 0 | P6: 6 | Q6: 6 | V6: 6 | W6: 6 | AB6: 6 | AC6: 6 | AH6: 6.2 | AI6: 6.2 | AL6: 6.2 | AM6: 6.2 | AP6: 6.2 | AQ6: 6.2 | AT6: 6.8 | AU6: 6.8 | BB6: 6.3 | BC6: 6.3
A7: 3 | B7: 大头菜 | E7: 1 | G7: =+E7*F7 -> 0 | H7: =SUMIF($N$4:$BW$4,$H$4,$N7:$BW7) -> 50.3 | I7: =+E7*H7 -> 50.3 | J7: =SUMIF($N$4:$BW$4,$J$4,$N7:$BW7) -> 50.3 | K7: =+E7*J7 -> 50.3 | L7: =+F7+H7-J7 -> 0 | M7: =+E7*L7 -> 0 | P7: 15.1 | Q7: 15.1 | AB7: 18.5 | AC7: 18.5 | AP7: 16.7 | AQ7: 16.7
A8: 4 | B8: 有机花菜 | E8: 2.5 | G8: =+E8*F8 -> 0 | H8: =SUMIF($N$4:$BW$4,$H$4,$N8:$BW8) -> 40.2 | I8: =+E8*H8 -> 100.5 | J8: =SUMIF($N$4:$BW$4,$J$4,$N8:$BW8) -> 40.2 | K8: =+E8*J8 -> 100.5 | L8: =+F8+H8-J8 -> 0 | M8: =+E8*L8 -> 0 | V8: 6.5 | W8: 6.5 | AB8: 7 | AC8: 7 | BB8: 6.7 | BC8: 6.7 | BH8: 6 | BI8: 6 | BN8: 14 | BO8: 14
A9: 5 | B9: 西兰花 | E9: 3.8 | G9: =+E9*F9 -> 0 | H9: =SUMIF($N$4:$BW$4,$H$4,$N9:$BW9) -> 38.2 | I9: =+E9*H9 -> 145.16 | J9: =SUMIF($N$4:$BW$4,$J$4,$N9:$BW9) -> 38.2 | K9: =+E9*J9 -> 145.16 | L9: =+F9+H9-J9 -> 0 | M9: =+E9*L9 -> 0 | V9: 6.4 | W9: 6.4 | AB9: 6.2 | AC9: 6.2 | AP9: 6.4 | AQ9: 6.4 | AT9: 6.8 | AU9: 6.8 | BB9: 6.4 | BC9: 6.4 | BH9: 6 | BI9: 6
A10: 6 | B10: 大土豆 | E10: 1.5 | G10: =+E10*F10 -> 0 | H10: =SUMIF($N$4:$BW$4,$H$4,$N10:$BW10) -> 81.1 | I10: =+E10*H10 -> 121.65 | J10: =SUMIF($N$4:$BW$4,$J$4,$N10:$BW10) -> 81.1 | K10: =+E10*J10 -> 121.65 | L10: =+F10+H10-J10 -> 0 | M10: =+E10*L10 -> 0 | P10: 10 | Q10: 10 | V10: 9.9 | W10: 9.9 | AB10: 10 | AC10: 10 | AH10: 10.1 | AI10: 10.1 | AL10: 10.2 | AM10: 10.2 | AP10: 10.3 | AQ10: 10.3 | AT10: 10.6 | AU10: 10.6 | BH10: 10 | BI10: 10
A11: 7 | B11: 地瓜 | E11: 3 | G11: =+E11*F11 -> 0 | H11: =SUMIF($N$4:$BW$4,$H$4,$N11:$BW11) -> 102.1 | I11: =+E11*H11 -> 306.3 | J11: =SUMIF($N$4:$BW$4,$J$4,$N11:$BW11) -> 102.1 | K11: =+E11*J11 -> 306.3 | L11: =+F11+H11-J11 -> 0 | M11: =+E11*L11 -> 0 | P11: 10 | Q11: 10 | V11: 10 | W11: 10 | AB11: 10 | AC11: 10 | AH11: 10 | AI11: 10 | AL11: 10.3 | AM11: 10.3 | AP11: 10.1 | AQ11: 10.1 | AT11: 21 | AU11: 21 | BB11: 10.7 | BC11: 10.7 | BN11: 10 | BO11: 10
A12: 8 | B12: 山药肉 | E12: 8.5 | G12: =+E12*F12 -> 0 | H12: =SUMIF($N$4:$BW$4,$H$4,$N12:$BW12) -> 31.7 | I12: =+E12*H12 -> 269.45 | J12: =SUMIF($N$4:$BW$4,$J$4,$N12:$BW12) -> 31.7 | K12: =+E12*J12 -> 269.45 | L12: =+F12+H12-J12 -> 0 | M12: =+E12*L12 -> 0 | P12: 5.2 | Q12: 5.2 | AB12: 5.4 | AC12: 5.4 | AP12: 5.3 | AQ12: 5.3 | BB12: 5.1 | BC12: 5.1 | BH12: 2 | BI12: 2 | BN12: 8.7 | BO12: 8.7
A13: 9 | B13: 莴笋肉 | E13: 4.5 | G13: =+E13*F13 -> 0 | H13: =SUMIF($N$4:$BW$4,$H$4,$N13:$BW13) -> 35.8 | I13: =+E13*H13 -> 161.1 | J13: =SUMIF($N$4:$BW$4,$J$4,$N13:$BW13) -> 35.8 | K13: =+E13*J13 -> 161.1 | L13: =+F13+H13-J13 -> 0 | M13: =+E13*L13 -> 0 | P13: 8 | Q13: 8 | AB13: 8.2 | AC13: 8.2 | AP13: 7.6 | AQ13: 7.6 | BH13: 2 | BI13: 2 | BN13: 10 | BO13: 10
A14: 10 | B14: 贝贝南瓜 | E14: 2.8 | G14: =+E14*F14 -> 0 | H14: =SUMIF($N$4:$BW$4,$H$4,$N14:$BW14) -> 48 | I14: =+E14*H14 -> 134.4 | J14: =SUMIF($N$4:$BW$4,$J$4,$N14:$BW14) -> 48 | K14: =+E14*J14 -> 134.4 | L14: =+F14+H14-J14 -> 0 | M14: =+E14*L14 -> 0 | P14: 9.9 | Q14: 9.9 | AH14: 8.5 | AI14: 8.5 | AP14: 10.2 | AQ14: 10.2 | AT14: 8.4 | AU14: 8.4 | BB14: 11 | BC14: 11
A15: 11 | B15: 油麦菜 | E15: 3.5 | G15: =+E15*F15 -> 0 | H15: =SUMIF($N$4:$BW$4,$H$4,$N15:$BW15) -> 21.9 | I15: =+E15*H15 -> 76.65 | J15: =SUMIF($N$4:$BW$4,$J$4,$N15:$BW15) -> 21.9 | K15: =+E15*J15 -> 76.65 | L15: =+F15+H15-J15 -> 0 | M15: =+E15*L15 -> 0 | AH15: 3 | AI15: 3 | AP15: 6.2 | AQ15: 6.2 | BH15: 6 | BI15: 6 | BN15: 6.7 | BO15: 6.7
A16: 12 | B16: 油菜 | E16: 1.5 | G16: =+E16*F16 -> 0 | H16: =SUMIF($N$4:$BW$4,$H$4,$N16:$BW16) -> 30.7 | I16: =+E16*H16 -> 46.05 | J16: =SUMIF($N$4:$BW$4,$J$4,$N16:$BW16) -> 30.7 | K16: =+E16*J16 -> 46.05 | L16: =+F16+H16-J16 -> 0 | M16: =+E16*L16 -> 0 | P16: 6 | Q16: 6 | AL16: 6.1 | AM16: 6.1 | AP16: 6.1 | AQ16: 6.1 | BB16: 6.5 | BC16: 6.5 | BH16: 6 | BI16: 6
A17: 13 | B17: 白菜 | E17: 1 | G17: =+E17*F17 -> 0 | H17: =SUMIF($N$4:$BW$4,$H$4,$N17:$BW17) -> 0 | I17: =+E17*H17 -> 0 | J17: =SUMIF($N$4:$BW$4,$J$4,$N17:$BW17) -> 0 | K17: =+E17*J17 -> 0 | L17: =+F17+H17-J17 -> 0 | M17: =+E17*L17 -> 0
A18: 14 | B18: 小白菜 | E18: 1 | G18: =+E18*F18 -> 0 | H18: =SUMIF($N$4:$BW$4,$H$4,$N18:$BW18) -> 25.4 | I18: =+E18*H18 -> 25.4 | J18: =SUMIF($N$4:$BW$4,$J$4,$N18:$BW18) -> 25.4 | K18: =+E18*J18 -> 25.4 | L18: =+F18+H18-J18 -> 0 | M18: =+E18*L18 -> 0 | AL18: 6 | AM18: 6 | AP18: 6.1 | AQ18: 6.1 | BB18: 7.3 | BC18: 7.3 | BN18: 6 | BO18: 6
A19: 15 | B19: 娃娃菜 | E19: 4 | G19: =+E19*F19 -> 0 | H19: =SUMIF($N$4:$BW$4,$H$4,$N19:$BW19) -> 48.8 | I19: =+E19*H19 -> 195.2 | J19: =SUMIF($N$4:$BW$4,$J$4,$N19:$BW19) -> 48.8 | K19: =+E19*J19 -> 195.2 | L19: =+F19+H19-J19 -> 0 | M19: =+E19*L19 -> 0 | P19: 6 | Q19: 6 | V19: 6 | W19: 6 | AB19: 6 | AC19: 6 | AH19: 6 | AI19: 6 | AL19: 6 | AM19: 6 | AP19: 6 | AQ19: 6 | BB19: 6 | BC19: 6 | BN19: 6.8 | BO19: 6.8
A20: 16 | B20: 菜心 | E20: 4 | G20: =+E20*F20 -> 0 | H20: =SUMIF($N$4:$BW$4,$H$4,$N20:$BW20) -> 30 | I20: =+E20*H20 -> 120 | J20: =SUMIF($N$4:$BW$4,$J$4,$N20:$BW20) -> 30 | K20: =+E20*J20 -> 120 | L20: =+F20+H20-J20 -> 0 | M20: =+E20*L20 -> 0 | P20: 6 | Q20: 6 | AB20: 6 | AC20: 6 | AH20: 6 | AI20: 6 | AL20: 6 | AM20: 6 | AP20: 6 | AQ20: 6
A21: 17 | B21: 紫生菜 | E21: 5 | G21: =+E21*F21 -> 0 | H21: =SUMIF($N$4:$BW$4,$H$4,$N21:$BW21) -> 27.1 | I21: =+E21*H21 -> 135.5 | J21: =SUMIF($N$4:$BW$4,$J$4,$N21:$BW21) -> 27.1 | K21: =+E21*J21 -> 135.5 | L21: =+F21+H21-J21 -> 0 | M21: =+E21*L21 -> 0 | P21: 3.3 | Q21: 3.3 | V21: 10.3 | W21: 10.3 | AH21: 6.3 | AI21: 6.3 | AP21: 3.2 | AQ21: 3.2 | BH21: 2 | BI21: 2 | BN21: 2 | BO21: 2
A22: 18 | B22: 苦菊 | E22: 4 | G22: =+E22*F22 -> 0 | H22: =SUMIF($N$4:$BW$4,$H$4,$N22:$BW22) -> 3.1 | I22: =+E22*H22 -> 12.4 | J22: =SUMIF($N$4:$BW$4,$J$4,$N22:$BW22) -> 3.1 | K22: =+E22*J22 -> 12.4 | L22: =+F22+H22-J22 -> 0 | M22: =+E22*L22 -> 0 | AH22: 3.1 | AI22: 3.1
A23: 19 | B23: 香菜 | E23: 3.5 | G23: =+E23*F23 -> 0 | H23: =SUMIF($N$4:$BW$4,$H$4,$N23:$BW23) -> 11.8 | I23: =+E23*H23 -> 41.3 | J23: =SUMIF($N$4:$BW$4,$J$4,$N23:$BW23) -> 11.8 | K23: =+E23*J23 -> 41.3 | L23: =+F23+H23-J23 -> 0 | M23: =+E23*L23 -> 0 | P23: 3 | Q23: 3 | AB23: 3 | AC23: 3 | AP23: 3.2 | AQ23: 3.2 | BB23: 2.6 | BC23: 2.6
A24: 20 | B24: 香葱 | E24: 6 | G24: =+E24*F24 -> 0 | H24: =SUMIF($N$4:$BW$4,$H$4,$N24:$BW24) -> 12.1 | I24: =+E24*H24 -> 72.6 | J24: =SUMIF($N$4:$BW$4,$J$4,$N24:$BW24) -> 12.1 | K24: =+E24*J24 -> 72.6 | L24: =+F24+H24-J24 -> 0 | M24: =+E24*L24 -> 0 | P24: 3 | Q24: 3 | AB24: 3 | AC24: 3 | AL24: 3.1 | AM24: 3.1 | AP24: 3 | AQ24: 3
A25: 21 | B25: 大葱 | E25: 1 | G25: =+E25*F25 -> 0 | H25: =SUMIF($N$4:$BW$4,$H$4,$N25:$BW25) -> 47.1 | I25: =+E25*H25 -> 47.1 | J25: =SUMIF($N$4:$BW$4,$J$4,$N25:$BW25) -> 47.1 | K25: =+E25*J25 -> 47.1 | L25: =+F25+H25-J25 -> 0 | M25: =+E25*L25 -> 0 | AH25: 31.6 | AI25: 31.6 | BB25: 5.5 | BC25: 5.5 | BF25: 10 | BG25: 10
A26: 22 | B26: 胡萝卜 | E26: 1.8 | G26: =+E26*F26 -> 0 | H26: =SUMIF($N$4:$BW$4,$H$4,$N26:$BW26) -> 33.4 | I26: =+E26*H26 -> 60.12 | J26: =SUMIF($N$4:$BW$4,$J$4,$N26:$BW26) -> 33.4 | K26: =+E26*J26 -> 60.12 | L26: =+F26+H26-J26 -> 0 | M26: =+E26*L26 -> 0 | P26: 6 | Q26: 6 | V26: 6 | W26: 6 | AB26: 6.1 | AC26: 6.1 | AH26: 3.2 | AI26: 3.2 | AL26: 3.1 | AM26: 3.1 | AP26: 3 | AQ26: 3 | BF26: 6 | BG26: 6
A27: 23 | B27: 菜豆 | E27: 6.1 | G27: =+E27*F27 -> 0 | H27: =SUMIF($N$4:$BW$4,$H$4,$N27:$BW27) -> 24.8 | I27: =+E27*H27 -> 151.28 | J27: =SUMIF($N$4:$BW$4,$J$4,$N27:$BW27) -> 24.8 | K27: =+E27*J27 -> 151.28 | L27: =+F27+H27-J27 -> 0 | M27: =+E27*L27 -> 0 | AB27: 6.1 | AC27: 6.1 | AP27: 6.2 | AQ27: 6.2 | BB27: 6.5 | BC27: 6.5 | BF27: 6 | BG27: 6
A28: 24 | B28: 芸豆 | E28: 3.5 | G28: =+E28*F28 -> 0 | H28: =SUMIF($N$4:$BW$4,$H$4,$N28:$BW28) -> 18 | I28: =+E28*H28 -> 63 | J28: =SUMIF($N$4:$BW$4,$J$4,$N28:$BW28) -> 18 | K28: =+E28*J28 -> 63 | L28: =+F28+H28-J28 -> 0 | M28: =+E28*L28 -> 0 | P28: 6 | Q28: 6 | AH28: 6 | AI28: 6 | AL28: 6 | AM28: 6
A29: 25 | B29: 大蒜肉 | E29: 5 | G29: =+E29*F29 -> 0 | H29: =SUMIF($N$4:$BW$4,$H$4,$N29:$BW29) -> 18 | I29: =+E29*H29 -> 90 | J29: =SUMIF($N$4:$BW$4,$J$4,$N29:$BW29) -> 18 | K29: =+E29*J29 -> 90 | L29: =+F29+H29-J29 -> 0 | M29: =+E29*L29 -> 0 | V29: 6 | W29: 6 | AL29: 6 | AM29: 6 | BF29: 6 | BG29: 6
A30: 26 | B30: 苦瓜 | E30: 4 | G30: =+E30*F30 -> 0 | H30: =SUMIF($N$4:$BW$4,$H$4,$N30:$BW30) -> 0 | I30: =+E30*H30 -> 0 | J30: =SUMIF($N$4:$BW$4,$J$4,$N30:$BW30) -> 0 | K30: =+E30*J30 -> 0 | L30: =+F30+H30-J30 -> 0 | M30: =+E30*L30 -> 0
A31: 27 | B31: 茄子 | E31: 2.8 | G31: =+E31*F31 -> 0 | H31: =SUMIF($N$4:$BW$4,$H$4,$N31:$BW31) -> 31.5 | I31: =+E31*H31 -> 88.2 | J31: =SUMIF($N$4:$BW$4,$J$4,$N31:$BW31) -> 31.5 | K31: =+E31*J31 -> 88.2 | L31: =+F31+H31-J31 -> 0 | M31: =+E31*L31 -> 0 | P31: 6 | Q31: 6 | AH31: 6.3 | AI31: 6.3 | AX31: 6.5 | AY31: 6.5 | BB31: 6.7 | BC31: 6.7 | BF31: 6 | BG31: 6
A32: 28 | B32: 香菇 | E32: 4.5 | G32: =+E32*F32 -> 0 | H32: =SUMIF($N$4:$BW$4,$H$4,$N32:$BW32) -> 21.2 | I32: =+E32*H32 -> 95.4 | J32: =SUMIF($N$4:$BW$4,$J$4,$N32:$BW32) -> 21.2 | K32: =+E32*J32 -> 95.4 | L32: =+F32+H32-J32 -> 0 | M32: =+E32*L32 -> 0 | P32: 3.1 | Q32: 3.1 | V32: 3 | W32: 3 | AB32: 3.1 | AC32: 3.1 | AL32: 3 | AM32: 3 | BF32: 3 | BG32: 3 | BL32: 6 | BM32: 6
A33: 29 | B33: 尖椒 | E33: 3.3 | G33: =+E33*F33 -> 0 | H33: =SUMIF($N$4:$BW$4,$H$4,$N33:$BW33) -> 15 | I33: =+E33*H33 -> 49.5 | J33: =SUMIF($N$4:$BW$4,$J$4,$N33:$BW33) -> 15 | K33: =+E33*J33 -> 49.5 | L33: =+F33+H33-J33 -> 0 | M33: =+E33*L33 -> 0 | AB33: 6 | AC33: 6 | BB33: 3 | BC33: 3 | BF33: 6 | BG33: 6
A34: 30 | B34: 韭菜 | G34: =+E34*F34 -> 0 | H34: =SUMIF($N$4:$BW$4,$H$4,$N34:$BW34) -> 12.1 | I34: =+E34*H34 -> 0 | J34: =SUMIF($N$4:$BW$4,$J$4,$N34:$BW34) -> 12.1 | K34: =+E34*J34 -> 0 | L34: =+F34+H34-J34 -> 0 | M34: =+E34*L34 -> 0 | AX34: 6.1 | AY34: 6.1 | BF34: 6 | BG34: 6
A35: 31 | B35: 蒜苔 | E35: 5.5 | G35: =+E35*F35 -> 0 | H35: =SUMIF($N$4:$BW$4,$H$4,$N35:$BW35) -> 43 | I35: =+E35*H35 -> 236.5 | J35: =SUMIF($N$4:$BW$4,$J$4,$N35:$BW35) -> 43 | K35: =+E35*J35 -> 236.5 | L35: =+F35+H35-J35 -> 0 | M35: =+E35*L35 -> 0 | P35: 6 | Q35: 6 | V35: 6 | W35: 6 | AB35: 6 | AC35: 6 | AH35: 6.2 | AI35: 6.2 | AL35: 6.2 | AM35: 6.2 | BB35: 6.6 | BC35: 6.6 | BF35: 6 | BG35: 6
A36: 32 | B36: 韭菜苔 | E36: 5 | G36: =+E36*F36 -> 0 | H36: =SUMIF($N$4:$BW$4,$H$4,$N36:$BW36) -> 27 | I36: =+E36*H36 -> 135 | J36: =SUMIF($N$4:$BW$4,$J$4,$N36:$BW36) -> 27 | K36: =+E36*J36 -> 135 | L36: =+F36+H36-J36 -> 0 | M36: =+E36*L36 -> 0 | AL36: 6 | AM36: 6 | AT36: 3 | AU36: 3 | AX36: 6 | AY36: 6 | BF36: 6 | BG36: 6 | BL36: 6 | BM36: 6
A37: 33 | B37: 田七 | E37: 3 | G37: =+E37*F37 -> 0 | H37: =SUMIF($N$4:$BW$4,$H$4,$N37:$BW37) -> 9.4 | I37: =+E37*H37 -> 28.2 | J37: =SUMIF($N$4:$BW$4,$J$4,$N37:$BW37) -> 9.4 | K37: =+E37*J37 -> 28.2 | L37: =+F37+H37-J37 -> 0 | M37: =+E37*L37 -> 0 | V37: 3 | W37: 3 | AT37: 2.4 | AU37: 2.4 | BF37: 2 | BG37: 2 | BL37: 2 | BM37: 2
A38: 34 | B38: 白萝卜 | G38: =+E38*F38 -> 0 | H38: =SUMIF($N$4:$BW$4,$H$4,$N38:$BW38) -> 16 | I38: =+E38*H38 -> 0 | J38: =SUMIF($N$4:$BW$4,$J$4,$N38:$BW38) -> 16 | K38: =+E38*J38 -> 0 | L38: =+F38+H38-J38 -> 0 | M38: =+E38*L38 -> 0 | AX38: 16 | AY38: 16
A39: 35 | B39: 青萝卜 | G39: =+E39*F39 -> 0 | H39: =SUMIF($N$4:$BW$4,$H$4,$N39:$BW39) -> 0 | I39: =+E39*H39 -> 0 | J39: =SUMIF($N$4:$BW$4,$J$4,$N39:$BW39) -> 0 | K39: =+E39*J39 -> 0 | L39: =+F39+H39-J39 -> 0 | M39: =+E39*L39 -> 0
A40: 36 | B40: 樱桃萝卜 | G40: =+E40*F40 -> 0 | H40: =SUMIF($N$4:$BW$4,$H$4,$N40:$BW40) -> 3.1 | I40: =+E40*H40 -> 0 | J40: =SUMIF($N$4:$BW$4,$J$4,$N40:$BW40) -> 3.1 | K40: =+E40*J40 -> 0 | L40: =+F40+H40-J40 -> 0 | M40: =+E40*L40 -> 0 | AH40: 3.1 | AI40: 3.1
A41: 37 | B41: 青杭椒 | E41: 8 | G41: =+E41*F41 -> 0 | H41: =SUMIF($N$4:$BW$4,$H$4,$N41:$BW41) -> 6.3 | I41: =+E41*H41 -> 50.4 | J41: =SUMIF($N$4:$BW$4,$J$4,$N41:$BW41) -> 6.3 | K41: =+E41*J41 -> 50.4 | L41: =+F41+H41-J41 -> 0 | M41: =+E41*L41 -> 0 | P41: 3.1 | Q41: 3.1 | AH41: 3.2 | AI41: 3.2
A42: 38 | B42: 紫甘蓝 | E42: 2 | G42: =+E42*F42 -> 0 | H42: =SUMIF($N$4:$BW$4,$H$4,$N42:$BW42) -> 15.5 | I42: =+E42*H42 -> 31 | J42: =SUMIF($N$4:$BW$4,$J$4,$N42:$BW42) -> 15.5 | K42: =+E42*J42 -> 31 | L42: =+F42+H42-J42 -> 0 | M42: =+E42*L42 -> 0 | V42: 5 | W42: 5 | AH42: 6.5 | AI42: 6.5 | BF42: 2 | BG42: 2 | BL42: 2 | BM42: 2
A43: 39 | B43: 马家沟芹菜 | E43: 8 | G43: =+E43*F43 -> 0 | H43: =SUMIF($N$4:$BW$4,$H$4,$N43:$BW43) -> 3 | I43: =+E43*H43 -> 24 | J43: =SUMIF($N$4:$BW$4,$J$4,$N43:$BW43) -> 3 | K43: =+E43*J43 -> 24 | L43: =+F43+H43-J43 -> 0 | M43: =+E43*L43 -> 0 | P43: 3 | Q43: 3
A44: 40 | B44: 洋葱 | E44: 1.2 | G44: =+E44*F44 -> 0 | H44: =SUMIF($N$4:$BW$4,$H$4,$N44:$BW44) -> 40.3 | I44: =+E44*H44 -> 48.36 | J44: =SUMIF($N$4:$BW$4,$J$4,$N44:$BW44) -> 40.3 | K44: =+E44*J44 -> 48.36 | L44: =+F44+H44-J44 -> 0 | M44: =+E44*L44 -> 0 | P44: 10.3 | Q44: 10.3 | AB44: 10 | AC44: 10 | BF44: 10 | BG44: 10 | BL44: 10 | BM44: 10
A45: 41 | B45: 芹菜 | G45: =+E45*F45 -> 0 | H45: =SUMIF($N$4:$BW$4,$H$4,$N45:$BW45) -> 0 | I45: =+E45*H45 -> 0 | J45: =SUMIF($N$4:$BW$4,$J$4,$N45:$BW45) -> 0 | K45: =+E45*J45 -> 0 | L45: =+F45+H45-J45 -> 0 | M45: =+E45*L45 -> 0
A46: 42 | B46: 西芹 | E46: 3 | G46: =+E46*F46 -> 0 | H46: =SUMIF($N$4:$BW$4,$H$4,$N46:$BW46) -> 6.3 | I46: =+E46*H46 -> 18.9 | J46: =SUMIF($N$4:$BW$4,$J$4,$N46:$BW46) -> 6.3 | K46: =+E46*J46 -> 18.9 | L46: =+F46+H46-J46 -> 0 | M46: =+E46*L46 -> 0 | AB46: 6.3 | AC46: 6.3
A47: 43 | B47: 角瓜 | E47: 1.5 | G47: =+E47*F47 -> 0 | H47: =SUMIF($N$4:$BW$4,$H$4,$N47:$BW47) -> 18.1 | I47: =+E47*H47 -> 27.15 | J47: =SUMIF($N$4:$BW$4,$J$4,$N47:$BW47) -> 18.1 | K47: =+E47*J47 -> 27.15 | L47: =+F47+H47-J47 -> 0 | M47: =+E47*L47 -> 0 | P47: 6.1 | Q47: 6.1 | AB47: 6 | AC47: 6 | BL47: 6 | BM47: 6
A48: 44 | B48: 蟹味菇 | E48: 15 | G48: =+E48*F48 -> 0 | H48: =SUMIF($N$4:$BW$4,$H$4,$N48:$BW48) -> 4 | I48: =+E48*H48 -> 60 | J48: =SUMIF($N$4:$BW$4,$J$4,$N48:$BW48) -> 4 | K48: =+E48*J48 -> 60 | L48: =+F48+H48-J48 -> 0 | M48: =+E48*L48 -> 0 | P48: 4 | Q48: 4
A49: 45 | B49: 球生菜 | E49: 3 | G49: =+E49*F49 -> 0 | H49: =SUMIF($N$4:$BW$4,$H$4,$N49:$BW49) -> 3 | I49: =+E49*H49 -> 9 | J49: =SUMIF($N$4:$BW$4,$J$4,$N49:$BW49) -> 3 | K49: =+E49*J49 -> 9 | L49: =+F49+H49-J49 -> 0 | M49: =+E49*L49 -> 0 | V49: 3 | W49: 3
A50: 46 | B50: 姜 | G50: =+E50*F50 -> 0 | H50: =SUMIF($N$4:$BW$4,$H$4,$N50:$BW50) -> 0 | I50: =+E50*H50 -> 0 | J50: =SUMIF($N$4:$BW$4,$J$4,$N50:$BW50) -> 0 | K50: =+E50*J50 -> 0 | L50: =+F50+H50-J50 -> 0 | M50: =+E50*L50 -> 0
A51: 47 | B51: 秋葵 | G51: =+E51*F51 -> 0 | H51: =SUMIF($N$4:$BW$4,$H$4,$N51:$BW51) -> 0 | I51: =+E51*H51 -> 0 | J51: =SUMIF($N$4:$BW$4,$J$4,$N51:$BW51) -> 0 | K51: =+E51*J51 -> 0 | L51: =+F51+H51-J51 -> 0 | M51: =+E51*L51 -> 0
A52: 48 | B52: 香椿 | G52: =+E52*F52 -> 0 | H52: =SUMIF($N$4:$BW$4,$H$4,$N52:$BW52) -> 0 | I52: =+E52*H52 -> 0 | J52: =SUMIF($N$4:$BW$4,$J$4,$N52:$BW52) -> 0 | K52: =+E52*J52 -> 0 | L52: =+F52+H52-J52 -> 0 | M52: =+E52*L52 -> 0
A53: 49 | B53: 蒜苗 | G53: =+E53*F53 -> 0 | H53: =SUMIF($N$4:$BW$4,$H$4,$N53:$BW53) -> 0 | I53: =+E53*H53 -> 0 | J53: =SUMIF($N$4:$BW$4,$J$4,$N53:$BW53) -> 0 | K53: =+E53*J53 -> 0 | L53: =+F53+H53-J53 -> 0 | M53: =+E53*L53 -> 0
A54: 50 | B54: 冬瓜 | G54: =+E54*F54 -> 0 | H54: =SUMIF($N$4:$BW$4,$H$4,$N54:$BW54) -> 0 | I54: =+E54*H54 -> 0 | J54: =SUMIF($N$4:$BW$4,$J$4,$N54:$BW54) -> 0 | K54: =+E54*J54 -> 0 | L54: =+F54+H54-J54 -> 0 | M54: =+E54*L54 -> 0
A55: 51 | G55: =+E55*F55 -> 0 | H55: =SUMIF($N$4:$BW$4,$H$4,$N55:$BW55) -> 0 | I55: =+E55*H55 -> 0 | J55: =SUMIF($N$4:$BW$4,$J$4,$N55:$BW55) -> 0 | K55: =+E55*J55 -> 0 | L55: =+F55+H55-J55 -> 0 | M55: =+E55*L55 -> 0
A56: 52 | G56: =+E56*F56 -> 0 | H56: =SUMIF($N$4:$BW$4,$H$4,$N56:$BW56) -> 0 | I56: =+E56*H56 -> 0 | J56: =SUMIF($N$4:$BW$4,$J$4,$N56:$BW56) -> 0 | K56: =+E56*J56 -> 0 | L56: =+F56+H56-J56 -> 0 | M56: =+E56*L56 -> 0
A57: 53 | G57: =+E57*F57 -> 0 | H57: =SUMIF($N$4:$BW$4,$H$4,$N57:$BW57) -> 0 | I57: =+E57*H57 -> 0 | J57: =SUMIF($N$4:$BW$4,$J$4,$N57:$BW57) -> 0 | K57: =+E57*J57 -> 0 | L57: =+F57+H57-J57 -> 0 | M57: =+E57*L57 -> 0
A58: 54 | G58: =+E58*F58 -> 0 | H58: =SUMIF($N$4:$BW$4,$H$4,$N58:$BW58) -> 0 | I58: =+E58*H58 -> 0 | J58: =SUMIF($N$4:$BW$4,$J$4,$N58:$BW58) -> 0 | K58: =+E58*J58 -> 0 | L58: =+F58+H58-J58 -> 0 | M58: =+E58*L58 -> 0
A59: 55 | G59: =+E59*F59 -> 0 | H59: =SUMIF($N$4:$BW$4,$H$4,$N59:$BW59) -> 0 | I59: =+E59*H59 -> 0 | J59: =SUMIF($N$4:$BW$4,$J$4,$N59:$BW59) -> 0 | K59: =+E59*J59 -> 0 | L59: =+F59+H59-J59 -> 0 | M59: =+E59*L59 -> 0
A60: 56 | G60: =+E60*F60 -> 0 | H60: =SUMIF($N$4:$BW$4,$H$4,$N60:$BW60) -> 0 | I60: =+E60*H60 -> 0 | J60: =SUMIF($N$4:$BW$4,$J$4,$N60:$BW60) -> 0 | K60: =+E60*J60 -> 0 | L60: =+F60+H60-J60 -> 0 | M60: =+E60*L60 -> 0
A61: 57 | G61: =+E61*F61 -> 0 | H61: =SUMIF($N$4:$BW$4,$H$4,$N61:$BW61) -> 0 | I61: =+E61*H61 -> 0 | J61: =SUMIF($N$4:$BW$4,$J$4,$N61:$BW61) -> 0 | K61: =+E61*J61 -> 0 | L61: =+F61+H61-J61 -> 0 | M61: =+E61*L61 -> 0
A62: 58 | G62: =+E62*F62 -> 0 | H62: =SUMIF($N$4:$BW$4,$H$4,$N62:$BW62) -> 0 | I62: =+E62*H62 -> 0 | J62: =SUMIF($N$4:$BW$4,$J$4,$N62:$BW62) -> 0 | K62: =+E62*J62 -> 0 | L62: =+F62+H62-J62 -> 0 | M62: =+E62*L62 -> 0
A63: 59 | G63: =+E63*F63 -> 0 | H63: =SUMIF($N$4:$BW$4,$H$4,$N63:$BW63) -> 0 | I63: =+E63*H63 -> 0 | J63: =SUMIF($N$4:$BW$4,$J$4,$N63:$BW63) -> 0 | K63: =+E63*J63 -> 0 | L63: =+F63+H63-J63 -> 0 | M63: =+E63*L63 -> 0
A64: 60 | G64: =+E64*F64 -> 0 | H64: =SUMIF($N$4:$BW$4,$H$4,$N64:$BW64) -> 0 | I64: =+E64*H64 -> 0 | J64: =SUMIF($N$4:$BW$4,$J$4,$N64:$BW64) -> 0 | K64: =+E64*J64 -> 0 | L64: =+F64+H64-J64 -> 0 | M64: =+E64*L64 -> 0
A65: 61 | B65: 60玉米段 | D65: 件 | E65: 60 | G65: =+E65*F65 -> 0 | H65: =SUMIF($N$4:$BW$4,$H$4,$N65:$BW65) -> 8 | I65: =+E65*H65 -> 480 | J65: =SUMIF($N$4:$BW$4,$J$4,$N65:$BW65) -> 8 | K65: =+E65*J65 -> 480 | L65: =+F65+H65-J65 -> 0 | M65: =+E65*L65 -> 0 | N65: 1 | O65: 1 | V65: 1 | W65: 1 | AF65: 1 | AG65: 1 | AL65: 1 | AM65: 1 | AP65: 1 | AQ65: 1 | AT65: 1 | AU65: 1 | BF65: 1 | BG65: 1 | BL65: 1 | BM65: 1
A66: 62 | B66: 排骨段 | D66: 件 | E66: 260 | G66: =+E66*F66 -> 0 | H66: =SUMIF($N$4:$BW$4,$H$4,$N66:$BW66) -> 3 | I66: =+E66*H66 -> 780 | J66: =SUMIF($N$4:$BW$4,$J$4,$N66:$BW66) -> 3 | K66: =+E66*J66 -> 780 | L66: =+F66+H66-J66 -> 0 | M66: =+E66*L66 -> 0 | R66: 1 | S66: 1 | AF66: 1 | AG66: 1 | AP66: 1 | AQ66: 1
A67: 63 | B67: 牛肉丸 | D67: 包 | E67: 25 | G67: =+E67*F67 -> 0 | H67: =SUMIF($N$4:$BW$4,$H$4,$N67:$BW67) -> 1 | I67: =+E67*H67 -> 25 | J67: =SUMIF($N$4:$BW$4,$J$4,$N67:$BW67) -> 1 | K67: =+E67*J67 -> 25 | L67: =+F67+H67-J67 -> 0 | M67: =+E67*L67 -> 0 | AF67: 1 | AG67: 1
A68: 64 | B68: 小五郎 | D68: 包 | E68: 17.6 | G68: =+E68*F68 -> 0 | H68: =SUMIF($N$4:$BW$4,$H$4,$N68:$BW68) -> 1 | I68: =+E68*H68 -> 17.6 | J68: =SUMIF($N$4:$BW$4,$J$4,$N68:$BW68) -> 1 | K68: =+E68*J68 -> 17.6 | L68: =+F68+H68-J68 -> 0 | M68: =+E68*L68 -> 0 | AF68: 1 | AG68: 1
A69: 65 | B69: 白腰花肠 | D69: 包 | E69: 21 | G69: =+E69*F69 -> 0 | H69: =SUMIF($N$4:$BW$4,$H$4,$N69:$BW69) -> 1 | I69: =+E69*H69 -> 21 | J69: =SUMIF($N$4:$BW$4,$J$4,$N69:$BW69) -> 1 | K69: =+E69*J69 -> 21 | L69: =+F69+H69-J69 -> 0 | M69: =+E69*L69 -> 0 | AF69: 1 | AG69: 1
A70: 66 | B70: 龙虾排 | D70: 包 | E70: 35 | G70: =+E70*F70 -> 0 | H70: =SUMIF($N$4:$BW$4,$H$4,$N70:$BW70) -> 1 | I70: =+E70*H70 -> 35 | J70: =SUMIF($N$4:$BW$4,$J$4,$N70:$BW70) -> 1 | K70: =+E70*J70 -> 35 | L70: =+F70+H70-J70 -> 0 | M70: =+E70*L70 -> 0 | AF70: 1 | AG70: 1
A71: 67 | B71: 鱼豆腐 | D71: 包 | E71: 25 | G71: =+E71*F71 -> 0 | H71: =SUMIF($N$4:$BW$4,$H$4,$N71:$BW71) -> 1 | I71: =+E71*H71 -> 25 | J71: =SUMIF($N$4:$BW$4,$J$4,$N71:$BW71) -> 1 | K71: =+E71*J71 -> 25 | L71: =+F71+H71-J71 -> 0 | M71: =+E71*L71 -> 0 | AF71: 1 | AG71: 1
A72: 68 | B72: 黄焖鸡块 | D72: 件 | E72: 110 | G72: =+E72*F72 -> 0 | H72: =SUMIF($N$4:$BW$4,$H$4,$N72:$BW72) -> 3 | I72: =+E72*H72 -> 330 | J72: =SUMIF($N$4:$BW$4,$J$4,$N72:$BW72) -> 3 | K72: =+E72*J72 -> 330 | L72: =+F72+H72-J72 -> 0 | M72: =+E72*L72 -> 0 | R72: 1 | S72: 1 | AF72: 1 | AG72: 1 | BF72: 1 | BG72: 1
A73: 69 | B73: 小酥肉 | E73: 117 | G73: =+E73*F73 -> 0 | H73: =SUMIF($N$4:$BW$4,$H$4,$N73:$BW73) -> 1 | I73: =+E73*H73 -> 117 | J73: =SUMIF($N$4:$BW$4,$J$4,$N73:$BW73) -> 1 | K73: =+E73*J73 -> 117 | L73: =+F73+H73-J73 -> 0 | M73: =+E73*L73 -> 0 | AP73: 1 | AQ73: 1
A74: 70 | B74: 盐酥鸡 | E74: 140 | G74: =+E74*F74 -> 0 | H74: =SUMIF($N$4:$BW$4,$H$4,$N74:$BW74) -> 2 | I74: =+E74*H74 -> 280 | J74: =SUMIF($N$4:$BW$4,$J$4,$N74:$BW74) -> 2 | K74: =+E74*J74 -> 280 | L74: =+F74+H74-J74 -> 0 | M74: =+E74*L74 -> 0 | V74: 1 | W74: 1 | AP74: 1 | AQ74: 1
A75: 71 | B75: 亲亲肠 | E75: 115 | G75: =+E75*F75 -> 0 | H75: =SUMIF($N$4:$BW$4,$H$4,$N75:$BW75) -> 4 | I75: =+E75*H75 -> 460 | J75: =SUMIF($N$4:$BW$4,$J$4,$N75:$BW75) -> 4 | K75: =+E75*J75 -> 460 | L75: =+F75+H75-J75 -> 0 | M75: =+E75*L75 -> 0 | R75: 1 | S75: 1 | AP75: 1 | AQ75: 1 | BB75: 1 | BC75: 1 | BF75: 1 | BG75: 1
A76: 72 | B76: 豆沙包 | E76: 75 | G76: =+E76*F76 -> 0 | H76: =SUMIF($N$4:$BW$4,$H$4,$N76:$BW76) -> 1 | I76: =+E76*H76 -> 75 | J76: =SUMIF($N$4:$BW$4,$J$4,$N76:$BW76) -> 1 | K76: =+E76*J76 -> 75 | L76: =+F76+H76-J76 -> 0 | M76: =+E76*L76 -> 0 | AP76: 1 | AQ76: 1
A77: 73 | B77: 小笼包 | E77: 98 | G77: =+E77*F77 -> 0 | H77: =SUMIF($N$4:$BW$4,$H$4,$N77:$BW77) -> 4 | I77: =+E77*H77 -> 392 | J77: =SUMIF($N$4:$BW$4,$J$4,$N77:$BW77) -> 4 | K77: =+E77*J77 -> 392 | L77: =+F77+H77-J77 -> 0 | M77: =+E77*L77 -> 0 | R77: 1 | S77: 1 | AP77: 1 | AQ77: 1 | BL77: 1 | BM77: 1 | BP77: 1 | BQ77: 1
A78: 74 | B78: 油条 | E78: 80 | G78: =+E78*F78 -> 0 | H78: =SUMIF($N$4:$BW$4,$H$4,$N78:$BW78) -> 5 | I78: =+E78*H78 -> 400 | J78: =SUMIF($N$4:$BW$4,$J$4,$N78:$BW78) -> 5 | K78: =+E78*J78 -> 400 | L78: =+F78+H78-J78 -> 0 | M78: =+E78*L78 -> 0 | R78: 1 | S78: 1 | V78: 1 | W78: 1 | AP78: 1 | AQ78: 1 | AT78: 1 | AU78: 1 | BL78: 1 | BM78: 1
A79: 75 | B79: 地瓜丸 | E79: 48 | G79: =+E79*F79 -> 0 | H79: =SUMIF($N$4:$BW$4,$H$4,$N79:$BW79) -> 4 | I79: =+E79*H79 -> 192 | J79: =SUMIF($N$4:$BW$4,$J$4,$N79:$BW79) -> 4 | K79: =+E79*J79 -> 192 | L79: =+F79+H79-J79 -> 0 | M79: =+E79*L79 -> 0 | N79: 1 | O79: 1 | AP79: 1 | AQ79: 1 | BB79: 1 | BC79: 1 | BL79: 1 | BM79: 1
A80: 76 | B80: 花卷 | E80: 75 | G80: =+E80*F80 -> 0 | H80: =SUMIF($N$4:$BW$4,$H$4,$N80:$BW80) -> 4 | I80: =+E80*H80 -> 300 | J80: =SUMIF($N$4:$BW$4,$J$4,$N80:$BW80) -> 4 | K80: =+E80*J80 -> 300 | L80: =+F80+H80-J80 -> 0 | M80: =+E80*L80 -> 0 | V80: 1 | W80: 1 | AP80: 1 | AQ80: 1 | BP80: 1 | BQ80: 1 | BT80: 1 | BU80: 1
A81: 77 | B81: 小馄饨 | E81: 116 | G81: =+E81*F81 -> 0 | H81: =SUMIF($N$4:$BW$4,$H$4,$N81:$BW81) -> 7 | I81: =+E81*H81 -> 812 | J81: =SUMIF($N$4:$BW$4,$J$4,$N81:$BW81) -> 7 | K81: =+E81*J81 -> 812 | L81: =+F81+H81-J81 -> 0 | M81: =+E81*L81 -> 0 | R81: 1 | S81: 1 | X81: 1 | Y81: 1 | AL81: 1 | AM81: 1 | AT81: 1 | AU81: 1 | BL81: 1 | BM81: 1 | BP81: 1 | BQ81: 1 | BT81: 1 | BU81: 1
A82: 78 | B82: 炸带鱼 | E82: 160 | G82: =+E82*F82 -> 0 | H82: =SUMIF($N$4:$BW$4,$H$4,$N82:$BW82) -> 3 | I82: =+E82*H82 -> 480 | J82: =SUMIF($N$4:$BW$4,$J$4,$N82:$BW82) -> 3 | K82: =+E82*J82 -> 480 | L82: =+F82+H82-J82 -> 0 | M82: =+E82*L82 -> 0 | R82: 1 | S82: 1 | BF82: 1 | BG82: 1 | BT82: 1 | BU82: 1
A83: 79 | B83: 扣肉 | E83: 190 | G83: =+E83*F83 -> 0 | H83: =SUMIF($N$4:$BW$4,$H$4,$N83:$BW83) -> 1 | I83: =+E83*H83 -> 190 | J83: =SUMIF($N$4:$BW$4,$J$4,$N83:$BW83) -> 1 | K83: =+E83*J83 -> 190 | L83: =+F83+H83-J83 -> 0 | M83: =+E83*L83 -> 0 | BT83: 1 | BU83: 1
A84: 80 | B84: 慕斯蛋糕 | E84: 120 | G84: =+E84*F84 -> 0 | H84: =SUMIF($N$4:$BW$4,$H$4,$N84:$BW84) -> 3 | I84: =+E84*H84 -> 360 | J84: =SUMIF($N$4:$BW$4,$J$4,$N84:$BW84) -> 3 | K84: =+E84*J84 -> 360 | L84: =+F84+H84-J84 -> 0 | M84: =+E84*L84 -> 0 | R84: 1 | S84: 1 | BB84: 1 | BC84: 1 | BL84: 1 | BM84: 1
A85: 81 | B85: 瑞士卷 | E85: 145 | G85: =+E85*F85 -> 0 | H85: =SUMIF($N$4:$BW$4,$H$4,$N85:$BW85) -> 2 | I85: =+E85*H85 -> 290 | J85: =SUMIF($N$4:$BW$4,$J$4,$N85:$BW85) -> 2 | K85: =+E85*J85 -> 290 | L85: =+F85+H85-J85 -> 0 | M85: =+E85*L85 -> 0 | R85: 1 | S85: 1 | BB85: 1 | BC85: 1
A86: 82 | B86: 蒙古肉 | E86: 150 | G86: =+E86*F86 -> 0 | H86: =SUMIF($N$4:$BW$4,$H$4,$N86:$BW86) -> 3 | I86: =+E86*H86 -> 450 | J86: =SUMIF($N$4:$BW$4,$J$4,$N86:$BW86) -> 3 | K86: =+E86*J86 -> 450 | L86: =+F86+H86-J86 -> 0 | M86: =+E86*L86 -> 0 | R86: 1 | S86: 1 | BH86: 1 | BI86: 1 | BT86: 1 | BU86: 1
A87: 83 | B87: 粽子 | E87: 90 | G87: =+E87*F87 -> 0 | H87: =SUMIF($N$4:$BW$4,$H$4,$N87:$BW87) -> 6 | I87: =+E87*H87 -> 540 | J87: =SUMIF($N$4:$BW$4,$J$4,$N87:$BW87) -> 6 | K87: =+E87*J87 -> 540 | L87: =+F87+H87-J87 -> 0 | M87: =+E87*L87 -> 0 | V87: 1 | W87: 1 | AL87: 1 | AM87: 1 | AT87: 1 | AU87: 1 | BH87: 1 | BI87: 1 | BL87: 1 | BM87: 1 | BT87: 1 | BU87: 1
A88: 84 | B88: 芝麻球 | E88: 55 | G88: =+E88*F88 -> 0 | H88: =SUMIF($N$4:$BW$4,$H$4,$N88:$BW88) -> 3 | I88: =+E88*H88 -> 165 | J88: =SUMIF($N$4:$BW$4,$J$4,$N88:$BW88) -> 3 | K88: =+E88*J88 -> 165 | L88: =+F88+H88-J88 -> 0 | M88: =+E88*L88 -> 0 | V88: 1 | W88: 1 | AT88: 1 | AU88: 1 | BL88: 1 | BM88: 1
A89: 85 | B89: 蛋挞 | E89: 96 | G89: =+E89*F89 -> 0 | H89: =SUMIF($N$4:$BW$4,$H$4,$N89:$BW89) -> 2 | I89: =+E89*H89 -> 192 | J89: =SUMIF($N$4:$BW$4,$J$4,$N89:$BW89) -> 2 | K89: =+E89*J89 -> 192 | L89: =+F89+H89-J89 -> 0 | M89: =+E89*L89 -> 0 | N89: 1 | O89: 1 | V89: 1 | W89: 1
A90: 86 | B90: 蒸花生 | E90: 80 | G90: =+E90*F90 -> 0 | H90: =SUMIF($N$4:$BW$4,$H$4,$N90:$BW90) -> 1 | I90: =+E90*H90 -> 80 | J90: =SUMIF($N$4:$BW$4,$J$4,$N90:$BW90) -> 1 | K90: =+E90*J90 -> 80 | L90: =+F90+H90-J90 -> 0 | M90: =+E90*L90 -> 0 | V90: 1 | W90: 1
A91: 87 | B91: 虾仁 | E91: 370 | G91: =+E91*F91 -> 0 | H91: =SUMIF($N$4:$BW$4,$H$4,$N91:$BW91) -> 1 | I91: =+E91*H91 -> 370 | J91: =SUMIF($N$4:$BW$4,$J$4,$N91:$BW91) -> 1 | K91: =+E91*J91 -> 370 | L91: =+F91+H91-J91 -> 0 | M91: =+E91*L91 -> 0 | N91: 1 | O91: 1
A92: 88 | B92: 带皮五花肉 | E92: 260 | G92: =+E92*F92 -> 0 | H92: =SUMIF($N$4:$BW$4,$H$4,$N92:$BW92) -> 2 | I92: =+E92*H92 -> 520 | J92: =SUMIF($N$4:$BW$4,$J$4,$N92:$BW92) -> 2 | K92: =+E92*J92 -> 520 | L92: =+F92+H92-J92 -> 0 | M92: =+E92*L92 -> 0 | AL92: 1 | AM92: 1 | BL92: 1 | BM92: 1
A93: 89 | B93: 翅根 | E93: 104 | G93: =+E93*F93 -> 0 | H93: =SUMIF($N$4:$BW$4,$H$4,$N93:$BW93) -> 2 | I93: =+E93*H93 -> 208 | J93: =SUMIF($N$4:$BW$4,$J$4,$N93:$BW93) -> 2 | K93: =+E93*J93 -> 208 | L93: =+F93+H93-J93 -> 0 | M93: =+E93*L93 -> 0 | R93: 1 | S93: 1 | BL93: 1 | BM93: 1
A94: 90 | B94: 鸡脖子 | E94: 45 | G94: =+E94*F94 -> 0 | H94: =SUMIF($N$4:$BW$4,$H$4,$N94:$BW94) -> 2 | I94: =+E94*H94 -> 90 | J94: =SUMIF($N$4:$BW$4,$J$4,$N94:$BW94) -> 2 | K94: =+E94*J94 -> 90 | L94: =+F94+H94-J94 -> 0 | M94: =+E94*L94 -> 0 | V94: 1 | W94: 1 | BR94: 1 | BS94: 1
A95: 91 | B95: 黑椒鸡块 | E95: 112 | G95: =+E95*F95 -> 0 | H95: =SUMIF($N$4:$BW$4,$H$4,$N95:$BW95) -> 2 | I95: =+E95*H95 -> 224 | J95: =SUMIF($N$4:$BW$4,$J$4,$N95:$BW95) -> 2 | K95: =+E95*J95 -> 224 | L95: =+F95+H95-J95 -> 0 | M95: =+E95*L95 -> 0 | V95: 1 | W95: 1 | BR95: 1 | BS95: 1
A96: 92 | B96: 卡通包 | E96: 75 | G96: =+E96*F96 -> 0 | H96: =SUMIF($N$4:$BW$4,$H$4,$N96:$BW96) -> 2 | I96: =+E96*H96 -> 150 | J96: =SUMIF($N$4:$BW$4,$J$4,$N96:$BW96) -> 2 | K96: =+E96*J96 -> 150 | L96: =+F96+H96-J96 -> 0 | M96: =+E96*L96 -> 0 | AL96: 1 | AM96: 1 | BR96: 1 | BS96: 1
A97: 93 | B97: 薯条 | E97: 105 | G97: =+E97*F97 -> 0 | H97: =SUMIF($N$4:$BW$4,$H$4,$N97:$BW97) -> 1 | I97: =+E97*H97 -> 105 | J97: =SUMIF($N$4:$BW$4,$J$4,$N97:$BW97) -> 1 | K97: =+E97*J97 -> 105 | L97: =+F97+H97-J97 -> 0 | M97: =+E97*L97 -> 0 | BR97: 1 | BS97: 1
A98: 95 | B98: 花生 | E98: 86 | G98: =+E98*F98 -> 0 | H98: =SUMIF($N$4:$BW$4,$H$4,$N98:$BW98) -> 1 | I98: =+E98*H98 -> 86 | J98: =SUMIF($N$4:$BW$4,$J$4,$N98:$BW98) -> 1 | K98: =+E98*J98 -> 86 | L98: =+F98+H98-J98 -> 0 | M98: =+E98*L98 -> 0 | BR98: 1 | BS98: 1
A99: 96 | B99: 洋葱圈 | E99: 105 | G99: =+E99*F99 -> 0 | H99: =SUMIF($N$4:$BW$4,$H$4,$N99:$BW99) -> 1 | I99: =+E99*H99 -> 105 | J99: =SUMIF($N$4:$BW$4,$J$4,$N99:$BW99) -> 1 | K99: =+E99*J99 -> 105 | L99: =+F99+H99-J99 -> 0 | M99: =+E99*L99 -> 0 | BR99: 1 | BS99: 1
A100: 97 | G100: =+E100*F100 -> 0 | H100: =SUMIF($N$4:$BW$4,$H$4,$N100:$BW100) -> 0 | I100: =+E100*H100 -> 0 | J100: =SUMIF($N$4:$BW$4,$J$4,$N100:$BW100) -> 0 | K100: =+E100*J100 -> 0 | L100: =+F100+H100-J100 -> 0 | M100: =+E100*L100 -> 0
...

Sheet 用餐人数录入
B1: 用餐人数明细
B2: 酒店名称：
A3: 序号 | B3: 货品名称 | C3: 单位 | D3: 单价（根据时间情况填写） | E3: 人数 | F3: 金额 | G3: 1号 | H3: 2号 | I3: 3号 | J3: 4号 | K3: 5号 | L3: 6号 | M3: 7号 | N3: 8号 | O3: 9号 | P3: 10号 | Q3: 11号 | R3: 12号 | S3: 13号 | T3: 14号 | U3: 15号 | V3: 16号 | W3: 17号 | X3: 18号 | Y3: 19号 | Z3: 20号 | AA3: 21号 | AB3: 22号 | AC3: 23号 | AD3: 24号 | AE3: 25号 | AF3: 26号 | AG3: 27号 | AH3: 28号 | AI3: 29号 | AJ3: 30号 | AK3: 31号
A4: 1 | B4: 客餐 | C4: 份 | D4: 7 | E4: =SUM(G4:AK4) -> 5082 | F4: =+D4*E4 -> 35574 | G4: 126 | H4: 136 | I4: 163 | J4: 155 | K4: 160 | L4: 145 | M4: 166 | N4: 172 | O4: 188 | P4: 200 | Q4: 180 | R4: 178 | S4: 126 | T4: 175 | U4: 170 | V4: 180 | W4: 158 | X4: 186 | Y4: 166 | Z4: 150 | AA4: 160 | AB4: 186 | AC4: 155 | AD4: 150 | AE4: 155 | AF4: 160 | AG4: 130 | AH4: 165 | AI4: 178 | AJ4: 180 | AK4: 183
A5: 2 | B5: 员工餐 | C5: 份 | D5: 3 | E5: =SUM(G5:AK5) -> 635 | F5: =+D5*E5 -> 1905 | G5: 21 | H5: 19 | I5: 22 | J5: 19 | K5: 22 | L5: 21 | M5: 21 | N5: 20 | O5: 24 | P5: 24 | Q5: 23 | R5: 19 | S5: 18 | T5: 23 | U5: 21 | V5: 19 | W5: 18 | X5: 21 | Y5: 19 | Z5: 22 | AA5: 21 | AB5: 19 | AC5: 16 | AD5: 21 | AE5: 23 | AF5: 21 | AG5: 20 | AH5: 19 | AI5: 19 | AJ5: 19 | AK5: 21
A6: 3 | B6: 下午茶 | C6: 天 | D6: 1 | E6: =SUM(G6:AK6) -> 2170 | F6: =+D6*E6 -> 2170 | G6: 70 | H6: 70 | I6: 70 | J6: 70 | K6: 70 | L6: 70 | M6: 70 | N6: 70 | O6: 70 | P6: 70 | Q6: 70 | R6: 70 | S6: 70 | T6: 70 | U6: 70 | V6: 70 | W6: 70 | X6: 70 | Y6: 70 | Z6: 70 | AA6: 70 | AB6: 70 | AC6: 70 | AD6: 70 | AE6: 70 | AF6: 70 | AG6: 70 | AH6: 70 | AI6: 70 | AJ6: 70 | AK6: 70
A7: 4 | E7: =SUM(G7:AK7) -> 0 | F7: =+D7*E7 -> 0
A8: 5 | E8: =SUM(G8:AK8) -> 0 | F8: =+D8*E8 -> 0
A9: 6 | E9: =SUM(G9:AK9) -> 0 | F9: =+D9*E9 -> 0
B10: 用餐人数 | E10: =SUM(E4:E9) -> 7887 | F10: =SUM(F4:F9) -> 39649 | G10: 201 | H10: 209 | I10: 232 | J10: 215 | K10: 202 | L10: 208 | M10: 181 | N10: 150 | O10: 150 | P10: 154 | Q10: 173 | R10: 189 | S10: 228 | T10: 253 | U10: =SUM(U4:U9) -> 261 | V10: =SUM(V4:V9) -> 269 | W10: =SUM(W4:W9) -> 246 | X10: =SUM(X4:X9) -> 277 | Y10: =SUM(Y4:Y9) -> 255 | Z10: =SUM(Z4:Z9) -> 242 | AA10: =SUM(AA4:AA9) -> 251 | AB10: =SUM(AB4:AB9) -> 275 | ... AK10: =SUM(AK4:AK9) -> 274

Sheet 餐厅工资录入 
A1: 姓名 | B1: 部门 | C1: 岗位 | D1: 是否转正 | E1: 薪等 | F1: 薪级 | G1: 总工资 | H1: 基本工资 | I1: 岗位工资 | J1: 绩效工资 | K1: 出勤天数 | L1: 1号工作时长 | M1: 2号工作时长 | N1: 3号工作时长 | O1: 4号工作时长 | P1: 5号工作时长 | Q1: 6号工作时长 | R1: 7号工作时长 | S1: 8号工作时长 | T1: 9号工作时长 | U1: 10号工作时长 | V1: 11号工作时长 | W1: 12号工作时长 | X1: 13号工作时长 | Y1: 14号工作时长 | Z1: 15号工作时长 | AA1: 16号工作时长 | AB1: 17号工作时长 | AC1: 18号工作时长 | AD1: 19号工作时长 | AE1: 20号工作时长 | AF1: 21号工作时长 | AG1: 22号工作时长 | AH1: 23号工作时长 | AI1: 24号工作时长 | AJ1: 25号工作时长 | AK1: 26号工作时长 | AL1: 27号工作时长 | AM1: 28号工作时长 | AN1: 29号工作时长 | AO1: 30号工作时长 | AP1: 31号工作时长
A2: 孟庆龙 | B2: 餐厅 | C2: 厨师 | D2: 是 | G2: 8000 | H2: 2200 | I2: 5800 | K2: 25 | L2: 0 | M2: 8 | N2: 8 | O2: 8 | P2: 8 | Q2: 8 | R2: 8 | S2: 0 | T2: 8 | U2: 8 | V2: 8 | W2: 8 | X2: 8 | Y2: 0 | Z2: 8 | AA2: 8 | AB2: 0 | AC2: 8 | AD2: 8 | AE2: 8 | AF2: 8 | AG2: 8 | AH2: 0 | AI2: 8 | AJ2: 8 | AK2: 8 | AL2: 8 | AM2: 8 | AN2: 8 | AO2: 8 | AP2: 0
A3: 梁晨 | B3: 餐厅 | C3: 厨师 | D3: 是 | G3: 7000 | H3: 2200 | I3: 4800 | K3: 25 | L3: 8 | M3: 8 | N3: 8 | O3: 8 | P3: 8 | Q3: 0 | R3: 8 | S3: 8 | T3: 8 | U3: 8 | V3: 8 | W3: 8 | X3: 0 | Y3: 8 | Z3: 8 | AA3: 8 | AB3: 8 | AC3: 8 | AD3: 8 | AE3: 0 | AF3: 8 | AG3: 8 | AH3: 8 | AI3: 8 | AJ3: 8 | AK3: 8 | AL3: 8 | AM3: 8 | AN3: 8 | AO3: 8 | AP3: 8
A4: 栾玉艳 | B4: 餐厅 | C4: 明档 | D4: 是 | G4: 3500 | H4: 2200 | I4: 1300 | J4: 0 | K4: 25 | L4: 8 | M4: 8 | N4: 8 | O4: 8 | P4: 8 | Q4: 8 | R4: 0 | S4: 8 | T4: 8 | U4: 8 | V4: 8 | W4: 8 | X4: 8 | Y4: 8 | Z4: 8 | AA4: 8 | AB4: 8 | AC4: 8 | AD4: 8 | AE4: 8 | AF4: 8 | AG4: 8 | AH4: 8 | AI4: 0 | AJ4: 8 | AK4: 8 | AL4: 8 | AM4: 8 | AN4: 0 | AO4: 0 | AP4: 8
A5: 唐艳 | B5: 餐厅 | C5: 明档 | D5: 是 | G5: 3500 | H5: 2200 | I5: 1300 | J5: 0 | K5: 25 | L5: 8 | M5: 8 | N5: 8 | O5: 8 | P5: 8 | Q5: 8 | R5: 8 | S5: 8 | T5: 0 | U5: 8 | V5: 0 | W5: 0 | X5: 8 | Y5: 8 | Z5: 8 | AA5: 8 | AB5: 8 | AC5: 8 | AD5: 8 | AE5: 8 | AF5: 8 | AG5: 8 | AH5: 8 | AI5: 8 | AJ5: 8 | AK5: 8 | AL5: 0 | AM5: 8 | AN5: 8 | AO5: 8 | AP5: 8
A13: 合计 | L13: =SUM(L2:L12) -> 24 | M13: =SUM(M2:M12) -> 32 | N13: =SUM(N2:N12) -> 32 | O13: =SUM(O2:O12) -> 32 | P13: =SUM(P2:P12) -> 32 | Q13: =SUM(Q2:Q12) -> 24 | R13: =SUM(R2:R12) -> 24 | S13: =SUM(S2:S12) -> 24 | ... AP13: =SUM(AP2:AP12) -> 24

Sheet 平台推广费录入
B1: 固定成本表
B2: 酒店名称：
A3: 序号 | B3: 项目 | C3: 总额 | D3: 单位 | E3: 单价 | F3: 总额 | G3: 天数 | H3: 用量 | I3: 剩余金额 | J3: 1号金额 | K3: 2号金额 | L3: 3号金额 | M3: 4号金额 | N3: 5号金额 | O3: 6号金额 | P3: 7号金额 | Q3: 8号金额 | R3: 9号金额 | S3: 10号金额 | T3: 11号金额 | U3: 12号金额 | V3: 13号金额 | W3: 14号金额 | X3: 15号金额 | Y3: 16号金额 | Z3: 17号金额 | AA3: 18号金额 | AB3: 19号金额 | AC3: 20号金额 | AD3: 21号金额 | AE3: 22号金额 | AF3: 23号金额 | AG3: 24号金额 | AH3: 25号金额 | AI3: 26号金额 | AJ3: 27号金额 | AK3: 28号金额 | AL3: 29号金额 | AM3: 30号金额 | AN3: 31号金额
A4: 1 | B4: 美团推广费 | F4: 6282.91 | G4: 31 | H4: =SUM(J4:AN4) -> 6200 | I4: =F4-H4 -> 82.91 | J4: 150 | K4: 150 | L4: 150 | M4: 150 | N4: 150 | O4: 150 | P4: 150 | Q4: 150 | R4: 150 | S4: 150 | T4: 150 | U4: 150 | V4: 200 | W4: 200 | X4: 200 | Y4: 200 | Z4: 200 | AA4: 200 | AB4: 200 | AC4: 200 | AD4: 200 | AE4: 200 | AF4: 200 | AG4: 200 | AH4: 200 | AI4: 200 | AJ4: 300 | AK4: 200 | AL4: 300 | AM4: 300 | AN4: 500
A5: 2 | B5: 携程推广费 | F5: 14956.77 | G5: 31 | H5: =SUM(J5:AN5) -> 5927.81 | I5: =F5-H5 -> 9028.96 | J5: 200 | K5: 200 | L5: 200 | M5: 200 | N5: 200 | O5: 200 | P5: 200 | Q5: 200 | R5: 200 | S5: 200 | T5: 200 | U5: 200 | V5: 200 | W5: 200 | X5: 200 | Y5: 200 | Z5: 200 | AA5: 200 | AB5: 200 | AC5: 115.54 | AD5: 200 | AE5: 149.78 | AF5: 200 | AG5: 200 | AH5: 128.48 | AI5: 88 | AJ5: 181.7 | AK5: 200 | AL5: 156.71 | AM5: 251.65 | AN5: 255.95
A6: 3 | B6: 抖音推广费 | F6: 0 | G6: 31 | H6: =SUM(J6:AN6) -> 0 | I6: =F6-H6 -> 0
A7: 4 | B7: 去哪推广费 | F7: 3600 | G7: 31 | H7: =SUM(J7:AN7) -> 3596 | I7: =F7-H7 -> 4 | J7: 116 | K7: 116 | L7: 116 | M7: 116 | N7: 116 | O7: 116 | P7: 116 | Q7: 116 | R7: 116 | S7: 116 | T7: 116 | U7: 116 | V7: 116 | W7: 116 | X7: 116 | Y7: 116 | Z7: 116 | AA7: 116 | AB7: 116 | AC7: 116 | AD7: 116 | AE7: 116 | AF7: 116 | AG7: 116 | AH7: 116 | AI7: 116 | AJ7: 116 | AK7: 116 | AL7: 116 | AM7: 116 | AN7: 116
A8: 5 | B8: 同城推广费 | F8: 620 | G8: 31 | H8: =SUM(J8:AN8) -> 620 | I8: =F8-H8 -> 0 | J8: 20 | K8: 20 | L8: 20 | M8: 20 | N8: 20 | O8: 20 | P8: 20 | Q8: 20 | R8: 20 | S8: 20 | T8: 20 | U8: 20 | V8: 20 | W8: 20 | X8: 20 | Y8: 20 | Z8: 20 | AA8: 20 | AB8: 20 | AC8: 20 | AD8: 20 | AE8: 20 | AF8: 20 | AG8: 20 | AH8: 20 | AI8: 20 | AJ8: 20 | AK8: 20 | AL8: 20 | AM8: 20 | AN8: 20
A9: 6 | B9: 飞猪推广费 | E9: 0.044 | F9: =28551.54*E9 -> 1256.2678 | G9: 31 | H9: =SUM(J9:AN9) -> 1256.2678 | I9: =F9-H9 -> 0 | J9: =F9/31 -> 40.524766 | K9: =F9/31 -> 40.524766 | L9: =F9/31 -> 40.524766 | M9: =F9/31 -> 40.524766 | N9: =F9/31 -> 40.524766 | O9: =F9/31 -> 40.524766 | P9: =F9/31 -> 40.524766 | Q9: =F9/31 -> 40.524766 | R9: =F9/31 -> 40.524766 | S9: =F9/31 -> 40.524766 | T9: =F9/31 -> 40.524766 | U9: =F9/31 -> 40.524766 | V9: =F9/31 -> 40.524766 | W9: =F9/31 -> 40.524766 | X9: =F9/31 -> 40.524766 | Y9: =F9/31 -> 40.524766 | Z9: =F9/31 -> 40.524766 | AA9: =F9/31 -> 40.524766 | AB9: =F9/31 -> 40.524766 | AC9: =F9/31 -> 40.524766 | AD9: =F9/31 -> 40.524766 | AE9: =F9/31 -> 40.524766 | AF9: =F9/31 -> 40.524766 | AG9: =F9/31 -> 40.524766 | AH9: =F9/31 -> 40.524766 | AI9: =F9/31 -> 40.524766 | AJ9: =F9/31 -> 40.524766 | AK9: =F9/31 -> 40.524766 | AL9: =F9/31 -> 40.524766 | AM9: =F9/31 -> 40.524766 | AN9: =F9/31 -> 40.524766
A10: 7 | H10: =SUM(J10:AN10) -> 0 | I10: =F10-H10 -> 0
A11: 8 | H11: =SUM(J11:AN11) -> 0 | I11: =F11-H11 -> 0
A12: 9 | H12: =SUM(J12:AN12) -> 0 | I12: =F12-H12 -> 0
A13: 10 | H13: =SUM(J13:AN13) -> 0 | I13: =F13-H13 -> 0
B14: 合计 | J14: =SUM(J4:J13) -> 526.52477 | K14: =SUM(K4:K13) -> 526.52477 | L14: =SUM(L4:L13) -> 526.52477 | M14: =SUM(M4:M13) -> 526.52477 | N14: =SUM(N4:N13) -> 526.52477 | O14: =SUM(O4:O13) -> 526.52477 | P14: =SUM(P4:P13) -> 526.52477 | Q14: =SUM(Q4:Q13) -> 526.52477 | ... AN14: =SUM(AN4:AN13) -> 932.47477

Sheet 能耗录入
A1: 耗能表
A2: 酒店名称： | I2: 周期：
A3: 项目 | B3: 规格型号 | C3: 单位 | D3: 单价 | E3: 月底表数/停车费余额 | F3: 电表 | G3: 出库金额 | I3: 1号 | K3: 2号 | M3: 3号 | O3: 4号 | Q3: 5号 | S3: 6号 | U3: 7号 | W3: 8号 | Y3: 9号 | AA3: 10号 | AC3: 11号 | AE3: 12号 | AG3: 13号 | AI3: 14号 | AK3: 15号 | AM3: 16号 | AO3: 17号 | AQ3: 18号 | AS3: 19号 | AU3: 20号 | AW3: 21号 | AY3: 22号 | BA3: 23号 | BC3: 24号 | BE3: 25号 | BG3: 26号 | BI3: 27号 | BK3: 28号 | BM3: 29号 | BO3: 30号 | BQ3: 31号
F4: 用量 | H4: 结存 | I4: 电表数 | J4: 用量 | K4: 电表数 | L4: 用量 | M4: 电表数 | N4: 用量 | O4: 电表数 | P4: 用量 | Q4: 电表数 | R4: 用量 | S4: 电表数 | T4: 用量 | U4: 电表数 | V4: 用量 | W4: 电表数 | X4: 用量 | Y4: 电表数 | Z4: 用量 | AA4: 电表数 | AB4: 用量 | AC4: 电表数 | AD4: 用量 | AE4: 电表数 | AF4: 用量 | AG4: 电表数 | AH4: 用量 | AI4: 电表数 | AJ4: 用量 | AK4: 电表数 | AL4: 用量 | AM4: 电表数 | AN4: 用量 | AO4: 电表数 | AP4: 用量 | AQ4: 电表数 | AR4: 用量 | AS4: 电表数 | AT4: 用量 | AU4: 电表数 | AV4: 用量 | AW4: 电表数 | AX4: 用量 | AY4: 电表数 | AZ4: 用量 | BA4: 电表数 | BB4: 用量 | BC4: 电表数 | BD4: 用量 | BE4: 电表数 | BF4: 用量 | BG4: 电表数 | BH4: 用量 | BI4: 电表数 | BJ4: 用量 | BK4: 电表数 | BL4: 用量 | BM4: 电表数 | BN4: 用量 | BO4: 电表数 | BP4: 用量 | BQ4: 电表数 | BR4: 用量
A5: 电费 | B5: 1 | C5: 度 | D5: 0.77 | E5: 0 | F5: =SUMIF($J$4:$BR$4,$G$3,$J$5:$BR$5) -> 0 | G5: =F5*B5*D5 -> 0 | H5: =E5+F5/B5 -> 0 | I5: =J5+E5 -> 2532.57 | J5: 2532.57 | K5: =L5+I5 -> 5010.26 | L5: 2477.69 | M5: =N5+K5 -> 8096.18 | N5: 3085.92 | O5: =P5+M5 -> 11673.93 | P5: 3577.75 | Q5: =R5+O5 -> 15267.57 | R5: 3593.64 | S5: =T5+Q5 -> 18956.95 | T5: 3689.38 | U5: =V5+S5 -> 22328.58 | V5: 3371.63 | W5: =X5+U5 -> 25709.31 | X5: 3380.73 | Y5: =Z5+W5 -> 29643.08 | Z5: 3933.77 | AA5: =AB5+Y5 -> 33367.31 | AB5: 3724.23 | AC5: =AD5+AA5 -> 37685.01 | AD5: 4317.7 | AE5: =AF5+AC5 -> 41665.36 | AF5: 3980.35 | AG5: =AH5+AE5 -> 44921.12 | AH5: 3255.76 | AI5: =AJ5+AG5 -> 47877.63 | AJ5: 2956.51 | AK5: =AL5+AI5 -> 50794.69 | AL5: 2917.06 | AM5: =AN5+AK5 -> 53982.42 | AN5: 3187.73 | AO5: =AP5+AM5 -> 57225.95 | AP5: 3243.53 | AQ5: =AR5+AO5 -> 59766.46 | AR5: 2540.51 | AS5: =AT5+AQ5 -> 63077.21 | AT5: 3310.75 | AU5: =AV5+AS5 -> 65614.45 | AV5: 2537.24 | AW5: =AX5+AU5 -> 68625.21 | AX5: 3010.76 | AY5: =AZ5+AW5 -> 71833.02 | AZ5: 3207.81 | BA5: =BB5+AY5 -> 74895.73 | BB5: 3062.71 | BC5: =BD5+BA5 -> 78103.46 | BD5: 3207.73 | BE5: =BF5+BC5 -> 81104.33 | BF5: 3000.87 | BG5: =BH5+BE5 -> 84396.09 | BH5: 3291.76 | BI5: =BJ5+BG5 -> 87431.54 | BJ5: 3035.45 | BK5: =BL5+BI5 -> 90880.42 | BL5: 3448.88 | BM5: =BN5+BK5 -> 94786.52 | BN5: 3906.1 | BO5: =BP5+BM5 -> 98689.5 | BP5: 3902.98 | BQ5: =BR5+BO5 -> 102763.38 | BR5: 4073.88
A6: 水费 | B6: 1 | C6: 吨 | D6: 5.3 | E6: 0 | F6: =SUMIF($J$4:$BR$4,$G$4,$J6:$BR6) -> 0 | G6: =F6*B6*D6 -> 0 | H6: =E6+F6/B6 -> 0 | I6: =J6+E6 -> 24 | J6: 24 | K6: =L6+I6 -> 53 | L6: 29 | M6: =N6+K6 -> 84 | N6: 31 | O6: =P6+M6 -> 116 | P6: 32 | Q6: =R6+O6 -> 164 | R6: 48 | S6: =T6+Q6 -> 202 | T6: 38 | U6: =V6+S6 -> 237 | V6: 35 | W6: =X6+U6 -> 279 | X6: 42 | Y6: =Z6+W6 -> 320 | Z6: 41 | AA6: =AB6+Y6 -> 364 | AB6: 44 | AC6: =AD6+AA6 -> 404 | AD6: 40 | AE6: =AF6+AC6 -> 442 | AF6: 38 | AG6: =AH6+AE6 -> 486 | AH6: 44 | AI6: =AJ6+AG6 -> 513 | AJ6: 27 | AK6: =AL6+AI6 -> 552 | AL6: 39 | AM6: =AN6+AK6 -> 587 | AN6: 35 | AO6: =AP6+AM6 -> 635 | AP6: 48 | AQ6: =AR6+AO6 -> 674 | AR6: 39 | AS6: =AT6+AQ6 -> 716 | AT6: 42 | AU6: =AV6+AS6 -> 756 | AV6: 40 | AW6: =AX6+AU6 -> 777 | AX6: 21 | AY6: =AZ6+AW6 -> 818 | AZ6: 41 | BA6: =BB6+AY6 -> 842 | BB6: 24 | BC6: =BD6+BA6 -> 881 | BD6: 39 | BE6: =BF6+BC6 -> 918.5 | BF6: 37.5 | BG6: =BH6+BE6 -> 962.5 | BH6: 44 | BI6: =BJ6+BG6 -> 996 | BJ6: 33.5 | BK6: =BL6+BI6 -> 1025 | BL6: 29 | BM6: =BN6+BK6 -> 1064 | BN6: 39 | BO6: =BP6+BM6 -> 1100 | BP6: 36 | BQ6: =BR6+BO6 -> 1137 | BR6: 37
A9: 4
A10: 5
A11: 6
A12: 7
A13: 8
A14: 9
A15: 10
A16: 11
A17: 12
A18: 13
A19: 14
A22: 1
... A24: 3
EE25: 0

Sheet 固定费用录入
B1: 固定成本表 | G1: 133
B2: 酒店名称：
A3: 序号 | B3: 项目 | C3: 总面积 | D3: 单位 | E3: 单价 | F3: 月总额(根据实际情况填写） | G3: 天数 | H3: 1号 | I3: 2号 | J3: 3号 | K3: 4号 | L3: 5号 | M3: 6号 | N3: 7号 | O3: 8号 | P3: 9号 | Q3: 10号 | R3: 11号 | S3: 12号 | T3: 13号 | U3: 14号 | V3: 15号 | W3: 16号 | X3: 17号 | Y3: 18号 | Z3: 19号 | AA3: 20号 | AB3: 21号 | AC3: 22号 | AD3: 23号 | AE3: 24号 | AF3: 25号 | AG3: 26号 | AH3: 27号 | AI3: 28号 | AJ3: 29号 | AK3: 30号 | AL3: 31号
H4: 1号金额 | I4: 2号金额 | J4: 3号金额 | K4: 4号金额 | L4: 5号金额 | M4: 6号金额 | N4: 7号金额 | O4: 8号金额 | P4: 9号金额 | Q4: 10号金额 | R4: 11号金额 | S4: 12号金额 | T4: 13号金额 | U4: 14号金额 | V4: 15号金额 | W4: 16号金额 | X4: 17号金额 | Y4: 18号金额 | Z4: 19号金额 | AA4: 20号金额 | AB4: 21号金额 | AC4: 22号金额 | AD4: 23号金额 | AE4: 24号金额 | AF4: 25号金额 | AG4: 26号金额 | AH4: 27号金额 | AI4: 28号金额 | AJ4: 29号金额 | AK4: 30号金额 | AL4: 31号金额
A5: 1 | B5: 租金 | D5: 平方 | F5: 193788 | G5: 31 | H5: =IFERROR($F5/$G5,0) -> 6251.2258 | I5: =IFERROR($F5/$G5,0) -> 6251.2258 | J5: =IFERROR($F5/$G5,0) -> 6251.2258 | K5: =IFERROR($F5/$G5,0) -> 6251.2258 | L5: =IFERROR($F5/$G5,0) -> 6251.2258 | M5: =IFERROR($F5/$G5,0) -> 6251.2258 | N5: =IFERROR($F5/$G5,0) -> 6251.2258 | O5: =IFERROR($F5/$G5,0) -> 6251.2258 | ... AL5: =IFERROR($F5/$G5,0) -> 6251.2258
A6: 2 | B6: 物业费 | D6: 平方 | F6: 27684 | G6: 31 | H6: =IFERROR($F6/$G6,0) -> 893.03226 | I6: =IFERROR($F6/$G6,0) -> 893.03226 | J6: =IFERROR($F6/$G6,0) -> 893.03226 | K6: =IFERROR($F6/$G6,0) -> 893.03226 | L6: =IFERROR($F6/$G6,0) -> 893.03226 | M6: =IFERROR($F6/$G6,0) -> 893.03226 | N6: =IFERROR($F6/$G6,0) -> 893.03226 | O6: =IFERROR($F6/$G6,0) -> 893.03226 | ... AL6: =IFERROR($F6/$G6,0) -> 893.03226
A7: 3 | B7: 保险 | D7: 月 | F7: 1963 | G7: 31 | H7: =IFERROR($F7/$G7,0) -> 63.322581 | I7: =IFERROR($F7/$G7,0) -> 63.322581 | J7: =IFERROR($F7/$G7,0) -> 63.322581 | K7: =IFERROR($F7/$G7,0) -> 63.322581 | L7: =IFERROR($F7/$G7,0) -> 63.322581 | M7: =IFERROR($F7/$G7,0) -> 63.322581 | N7: =IFERROR($F7/$G7,0) -> 63.322581 | O7: =IFERROR($F7/$G7,0) -> 63.322581 | ... AL7: =IFERROR($F7/$G7,0) -> 63.322581
A8: 4 | B8: 网费 | D8: 月 | F8: 1200 | G8: 31 | H8: =IFERROR($F8/$G8,0) -> 38.709677 | I8: =IFERROR($F8/$G8,0) -> 38.709677 | J8: =IFERROR($F8/$G8,0) -> 38.709677 | K8: =IFERROR($F8/$G8,0) -> 38.709677 | L8: =IFERROR($F8/$G8,0) -> 38.709677 | M8: =IFERROR($F8/$G8,0) -> 38.709677 | N8: =IFERROR($F8/$G8,0) -> 38.709677 | O8: =IFERROR($F8/$G8,0) -> 38.709677 | ... AL8: =IFERROR($F8/$G8,0) -> 38.709677
A9: 5 | B9: 通讯费 | D9: 月 | F9: 300 | G9: 31 | H9: =IFERROR($F9/$G9,0) -> 9.6774194 | I9: =IFERROR($F9/$G9,0) -> 9.6774194 | J9: =IFERROR($F9/$G9,0) -> 9.6774194 | K9: =IFERROR($F9/$G9,0) -> 9.6774194 | L9: =IFERROR($F9/$G9,0) -> 9.6774194 | M9: =IFERROR($F9/$G9,0) -> 9.6774194 | N9: =IFERROR($F9/$G9,0) -> 9.6774194 | O9: =IFERROR($F9/$G9,0) -> 9.6774194 | ... AL9: =IFERROR($F9/$G9,0) -> 9.6774194
A10: 6 | B10: 社保公积金 | D10: 月 | E10: 19 | F10: =E10*1130.5 -> 21479.5 | G10: 31 | H10: =IFERROR($F10/$G10,0) -> 692.8871 | I10: =IFERROR($F10/$G10,0) -> 692.8871 | J10: =IFERROR($F10/$G10,0) -> 692.8871 | K10: =IFERROR($F10/$G10,0) -> 692.8871 | L10: =IFERROR($F10/$G10,0) -> 692.8871 | M10: =IFERROR($F10/$G10,0) -> 692.8871 | N10: =IFERROR($F10/$G10,0) -> 692.8871 | O10: =IFERROR($F10/$G10,0) -> 692.8871 | ... AL10: =IFERROR($F10/$G10,0) -> 692.8871
A11: 7
A12: 8
A13: 9
A14: 10
A15: 11 | H15: =SUM(H5:H14) -> 7948.8548 | I15: =SUM(I5:I14) -> 7948.8548 | J15: =SUM(J5:J14) -> 7948.8548 | K15: =SUM(K5:K14) -> 7948.8548 | L15: =SUM(L5:L14) -> 7948.8548 | M15: =SUM(M5:M14) -> 7948.8548 | N15: =SUM(N5:N14) -> 7948.8548 | O15: =SUM(O5:O14) -> 7948.8548 | ... AL15: =SUM(AL5:AL14) -> 7948.8548

Sheet 管理层工资录入
A1: 姓名 | B1: 部门 | C1: 岗位 | D1: 是否转正 | E1: 薪等 | F1: 薪级 | G1: 总工资 | H1: 基本工资 | I1: 岗位工资 | J1: 绩效工资 | K1: 出勤天数 | L1: 1号 | M1: 2号 | N1: 3号 | O1: 4号 | P1: 5号 | Q1: 6号 | R1: 7号 | S1: 8号 | T1: 9号 | U1: 10号 | V1: 11号 | W1: 12号 | X1: 13号 | Y1: 14号 | Z1: 15号 | AA1: 16号 | AB1: 17号 | AC1: 18号 | AD1: 19号 | AE1: 20号 | AF1: 21号 | AG1: 22号 | AH1: 23号 | AI1: 24号 | AJ1: 25号 | AK1: 26号 | AL1: 27号 | AM1: 28号 | AN1: 29号 | AO1: 30号 | AP1: 31号
A2: 李祯 | B2: 运营 | C2: 店总 | D2: 是 | G2: =H2+I2+J2 -> 16800 | H2: 2200 | I2: 9560 | J2: 5040 | K2: 30 | L2: 8 | M2: 8 | N2: 8 | O2: 8 | P2: 8 | Q2: 0 | R2: 0 | S2: 0 | T2: 0 | U2: 0 | V2: 8 | W2: 8 | X2: 8 | Y2: 8 | Z2: 8 | AA2: 8 | AB2: 8 | AC2: 8 | AD2: 8 | AE2: 8 | AF2: 8 | AG2: 8 | AH2: 8 | AI2: 8 | AJ2: 8 | AK2: 8 | AL2: 8 | AM2: 8 | AN2: 8 | AO2: 8 | AP2: 8
A3: 苏梦洁 | B3: 运营 | C3: 店助 | D3: 是 | G3: =H3+I3+J3 -> 8000 | H3: 2200 | I3: 3400 | J3: 2400 | K3: 30 | L3: 8 | M3: 8 | N3: 8 | O3: 8 | P3: 8 | Q3: 8 | R3: 8 | S3: 8 | T3: 8 | U3: 8 | V3: 8 | W3: 0 | X3: 8 | Y3: 8 | Z3: 8 | AA3: 0 | AB3: 0 | AC3: 0 | AD3: 8 | AE3: 8 | AF3: 8 | AG3: 8 | AH3: 8 | AI3: 8 | AJ3: 8 | AK3: 0 | AL3: 8 | AM3: 8 | AN3: 8 | AO3: 8 | AP3: 8
A4: 合计 | L4: =SUM(L2:L3) -> 16 | M4: =SUM(M2:M3) -> 16 | N4: =SUM(N2:N3) -> 16 | O4: =SUM(O2:O3) -> 16 | P4: =SUM(P2:P3) -> 16 | Q4: =SUM(Q2:Q3) -> 8 | R4: =SUM(R2:R3) -> 8 | S4: =SUM(S2:S3) -> 8 | ... AP4: =SUM(AP2:AP3) -> 16

Sheet 前台二维码提成呈现
B1: 前台二维码提成明细
B2: 酒店名称：
A3: 序号 | B3: 货品名称 | C3: 平台 | D3: 单位 | E3: 单价 | G3: 出库金额 | H3: 1号 | I3: 2号 | J3: 3号 | K3: 4号 | L3: 5号 | M3: 6号 | N3: 7号 | O3: 8号 | P3: 9号 | Q3: 10号 | R3: 11号 | S3: 12号 | T3: 13号 | U3: 14号 | V3: 15号 | W3: 16号 | X3: 17号 | Y3: 18号 | Z3: 19号 | AA3: 20号 | AB3: 21号 | AC3: 22号 | AD3: 23号 | AE3: 24号 | AF3: 25号 | AG3: 26号 | AH3: 27号 | AI3: 28号 | AJ3: 29号 | AK3: 30号 | AL3: 31号
F4: 服务次数 | H4: 金额 | I4: 金额 | J4: 金额 | K4: 金额 | L4: 金额 | M4: 金额 | N4: 金额 | O4: 金额 | P4: 金额 | Q4: 金额 | R4: 金额 | S4: 金额 | T4: 金额 | U4: 金额 | V4: 金额 | W4: 金额 | X4: 金额 | Y4: 金额 | Z4: 金额 | AA4: 金额 | AB4: 金额 | AC4: 金额 | AD4: 金额 | AE4: 金额 | AF4: 金额 | AG4: 金额 | AH4: 金额 | AI4: 金额 | AJ4: 金额 | AK4: 金额 | AL4: 金额
A5: 1 | B5: =前台二维码提成录入!B5 -> 李龙梅 | C5: =前台二维码提成录入!C5 -> 洗衣 | D5: =前台二维码提成录入!D5 -> 次 | E5: =前台二维码提成录入!E5 -> 1.5 | F5: =前台二维码提成录入!F5 -> 3 | G5: =前台二维码提成录入!G5 -> 4.5 | H5: =前台二维码提成录入!H5*$E5 -> 0 | I5: =前台二维码提成录入!I5*$E5 -> 0 | J5: =前台二维码提成录入!J5*$E5 -> 0 | K5: =前台二维码提成录入!K5*$E5 -> 0 | L5: =前台二维码提成录入!L5*$E5 -> 0 | M5: =前台二维码提成录入!M5*$E5 -> 0 | N5: =前台二维码提成录入!N5*$E5 -> 0 | O5: =前台二维码提成录入!O5*$E5 -> 1.5 | ... AL5: =前台二维码提成录入!AL5*$E5 -> 0
A6: 2 | B6: =前台二维码提成录入!B6 -> 李龙梅 | C6: =前台二维码提成录入!C6 -> 送物品 | D6: =前台二维码提成录入!D6 -> 次 | E6: =前台二维码提成录入!E6 -> 0.5 | F6: =前台二维码提成录入!F6 -> 63 | G6: =前台二维码提成录入!G6 -> 31.5 | H6: =前台二维码提成录入!H6*$E6 -> 0 | I6: =前台二维码提成录入!I6*$E6 -> 0 | J6: =前台二维码提成录入!J6*$E6 -> 5.5 | K6: =前台二维码提成录入!K6*$E6 -> 1 | L6: =前台二维码提成录入!L6*$E6 -> 1.5 | M6: =前台二维码提成录入!M6*$E6 -> 1.5 | N6: =前台二维码提成录入!N6*$E6 -> 0 | O6: =前台二维码提成录入!O6*$E6 -> 2.5 | ... AL6: =前台二维码提成录入!AL6*$E6 -> 1.5
A7: 3 | B7: =前台二维码提成录入!B7 -> 李龙梅 | C7: =前台二维码提成录入!C7 -> 点名表扬 | D7: =前台二维码提成录入!D7 -> 次 | E7: =前台二维码提成录入!E7 -> 1 | F7: =前台二维码提成录入!F7 -> 0 | G7: =前台二维码提成录入!G7 -> 0 | H7: =前台二维码提成录入!H7*$E7 -> 0 | I7: =前台二维码提成录入!I7*$E7 -> 0 | J7: =前台二维码提成录入!J7*$E7 -> 0 | K7: =前台二维码提成录入!K7*$E7 -> 0 | L7: =前台二维码提成录入!L7*$E7 -> 0 | M7: =前台二维码提成录入!M7*$E7 -> 0 | N7: =前台二维码提成录入!N7*$E7 -> 0 | O7: =前台二维码提成录入!O7*$E7 -> 0 | ... AL7: =前台二维码提成录入!AL7*$E7 -> 0
A8: 4 | B8: =前台二维码提成录入!B8 -> 李龙梅 | C8: =前台二维码提成录入!C8 -> 违规 | D8: =前台二维码提成录入!D8 -> 次 | E8: =前台二维码提成录入!E8 -> -2 | F8: =前台二维码提成录入!F8 -> 0 | G8: =前台二维码提成录入!G8 -> 0 | H8: =前台二维码提成录入!H8*$E8 -> 0 | I8: =前台二维码提成录入!I8*$E8 -> 0 | J8: =前台二维码提成录入!J8*$E8 -> 0 | K8: =前台二维码提成录入!K8*$E8 -> 0 | L8: =前台二维码提成录入!L8*$E8 -> 0 | M8: =前台二维码提成录入!M8*$E8 -> 0 | N8: =前台二维码提成录入!N8*$E8 -> 0 | O8: =前台二维码提成录入!O8*$E8 -> 0 | ... AL8: =前台二维码提成录入!AL8*$E8 -> 0
A9: 5 | B9: =前台二维码提成录入!B9 -> 李龙梅 | C9: =前台二维码提成录入!C9 -> 其他 | D9: =前台二维码提成录入!D9 -> 次 | E9: =前台二维码提成录入!E9 -> 2 | F9: =前台二维码提成录入!F9 -> 0 | G9: =前台二维码提成录入!G9 -> 0 | H9: =前台二维码提成录入!H9*$E9 -> 0 | I9: =前台二维码提成录入!I9*$E9 -> 0 | J9: =前台二维码提成录入!J9*$E9 -> 0 | K9: =前台二维码提成录入!K9*$E9 -> 0 | L9: =前台二维码提成录入!L9*$E9 -> 0 | M9: =前台二维码提成录入!M9*$E9 -> 0 | N9: =前台二维码提成录入!N9*$E9 -> 0 | O9: =前台二维码提成录入!O9*$E9 -> 0 | ... AL9: =前台二维码提成录入!AL9*$E9 -> 0
A10: 6 | B10: =前台二维码提成录入!B10 -> 于子杭 | C10: =前台二维码提成录入!C10 -> 洗衣 | D10: =前台二维码提成录入!D10 -> 次 | E10: =前台二维码提成录入!E10 -> 1.5 | F10: =前台二维码提成录入!F10 -> 0 | G10: =前台二维码提成录入!G10 -> 0 | H10: =前台二维码提成录入!H10*$E10 -> 0 | I10: =前台二维码提成录入!I10*$E10 -> 0 | J10: =前台二维码提成录入!J10*$E10 -> 0 | K10: =前台二维码提成录入!K10*$E10 -> 0 | L10: =前台二维码提成录入!L10*$E10 -> 0 | M10: =前台二维码提成录入!M10*$E10 -> 0 | N10: =前台二维码提成录入!N10*$E10 -> 0 | O10: =前台二维码提成录入!O10*$E10 -> 0 | ... AL10: =前台二维码提成录入!AL10*$E10 -> 0
A11: 7 | B11: =前台二维码提成录入!B11 -> 于子杭 | C11: =前台二维码提成录入!C11 -> 送物品 | D11: =前台二维码提成录入!D11 -> 次 | E11: =前台二维码提成录入!E11 -> 0.5 | F11: =前台二维码提成录入!F11 -> 67 | G11: =前台二维码提成录入!G11 -> 33.5 | H11: =前台二维码提成录入!H11*$E11 -> 0 | I11: =前台二维码提成录入!I11*$E11 -> 0 | J11: =前台二维码提成录入!J11*$E11 -> 5.5 | K11: =前台二维码提成录入!K11*$E11 -> 0 | L11: =前台二维码提成录入!L11*$E11 -> 1.5 | M11: =前台二维码提成录入!M11*$E11 -> 1.5 | N11: =前台二维码提成录入!N11*$E11 -> 0 | O11: =前台二维码提成录入!O11*$E11 -> 2.5 | ... AL11: =前台二维码提成录入!AL11*$E11 -> 1
A12: 8 | B12: =前台二维码提成录入!B12 -> 于子杭 | C12: =前台二维码提成录入!C12 -> 点名表扬 | D12: =前台二维码提成录入!D12 -> 次 | E12: =前台二维码提成录入!E12 -> 1 | F12: =前台二维码提成录入!F12 -> 0 | G12: =前台二维码提成录入!G12 -> 0 | H12: =前台二维码提成录入!H12*$E12 -> 0 | I12: =前台二维码提成录入!I12*$E12 -> 0 | J12: =前台二维码提成录入!J12*$E12 -> 0 | K12: =前台二维码提成录入!K12*$E12 -> 0 | L12: =前台二维码提成录入!L12*$E12 -> 0 | M12: =前台二维码提成录入!M12*$E12 -> 0 | N12: =前台二维码提成录入!N12*$E12 -> 0 | O12: =前台二维码提成录入!O12*$E12 -> 0 | ... AL12: =前台二维码提成录入!AL12*$E12 -> 0
A13: 9 | B13: =前台二维码提成录入!B13 -> 于子杭 | C13: =前台二维码提成录入!C13 -> 违规 | D13: =前台二维码提成录入!D13 -> 次 | E13: =前台二维码提成录入!E13 -> -2 | F13: =前台二维码提成录入!F13 -> 0 | G13: =前台二维码提成录入!G13 -> 0 | H13: =前台二维码提成录入!H13*$E13 -> 0 | I13: =前台二维码提成录入!I13*$E13 -> 0 | J13: =前台二维码提成录入!J13*$E13 -> 0 | K13: =前台二维码提成录入!K13*$E13 -> 0 | L13: =前台二维码提成录入!L13*$E13 -> 0 | M13: =前台二维码提成录入!M13*$E13 -> 0 | N13: =前台二维码提成录入!N13*$E13 -> 0 | O13: =前台二维码提成录入!O13*$E13 -> 0 | ... AL13: =前台二维码提成录入!AL13*$E13 -> 0
A14: 10 | B14: =前台二维码提成录入!B14 -> 于子杭 | C14: =前台二维码提成录入!C14 -> 其他 | D14: =前台二维码提成录入!D14 -> 次 | E14: =前台二维码提成录入!E14 -> 2 | F14: =前台二维码提成录入!F14 -> 0 | G14: =前台二维码提成录入!G14 -> 0 | H14: =前台二维码提成录入!H14*$E14 -> 0 | I14: =前台二维码提成录入!I14*$E14 -> 0 | J14: =前台二维码提成录入!J14*$E14 -> 0 | K14: =前台二维码提成录入!K14*$E14 -> 0 | L14: =前台二维码提成录入!L14*$E14 -> 0 | M14: =前台二维码提成录入!M14*$E14 -> 0 | N14: =前台二维码提成录入!N14*$E14 -> 0 | O14: =前台二维码提成录入!O14*$E14 -> 0 | ... AL14: =前台二维码提成录入!AL14*$E14 -> 0
A15: 11 | B15: =前台二维码提成录入!B15 -> 张馨月 | C15: =前台二维码提成录入!C15 -> 洗衣 | D15: =前台二维码提成录入!D15 -> 次 | E15: =前台二维码提成录入!E15 -> 1.5 | F15: =前台二维码提成录入!F15 -> 1 | G15: =前台二维码提成录入!G15 -> 1.5 | H15: =前台二维码提成录入!H15*$E15 -> 0 | I15: =前台二维码提成录入!I15*$E15 -> 0 | J15: =前台二维码提成录入!J15*$E15 -> 0 | K15: =前台二维码提成录入!K15*$E15 -> 0 | L15: =前台二维码提成录入!L15*$E15 -> 0 | M15: =前台二维码提成录入!M15*$E15 -> 0 | N15: =前台二维码提成录入!N15*$E15 -> 0 | O15: =前台二维码提成录入!O15*$E15 -> 0 | ... AL15: =前台二维码提成录入!AL15*$E15 -> 0
A16: 12 | B16: =前台二维码提成录入!B16 -> 张馨月 | C16: =前台二维码提成录入!C16 -> 送物品 | D16: =前台二维码提成录入!D16 -> 次 | E16: =前台二维码提成录入!E16 -> 0.5 | F16: =前台二维码提成录入!F16 -> 70 | G16: =前台二维码提成录入!G16 -> 35 | H16: =前台二维码提成录入!H16*$E16 -> 0 | I16: =前台二维码提成录入!I16*$E16 -> 0 | J16: =前台二维码提成录入!J16*$E16 -> 5.5 | K16: =前台二维码提成录入!K16*$E16 -> 1 | L16: =前台二维码提成录入!L16*$E16 -> 1.5 | M16: =前台二维码提成录入!M16*$E16 -> 1.5 | N16: =前台二维码提成录入!N16*$E16 -> 0 | O16: =前台二维码提成录入!O16*$E16 -> 2.5 | ... AL16: =前台二维码提成录入!AL16*$E16 -> 1
... A104: 100 | B104: =前台二维码提成录入!B104 -> 0 | C104: =前台二维码提成录入!C104 -> 0 | D104: =前台二维码提成录入!D104 -> 次 | E104: =前台二维码提成录入!E104 -> 0 | F104: =前台二维码提成录入!F104 -> 0 | G104: =前台二维码提成录入!G104 -> 0 | H104: =前台二维码提成录入!H104*$E104 -> 0 | I104: =前台二维码提成录入!I104*$E104 -> 0 | J104: =前台二维码提成录入!J104*$E104 -> 0 | K104: =前台二维码提成录入!K104*$E104 -> 0 | L104: =前台二维码提成录入!L104*$E104 -> 0 | M104: =前台二维码提成录入!M104*$E104 -> 0 | N104: =前台二维码提成录入!N104*$E104 -> 0 | O104: =前台二维码提成录入!O104*$E104 -> 0 | ... AL104: =前台二维码提成录入!AL104*$E104 -> 0
B105: =前台二维码提成录入!B105 -> 前台二维码提成 | C105: =前台二维码提成录入!C105 -> 0 | D105: =前台二维码提成录入!D105 -> 0 | E105: =前台二维码提成录入!E105 -> 0 | F105: =前台二维码提成录入!F105 -> 1006 | G105: =前台二维码提成录入!G105 -> 559 | H105: =SUM(H5:H104) -> 9 | I105: =SUM(I5:I104) -> 3 | J105: =SUM(J5:J104) -> 23.5 | K105: =SUM(K5:K104) -> 4.5 | L105: =SUM(L5:L104) -> 17 | M105: =SUM(M5:M104) -> 18 | N105: =SUM(N5:N104) -> 5.5 | O105: =SUM(O5:O104) -> 31 | ... AL105: =SUM(AL5:AL104) -> 13.5

Sheet 前台好评提成呈现
B1: 前台好评提成明细
B2: 酒店名称：
A3: 序号 | B3: 货品名称 | C3: 平台 | D3: 单位 | E3: 单价 | G3: 金额 | H3: 1号 | I3: 2号 | J3: 3号 | K3: 4号 | L3: 5号 | M3: 6号 | N3: 7号 | O3: 8号 | P3: 9号 | Q3: 10号 | R3: 11号 | S3: 12号 | T3: 13号 | U3: 14号 | V3: 15号 | W3: 16号 | X3: 17号 | Y3: 18号 | Z3: 19号 | AA3: 20号 | AB3: 21号 | AC3: 22号 | AD3: 23号 | AE3: 24号 | AF3: 25号 | AG3: 26号 | AH3: 27号 | AI3: 28号 | AJ3: 29号 | AK3: 30号 | AL3: 31号
F4: 好评数 | H4: 好评数 | I4: 好评数 | J4: 好评数 | K4: 好评数 | L4: 好评数 | M4: 好评数 | N4: 好评数 | O4: 好评数 | P4: 好评数 | Q4: 好评数 | R4: 好评数 | S4: 好评数 | T4: 好评数 | U4: 好评数 | V4: 好评数 | W4: 好评数 | X4: 好评数 | Y4: 好评数 | Z4: 好评数 | AA4: 好评数 | AB4: 好评数 | AC4: 好评数 | AD4: 好评数 | AE4: 好评数 | AF4: 好评数 | AG4: 好评数 | AH4: 好评数 | AI4: 好评数 | AJ4: 好评数 | AK4: 好评数 | AL4: 好评数
A5: 1 | B5: =前台好评提成录入!B5 -> 张馨月 | C5: =前台好评提成录入!C5 -> 携程 | D5: =前台好评提成录入!D5 -> 条 | E5: =前台好评提成录入!E5 -> 6 | F5: =前台好评提成录入!F5 -> 65 | G5: =前台好评提成录入!G5 -> 390 | H5: =前台好评提成录入!H5*$E5 -> 390 | I5: =前台好评提成录入!I5*$E5 -> 0 | J5: =前台好评提成录入!J5*$E5 -> 0 | K5: =前台好评提成录入!K5*$E5 -> 0 | L5: =前台好评提成录入!L5*$E5 -> 0 | M5: =前台好评提成录入!M5*$E5 -> 0 | N5: =前台好评提成录入!N5*$E5 -> 0 | O5: =前台好评提成录入!O5*$E5 -> 0 | ... AL5: =前台好评提成录入!AL5*$E5 -> 0
A6: 2 | B6: =前台好评提成录入!B8 -> 张馨月 | C6: =前台好评提成录入!C8 -> 去哪儿 | D6: =前台好评提成录入!D8 -> 条 | E6: =前台好评提成录入!E8 -> 6 | F6: =前台好评提成录入!F8 -> 0 | G6: =前台好评提成录入!G8 -> 0 | H6: =前台好评提成录入!H8*$E6 -> 0 | I6: =前台好评提成录入!I8*$E6 -> 0 | J6: =前台好评提成录入!J8*$E6 -> 0 | K6: =前台好评提成录入!K8*$E6 -> 0 | L6: =前台好评提成录入!L8*$E6 -> 0 | M6: =前台好评提成录入!M8*$E6 -> 0 | N6: =前台好评提成录入!N8*$E6 -> 0 | O6: =前台好评提成录入!O8*$E6 -> 0 | ... AL6: =前台好评提成录入!AL8*$E6 -> 0
A7: 3 | B7: =前台好评提成录入!B9 -> 张馨月 | C7: =前台好评提成录入!C9 -> 同程 | D7: =前台好评提成录入!D9 -> 条 | E7: =前台好评提成录入!E9 -> 6 | F7: =前台好评提成录入!F9 -> 0 | G7: =前台好评提成录入!G9 -> 0 | H7: =前台好评提成录入!H9*$E7 -> 0 | I7: =前台好评提成录入!I9*$E7 -> 0 | J7: =前台好评提成录入!J9*$E7 -> 0 | K7: =前台好评提成录入!K9*$E7 -> 0 | L7: =前台好评提成录入!L9*$E7 -> 0 | M7: =前台好评提成录入!M9*$E7 -> 0 | N7: =前台好评提成录入!N9*$E7 -> 0 | O7: =前台好评提成录入!O9*$E7 -> 0 | ... AL7: =前台好评提成录入!AL9*$E7 -> 0
A8: 4 | B8: =前台好评提成录入!B10 -> 张馨月 | C8: =前台好评提成录入!C10 -> 智行 | D8: =前台好评提成录入!D10 -> 条 | E8: =前台好评提成录入!E10 -> 6 | F8: =前台好评提成录入!F10 -> 0 | G8: =前台好评提成录入!G10 -> 0 | H8: =前台好评提成录入!H10*$E8 -> 0 | I8: =前台好评提成录入!I10*$E8 -> 0 | J8: =前台好评提成录入!J10*$E8 -> 0 | K8: =前台好评提成录入!K10*$E8 -> 0 | L8: =前台好评提成录入!L10*$E8 -> 0 | M8: =前台好评提成录入!M10*$E8 -> 0 | N8: =前台好评提成录入!N10*$E8 -> 0 | O8: =前台好评提成录入!O10*$E8 -> 0 | ... AL8: =前台好评提成录入!AL10*$E8 -> 0
A9: 5 | B9: =前台好评提成录入!B11 -> 张馨月 | C9: =前台好评提成录入!C11 -> 抖音 | D9: =前台好评提成录入!D11 -> 条 | E9: =前台好评提成录入!E11 -> 6 | F9: =前台好评提成录入!F11 -> 0 | G9: =前台好评提成录入!G11 -> 0 | H9: =前台好评提成录入!H11*$E9 -> 0 | I9: =前台好评提成录入!I11*$E9 -> 0 | J9: =前台好评提成录入!J11*$E9 -> 0 | K9: =前台好评提成录入!K11*$E9 -> 0 | L9: =前台好评提成录入!L11*$E9 -> 0 | M9: =前台好评提成录入!M11*$E9 -> 0 | N9: =前台好评提成录入!N11*$E9 -> 0 | O9: =前台好评提成录入!O11*$E9 -> 0 | ... AL9: =前台好评提成录入!AL11*$E9 -> 0
A10: 6 | B10: =前台好评提成录入!B12 -> 张馨月 | C10: =前台好评提成录入!C12 -> 美团 | D10: =前台好评提成录入!D12 -> 条 | E10: =前台好评提成录入!E12 -> 6 | F10: =前台好评提成录入!F12 -> 1 | G10: =前台好评提成录入!G12 -> 6 | H10: =前台好评提成录入!H12*$E10 -> 6 | I10: =前台好评提成录入!I12*$E10 -> 0 | J10: =前台好评提成录入!J12*$E10 -> 0 | K10: =前台好评提成录入!K12*$E10 -> 0 | L10: =前台好评提成录入!L12*$E10 -> 0 | M10: =前台好评提成录入!M12*$E10 -> 0 | N10: =前台好评提成录入!N12*$E10 -> 0 | O10: =前台好评提成录入!O12*$E10 -> 0 | ... AL10: =前台好评提成录入!AL12*$E10 -> 0
A11: 7 | B11: =前台好评提成录入!B13 -> 张馨月 | C11: =前台好评提成录入!C13 -> 飞猪 | D11: =前台好评提成录入!D13 -> 条 | E11: =前台好评提成录入!E13 -> 6 | F11: =前台好评提成录入!F13 -> 0 | G11: =前台好评提成录入!G13 -> 0 | H11: =前台好评提成录入!H13*$E11 -> 0 | I11: =前台好评提成录入!I13*$E11 -> 0 | J11: =前台好评提成录入!J13*$E11 -> 0 | K11: =前台好评提成录入!K13*$E11 -> 0 | L11: =前台好评提成录入!L13*$E11 -> 0 | M11: =前台好评提成录入!M13*$E11 -> 0 | N11: =前台好评提成录入!N13*$E11 -> 0 | O11: =前台好评提成录入!O13*$E11 -> 0 | ... AL11: =前台好评提成录入!AL13*$E11 -> 0
A12: 8 | B12: =前台好评提成录入!B16 -> 徐嘉瑜 | C12: =前台好评提成录入!C16 -> 携程优质 | D12: =前台好评提成录入!D16 -> 条 | E12: =前台好评提成录入!E16 -> 15 | F12: =前台好评提成录入!F16 -> 1 | G12: =前台好评提成录入!G16 -> 15 | H12: =前台好评提成录入!H16*$E12 -> 15 | I12: =前台好评提成录入!I16*$E12 -> 0 | J12: =前台好评提成录入!J16*$E12 -> 0 | K12: =前台好评提成录入!K16*$E12 -> 0 | L12: =前台好评提成录入!L16*$E12 -> 0 | M12: =前台好评提成录入!M16*$E12 -> 0 | N12: =前台好评提成录入!N16*$E12 -> 0 | O12: =前台好评提成录入!O16*$E12 -> 0 | ... AL12: =前台好评提成录入!AL16*$E12 -> 0
A13: 9 | B13: =前台好评提成录入!B17 -> 徐嘉瑜 | C13: =前台好评提成录入!C17 -> 黑/金优质 | D13: =前台好评提成录入!D17 -> 条 | E13: =前台好评提成录入!E17 -> 30 | F13: =前台好评提成录入!F17 -> 0 | G13: =前台好评提成录入!G17 -> 0 | H13: =前台好评提成录入!H17*$E13 -> 0 | I13: =前台好评提成录入!I17*$E13 -> 0 | J13: =前台好评提成录入!J17*$E13 -> 0 | K13: =前台好评提成录入!K17*$E13 -> 0 | L13: =前台好评提成录入!L17*$E13 -> 0 | M13: =前台好评提成录入!M17*$E13 -> 0 | N13: =前台好评提成录入!N17*$E13 -> 0 | O13: =前台好评提成录入!O17*$E13 -> 0 | ... AL13: =前台好评提成录入!AL17*$E13 -> 0
A14: 10 | B14: =前台好评提成录入!B18 -> 徐嘉瑜 | C14: =前台好评提成录入!C18 -> 去哪儿 | D14: =前台好评提成录入!D18 -> 条 | E14: =前台好评提成录入!E18 -> 5 | F14: =前台好评提成录入!F18 -> 0 | G14: =前台好评提成录入!G18 -> 0 | H14: =前台好评提成录入!H18*$E14 -> 0 | I14: =前台好评提成录入!I18*$E14 -> 0 | J14: =前台好评提成录入!J18*$E14 -> 0 | K14: =前台好评提成录入!K18*$E14 -> 0 | L14: =前台好评提成录入!L18*$E14 -> 0 | M14: =前台好评提成录入!M18*$E14 -> 0 | N14: =前台好评提成录入!N18*$E14 -> 0 | O14: =前台好评提成录入!O18*$E14 -> 0 | ... AL14: =前台好评提成录入!AL18*$E14 -> 0
A15: 11 | B15: =前台好评提成录入!B19 -> 徐嘉瑜 | C15: =前台好评提成录入!C19 -> 同程 | D15: =前台好评提成录入!D19 -> 条 | E15: =前台好评提成录入!E19 -> 5 | F15: =前台好评提成录入!F19 -> 1 | G15: =前台好评提成录入!G19 -> 5 | H15: =前台好评提成录入!H19*$E15 -> 5 | I15: =前台好评提成录入!I19*$E15 -> 0 | J15: =前台好评提成录入!J19*$E15 -> 0 | K15: =前台好评提成录入!K19*$E15 -> 0 | L15: =前台好评提成录入!L19*$E15 -> 0 | M15: =前台好评提成录入!M19*$E15 -> 0 | N15: =前台好评提成录入!N19*$E15 -> 0 | O15: =前台好评提成录入!O19*$E15 -> 0 | ... AL15: =前台好评提成录入!AL19*$E15 -> 0
A16: 12 | B16: =前台好评提成录入!B20 -> 徐嘉瑜 | C16: =前台好评提成录入!C20 -> 智行 | D16: =前台好评提成录入!D20 -> 条 | E16: =前台好评提成录入!E20 -> 5 | F16: =前台好评提成录入!F20 -> 0 | G16: =前台好评提成录入!G20 -> 0 | H16: =前台好评提成录入!H20*$E16 -> 0 | I16: =前台好评提成录入!I20*$E16 -> 0 | J16: =前台好评提成录入!J20*$E16 -> 0 | K16: =前台好评提成录入!K20*$E16 -> 0 | L16: =前台好评提成录入!L20*$E16 -> 0 | M16: =前台好评提成录入!M20*$E16 -> 0 | N16: =前台好评提成录入!N20*$E16 -> 0 | O16: =前台好评提成录入!O20*$E16 -> 0 | ... AL16: =前台好评提成录入!AL20*$E16 -> 0
A17: 13 | B17: =前台好评提成录入!B21 -> 徐嘉瑜 | C17: =前台好评提成录入!C21 -> 抖音 | D17: =前台好评提成录入!D21 -> 条 | E17: =前台好评提成录入!E21 -> 5 | F17: =前台好评提成录入!F21 -> 2 | G17: =前台好评提成录入!G21 -> 10 | H17: =前台好评提成录入!H21*$E17 -> 10 | I17: =前台好评提成录入!I21*$E17 -> 0 | J17: =前台好评提成录入!J21*$E17 -> 0 | K17: =前台好评提成录入!K21*$E17 -> 0 | L17: =前台好评提成录入!L21*$E17 -> 0 | M17: =前台好评提成录入!M21*$E17 -> 0 | N17: =前台好评提成录入!N21*$E17 -> 0 | O17: =前台好评提成录入!O21*$E17 -> 0 | ... AL17: =前台好评提成录入!AL21*$E17 -> 0
A18: 14 | B18: =前台好评提成录入!B22 -> 徐嘉瑜 | C18: =前台好评提成录入!C22 -> 美团 | D18: =前台好评提成录入!D22 -> 条 | E18: =前台好评提成录入!E22 -> 5 | F18: =前台好评提成录入!F22 -> 20 | G18: =前台好评提成录入!G22 -> 100 | H18: =前台好评提成录入!H22*$E18 -> 100 | I18: =前台好评提成录入!I22*$E18 -> 0 | J18: =前台好评提成录入!J22*$E18 -> 0 | K18: =前台好评提成录入!K22*$E18 -> 0 | L18: =前台好评提成录入!L22*$E18 -> 0 | M18: =前台好评提成录入!M22*$E18 -> 0 | N18: =前台好评提成录入!N22*$E18 -> 0 | O18: =前台好评提成录入!O22*$E18 -> 0 | ... AL18: =前台好评提成录入!AL22*$E18 -> 0
A19: 15 | B19: =前台好评提成录入!B23 -> 徐嘉瑜 | C19: =前台好评提成录入!C23 -> 飞猪 | D19: =前台好评提成录入!D23 -> 条 | E19: =前台好评提成录入!E23 -> 5 | F19: =前台好评提成录入!F23 -> 1 | G19: =前台好评提成录入!G23 -> 5 | H19: =前台好评提成录入!H23*$E19 -> 5 | I19: =前台好评提成录入!I23*$E19 -> 0 | J19: =前台好评提成录入!J23*$E19 -> 0 | K19: =前台好评提成录入!K23*$E19 -> 0 | L19: =前台好评提成录入!L23*$E19 -> 0 | M19: =前台好评提成录入!M23*$E19 -> 0 | N19: =前台好评提成录入!N23*$E19 -> 0 | O19: =前台好评提成录入!O23*$E19 -> 0 | ... AL19: =前台好评提成录入!AL23*$E19 -> 0
A20: 16 | B20: =前台好评提成录入!B24 -> 徐嘉瑜 | C20: =前台好评提成录入!C24 -> 官网 | D20: =前台好评提成录入!D24 -> 条 | E20: =前台好评提成录入!E24 -> 5 | F20: =前台好评提成录入!F24 -> 7 | G20: =前台好评提成录入!G24 -> 35 | H20: =前台好评提成录入!H24*$E20 -> 35 | I20: =前台好评提成录入!I24*$E20 -> 0 | J20: =前台好评提成录入!J24*$E20 -> 0 | K20: =前台好评提成录入!K24*$E20 -> 0 | L20: =前台好评提成录入!L24*$E20 -> 0 | M20: =前台好评提成录入!M24*$E20 -> 0 | N20: =前台好评提成录入!N24*$E20 -> 0 | O20: =前台好评提成录入!O24*$E20 -> 0 | ... AL20: =前台好评提成录入!AL24*$E20 -> 0
A21: 17 | B21: =前台好评提成录入!B25 -> 王增 | C21: =前台好评提成录入!C25 -> 携程 | D21: =前台好评提成录入!D25 -> 条 | E21: =前台好评提成录入!E25 -> 5 | F21: =前台好评提成录入!F25 -> 0 | G21: =前台好评提成录入!G25 -> 0 | H21: =前台好评提成录入!H25*$E21 -> 0 | I21: =前台好评提成录入!I25*$E21 -> 0 | J21: =前台好评提成录入!J25*$E21 -> 0 | K21: =前台好评提成录入!K25*$E21 -> 0 | L21: =前台好评提成录入!L25*$E21 -> 0 | M21: =前台好评提成录入!M25*$E21 -> 0 | N21: =前台好评提成录入!N25*$E21 -> 0 | O21: =前台好评提成录入!O25*$E21 -> 0 | ... AL21: =前台好评提成录入!AL25*$E21 -> 0
A22: 18 | B22: =前台好评提成录入!B27 -> 王增 | C22: =前台好评提成录入!C27 -> 黑/金优质 | D22: =前台好评提成录入!D27 -> 条 | E22: =前台好评提成录入!E27 -> 30 | F22: =前台好评提成录入!F27 -> 1 | G22: =前台好评提成录入!G27 -> 30 | H22: =前台好评提成录入!H27*$E22 -> 30 | I22: =前台好评提成录入!I27*$E22 -> 0 | J22: =前台好评提成录入!J27*$E22 -> 0 | K22: =前台好评提成录入!K27*$E22 -> 0 | L22: =前台好评提成录入!L27*$E22 -> 0 | M22: =前台好评提成录入!M27*$E22 -> 0 | N22: =前台好评提成录入!N27*$E22 -> 0 | O22: =前台好评提成录入!O27*$E22 -> 0 | ... AL22: =前台好评提成录入!AL27*$E22 -> 0
A23: 19 | B23: =前台好评提成录入!B28 -> 王增 | C23: =前台好评提成录入!C28 -> 去哪儿 | D23: =前台好评提成录入!D28 -> 条 | E23: =前台好评提成录入!E28 -> 5 | F23: =前台好评提成录入!F28 -> 4 | G23: =前台好评提成录入!G28 -> 20 | H23: =前台好评提成录入!H28*$E23 -> 20 | I23: =前台好评提成录入!I28*$E23 -> 0 | J23: =前台好评提成录入!J28*$E23 -> 0 | K23: =前台好评提成录入!K28*$E23 -> 0 | L23: =前台好评提成录入!L28*$E23 -> 0 | M23: =前台好评提成录入!M28*$E23 -> 0 | N23: =前台好评提成录入!N28*$E23 -> 0 | O23: =前台好评提成录入!O28*$E23 -> 0 | ... AL23: =前台好评提成录入!AL28*$E23 -> 0
A24: 20 | B24: =前台好评提成录入!B29 -> 王增 | C24: =前台好评提成录入!C29 -> 同程 | D24: =前台好评提成录入!D29 -> 条 | E24: =前台好评提成录入!E29 -> 5 | F24: =前台好评提成录入!F29 -> 1 | G24: =前台好评提成录入!G29 -> 5 | H24: =前台好评提成录入!H29*$E24 -> 5 | I24: =前台好评提成录入!I29*$E24 -> 0 | J24: =前台好评提成录入!J29*$E24 -> 0 | K24: =前台好评提成录入!K29*$E24 -> 0 | L24: =前台好评提成录入!L29*$E24 -> 0 | M24: =前台好评提成录入!M29*$E24 -> 0 | N24: =前台好评提成录入!N29*$E24 -> 0 | O24: =前台好评提成录入!O29*$E24 -> 0 | ... AL24: =前台好评提成录入!AL29*$E24 -> 0
A25: 21 | B25: =前台好评提成录入!B30 -> 王增 | C25: =前台好评提成录入!C30 -> 智行 | D25: =前台好评提成录入!D30 -> 条 | E25: =前台好评提成录入!E30 -> 5 | F25: =前台好评提成录入!F30 -> 0 | G25: =前台好评提成录入!G30 -> 0 | H25: =前台好评提成录入!H30*$E25 -> 0 | I25: =前台好评提成录入!I30*$E25 -> 0 | J25: =前台好评提成录入!J30*$E25 -> 0 | K25: =前台好评提成录入!K30*$E25 -> 0 | L25: =前台好评提成录入!L30*$E25 -> 0 | M25: =前台好评提成录入!M30*$E25 -> 0 | N25: =前台好评提成录入!N30*$E25 -> 0 | O25: =前台好评提成录入!O30*$E25 -> 0 | ... AL25: =前台好评提成录入!AL30*$E25 -> 0
A26: 22 | B26: =前台好评提成录入!B31 -> 王增 | C26: =前台好评提成录入!C31 -> 抖音 | D26: =前台好评提成录入!D31 -> 条 | E26: =前台好评提成录入!E31 -> 5 | F26: =前台好评提成录入!F31 -> 14 | G26: =前台好评提成录入!G31 -> 70 | H26: =前台好评提成录入!H31*$E26 -> 70 | I26: =前台好评提成录入!I31*$E26 -> 0 | J26: =前台好评提成录入!J31*$E26 -> 0 | K26: =前台好评提成录入!K31*$E26 -> 0 | L26: =前台好评提成录入!L31*$E26 -> 0 | M26: =前台好评提成录入!M31*$E26 -> 0 | N26: =前台好评提成录入!N31*$E26 -> 0 | O26: =前台好评提成录入!O31*$E26 -> 0 | ... AL26: =前台好评提成录入!AL31*$E26 -> 0
A27: 23 | B27: =前台好评提成录入!B32 -> 王增 | C27: =前台好评提成录入!C32 -> 美团 | D27: =前台好评提成录入!D32 -> 条 | E27: =前台好评提成录入!E32 -> 5 | F27: =前台好评提成录入!F32 -> 50 | G27: =前台好评提成录入!G32 -> 250 | H27: =前台好评提成录入!H32*$E27 -> 250 | I27: =前台好评提成录入!I32*$E27 -> 0 | J27: =前台好评提成录入!J32*$E27 -> 0 | K27: =前台好评提成录入!K32*$E27 -> 0 | L27: =前台好评提成录入!L32*$E27 -> 0 | M27: =前台好评提成录入!M32*$E27 -> 0 | N27: =前台好评提成录入!N32*$E27 -> 0 | O27: =前台好评提成录入!O32*$E27 -> 0 | ... AL27: =前台好评提成录入!AL32*$E27 -> 0
A28: 24 | B28: =前台好评提成录入!B33 -> 王增 | C28: =前台好评提成录入!C33 -> 飞猪 | D28: =前台好评提成录入!D33 -> 条 | E28: =前台好评提成录入!E33 -> 5 | F28: =前台好评提成录入!F33 -> 1 | G28: =前台好评提成录入!G33 -> 5 | H28: =前台好评提成录入!H33*$E28 -> 5 | I28: =前台好评提成录入!I33*$E28 -> 0 | J28: =前台好评提成录入!J33*$E28 -> 0 | K28: =前台好评提成录入!K33*$E28 -> 0 | L28: =前台好评提成录入!L33*$E28 -> 0 | M28: =前台好评提成录入!M33*$E28 -> 0 | N28: =前台好评提成录入!N33*$E28 -> 0 | O28: =前台好评提成录入!O33*$E28 -> 0 | ... AL28: =前台好评提成录入!AL33*$E28 -> 0
A29: 25 | B29: =前台好评提成录入!B34 -> 王增 | C29: =前台好评提成录入!C34 -> 官网 | D29: =前台好评提成录入!D34 -> 条 | E29: =前台好评提成录入!E34 -> 5 | F29: =前台好评提成录入!F34 -> 26 | G29: =前台好评提成录入!G34 -> 130 | H29: =前台好评提成录入!H34*$E29 -> 130 | I29: =前台好评提成录入!I34*$E29 -> 0 | J29: =前台好评提成录入!J34*$E29 -> 0 | K29: =前台好评提成录入!K34*$E29 -> 0 | L29: =前台好评提成录入!L34*$E29 -> 0 | M29: =前台好评提成录入!M34*$E29 -> 0 | N29: =前台好评提成录入!N34*$E29 -> 0 | O29: =前台好评提成录入!O34*$E29 -> 0 | ... AL29: =前台好评提成录入!AL34*$E29 -> 0
A30: 26 | B30: =前台好评提成录入!B35 -> 翟芮瑶 | C30: =前台好评提成录入!C35 -> 携程 | D30: =前台好评提成录入!D35 -> 条 | E30: =前台好评提成录入!E35 -> 5 | F30: =前台好评提成录入!F35 -> 2 | G30: =前台好评提成录入!G35 -> 10 | H30: =前台好评提成录入!H35*$E30 -> 10 | I30: =前台好评提成录入!I35*$E30 -> 0 | J30: =前台好评提成录入!J35*$E30 -> 0 | K30: =前台好评提成录入!K35*$E30 -> 0 | L30: =前台好评提成录入!L35*$E30 -> 0 | M30: =前台好评提成录入!M35*$E30 -> 0 | N30: =前台好评提成录入!N35*$E30 -> 0 | O30: =前台好评提成录入!O35*$E30 -> 0 | ... AL30: =前台好评提成录入!AL35*$E30 -> 0
A31: 27 | B31: =前台好评提成录入!B36 -> 翟芮瑶 | C31: =前台好评提成录入!C36 -> 携程优质 | D31: =前台好评提成录入!D36 -> 条 | E31: =前台好评提成录入!E36 -> 15 | F31: =前台好评提成录入!F36 -> 7 | G31: =前台好评提成录入!G36 -> 105 | H31: =前台好评提成录入!H36*$E31 -> 105 | I31: =前台好评提成录入!I36*$E31 -> 0 | J31: =前台好评提成录入!J36*$E31 -> 0 | K31: =前台好评提成录入!K36*$E31 -> 0 | L31: =前台好评提成录入!L36*$E31 -> 0 | M31: =前台好评提成录入!M36*$E31 -> 0 | N31: =前台好评提成录入!N36*$E31 -> 0 | O31: =前台好评提成录入!O36*$E31 -> 0 | ... AL31: =前台好评提成录入!AL36*$E31 -> 0
A32: 28 | B32: =前台好评提成录入!B37 -> 翟芮瑶 | C32: =前台好评提成录入!C37 -> 黑/金优质 | D32: =前台好评提成录入!D37 -> 条 | E32: =前台好评提成录入!E37 -> 30 | F32: =前台好评提成录入!F37 -> 2 | G32: =前台好评提成录入!G37 -> 60 | H32: =前台好评提成录入!H37*$E32 -> 60 | I32: =前台好评提成录入!I37*$E32 -> 0 | J32: =前台好评提成录入!J37*$E32 -> 0 | K32: =前台好评提成录入!K37*$E32 -> 0 | L32: =前台好评提成录入!L37*$E32 -> 0 | M32: =前台好评提成录入!M37*$E32 -> 0 | N32: =前台好评提成录入!N37*$E32 -> 0 | O32: =前台好评提成录入!O37*$E32 -> 0 | ... AL32: =前台好评提成录入!AL37*$E32 -> 0
A33: 29 | B33: =前台好评提成录入!B38 -> 翟芮瑶 | C33: =前台好评提成录入!C38 -> 去哪儿 | D33: =前台好评提成录入!D38 -> 条 | E33: =前台好评提成录入!E38 -> 5 | F33: =前台好评提成录入!F38 -> 3 | G33: =前台好评提成录入!G38 -> 15 | H33: =前台好评提成录入!H38*$E33 -> 15 | I33: =前台好评提成录入!I38*$E33 -> 0 | J33: =前台好评提成录入!J38*$E33 -> 0 | K33: =前台好评提成录入!K38*$E33 -> 0 | L33: =前台好评提成录入!L38*$E33 -> 0 | M33: =前台好评提成录入!M38*$E33 -> 0 | N33: =前台好评提成录入!N38*$E33 -> 0 | O33: =前台好评提成录入!O38*$E33 -> 0 | ... AL33: =前台好评提成录入!AL38*$E33 -> 0
... A104: 100 | B104: =前台好评提成录入!B109 -> 0 | C104: =前台好评提成录入!C109 -> 0 | D104: =前台好评提成录入!D109 -> 条 | E104: =前台好评提成录入!E109 -> 0 | F104: =前台好评提成录入!F109 -> 0 | G104: =前台好评提成录入!G109 -> 0 | H104: =前台好评提成录入!H109*$E104 -> 0 | I104: =前台好评提成录入!I109*$E104 -> 0 | J104: =前台好评提成录入!J109*$E104 -> 0 | K104: =前台好评提成录入!K109*$E104 -> 0 | L104: =前台好评提成录入!L109*$E104 -> 0 | M104: =前台好评提成录入!M109*$E104 -> 0 | N104: =前台好评提成录入!N109*$E104 -> 0 | O104: =前台好评提成录入!O109*$E104 -> 0 | ... AL104: =前台好评提成录入!AL109*$E104 -> 0
B105: 前台好评提成 | F105: =SUMIF($H$4:$I$4,$F$4,$H105:$I105) -> 2266 | G105: =+E105*F105 -> 0 | H105: =SUM(H5:H104) -> 2266 | I105: =SUM(I5:I104) -> 0 | J105: =SUM(J5:J104) -> 0 | K105: =SUM(K5:K104) -> 0 | L105: =SUM(L5:L104) -> 0 | M105: =SUM(M5:M104) -> 0 | N105: =SUM(N5:N104) -> 0 | O105: =SUM(O5:O104) -> 0 | ... AL105: =SUM(AL5:AL104) -> 0

Sheet 会员卡提成呈现
B1: 前台会员卡提成明细
B2: 酒店名称：
A3: 序号 | B3: 货品名称 | C3: 平台 | D3: 单位 | E3: 单价 | G3: 出库金额 | H3: 1号 | I3: 2号 | J3: 3号 | K3: 4号 | L3: 5号 | M3: 6号 | N3: 7号 | O3: 8号 | P3: 9号 | Q3: 10号 | R3: 11号 | S3: 12号 | T3: 13号 | U3: 14号 | V3: 15号 | W3: 16号 | X3: 17号 | Y3: 18号 | Z3: 19号 | AA3: 20号 | AB3: 21号 | AC3: 22号 | AD3: 23号 | AE3: 24号 | AF3: 25号 | AG3: 26号 | AH3: 27号 | AI3: 28号 | AJ3: 29号 | AK3: 30号 | AL3: 31号
F4: 张数 | H4: 金额 | I4: 金额 | J4: 金额 | K4: 金额 | L4: 金额 | M4: 金额 | N4: 金额 | O4: 金额 | P4: 金额 | Q4: 金额 | R4: 金额 | S4: 金额 | T4: 金额 | U4: 金额 | V4: 金额 | W4: 金额 | X4: 金额 | Y4: 金额 | Z4: 金额 | AA4: 金额 | AB4: 金额 | AC4: 金额 | AD4: 金额 | AE4: 金额 | AF4: 金额 | AG4: 金额 | AH4: 金额 | AI4: 金额 | AJ4: 金额 | AK4: 金额 | AL4: 金额
A5: 1 | B5: =会员卡提成录入!B5 -> 李龙梅 | C5: =会员卡提成录入!C5 -> 金卡 | D5: =会员卡提成录入!D5 -> 张 | E5: =会员卡提成录入!E5 -> 11 | F5: =会员卡提成录入!F5 -> 0 | G5: =会员卡提成录入!G5 -> 0 | H5: =前台好评提成录入!H5*$E5 -> 715 | I5: =前台好评提成录入!I5*$E5 -> 0 | J5: =前台好评提成录入!J5*$E5 -> 0 | K5: =前台好评提成录入!K5*$E5 -> 0 | L5: =前台好评提成录入!L5*$E5 -> 0 | M5: =前台好评提成录入!M5*$E5 -> 0 | N5: =前台好评提成录入!N5*$E5 -> 0 | O5: =前台好评提成录入!O5*$E5 -> 0 | ... AL5: =前台好评提成录入!AL5*$E5 -> 0
